Workbook
Name OLE_LINK10: '(参考)第1期中期小項目別評価'!#REF!
Name OLE_LINK10: '①業務実績報告書 (表紙～Ⅲ) '!#REF!
Name OLE_LINK10: ④小項目別評価!#REF!
Name OLE_LINK21: '(参考)第1期中期小項目別評価'!#REF!
Name OLE_LINK21: '①業務実績報告書 (表紙～Ⅲ) '!#REF!
Name OLE_LINK21: ④小項目別評価!#REF!
Name OLE_LINK26: '①業務実績報告書 (表紙～Ⅲ) '!#REF!
Name OLE_LINK26: ④小項目別評価!#REF!
Name OLE_LINK5: '(参考)第1期中期小項目別評価'!#REF!
Name OLE_LINK5: '①業務実績報告書 (表紙～Ⅲ) '!#REF!
Name OLE_LINK5: ④小項目別評価!#REF!
Name OLE_LINK66: '①業務実績報告書 (表紙～Ⅲ) '!#REF!
Name OLE_LINK66: ④小項目別評価!#REF!
Name OLE_LINK81: '①業務実績報告書 (表紙～Ⅲ) '!#REF!
Name OLE_LINK81: ④小項目別評価!#REF!
Name OLE_LINK82: '①業務実績報告書 (表紙～Ⅲ) '!#REF!
Name OLE_LINK82: ④小項目別評価!#REF!
Name OLE_LINK91: '①業務実績報告書 (表紙～Ⅲ) '!#REF!
Name OLE_LINK91: ④小項目別評価!#REF!

Sheet ①業務実績報告書 (表紙～Ⅲ) 
B11: 公立大学法人福知山公立大学
B14: 令和７事業年度及び中期目標期間（４年終了時）の | J14: ←〇〇事業年度の表記
B17: 業務実績報告書（案）
B36: 令和８年６月
J50: ←〇〇年度の表記
J60: ←〇〇年度の表記
B83: １ 基本情報（令和７年５月１日現在）
B84: （１）法人名 | D84: 公立大学法人福知山公立大学
B85: （２）所在地 | D85: 京都府福知山市字堀3370番地
B86: （３）設立団体 | D86: 福知山市
B87: （４）設立根拠法 | D87: 地方独立行政法人法
B88: （５）設立認可年月日 | D88: 平成27年11月24日
B89: （６）設立登記年月日 | D89: 平成28年４月１日
B90: （７）資本金 | D90: 1,562,130,000円（全額 福知山市出資）
B91: （８）理事長（代表者） | D91: 川添 信介
B93: （９）法人の目的 | D93: この公立大学法人は、教育のまち福知山における「学びの拠点」として、地方独立行政法人法に基づき、大学を設置し、及び管理することにより、総合的な知識と専門的な学術を深く教授研究するとともに、地域協働型教育研究を積極的に展開することにより、地域に根ざし、世界を視野に活躍できる高度な知識及び技能を有する人材を育成し、北近畿地域の持続可能な地域社会の形成と地方創生に寄与することを目的とする。
B96: （10）法人の業務 | D96: ア 公立大学を設置し、これを運営すること。 イ 学生に対し、修学、進路選択及び心身の健康等に関する相談その他の援助を行うこと。 ウ 法人以外の者から委託を受け、又はこれと共同して行う研究の実施その他の法人以外の者との連携による教育研究活動 を行うこと。 エ 地域の生涯学習の充実に資する多様な学習機会を提供すること。 オ 公立大学における教育研究成果の普及及び活用を通じ、地域社会及び国際社会に貢献すること。 カ 前各号の業務に附帯する業務を行うこと。
B98: （11）基本理念 | D98: 市民の大学、地域のための大学、世界とともに歩む大学
B100: ２ 設置する大学の学部・研究科の構成（令和７年５月１日現在）
B109: ３ 組織、運営体制 | E109: ５ 組織図（令和７年８月26日現在）
B110: （１）役員（令和７年４月１日現在）
B111: 理事長（学長） 川添 信介
B112: 理事（副学長） 西田 豊明
B113: 理事（副学長） 倉田 良樹
B114: 理事（非常勤） 柴田 洋三郎
B115: 理事（非常勤） 仁張 直敏
B116: 理事（非常勤） 三浦 和幸
B117: 監事（非常勤） 小嶋 勝
B118: 監事（非常勤） 西垣 秀照
B120: （２）専任教職員数（令和７年５月１日現在）
B121: 教員 教授 24人（地域経営学部12人、情報学部11人、
B122: 地域防災研究センター１人）
... B159: 法人による自己評価
B160: 令和７事業年度及び第２期中期目標期間（４年終了時）に係る業務実績報告書における自己評価は、以下の基準により実施する。 | J160: ←〇〇事業年度の表記
B161: ①小項目別評価
B162: 年度計画（中期計画）の記載項目（小項目）ごとの進捗状況の自己評価を行い、業務実績報告書において、次の４段階により進捗状況を示すとともに、
B163: 自己評価の判断理由（実施状況等）を記載する。
B165: ４･･･年度計画（中期計画）を上回って実施している（上回る実施状況）
B166: ３･･･年度計画（中期計画）を順調に実施している（十分な若しくは概ね実施）
B167: ２･･･年度計画（中期計画）を十分に実施できていない（下回る若しくは実施が不十分）
B168: １･･･年度計画（中期計画）を大幅に下回っている（特に劣る若しくは実施していない）
B170: ②大項目別評価
B171: 年度計画（中期計画）の小項目別評価及び特筆すべき事項（以下「特記事項」という。）を踏まえ、中期計画の事項（以下「大項目」という。）ごとに、
B172: 当該事業年度及び中期目標の期間の最後の事業年度の前々事業年度における中期目標の進捗状況について、次の４段階により進捗状況を示すとともに、
B173: 記述式により自己評価する。
B175: 中期計画の達成に向け 計画を上回って進捗し ている。
... B187: 中期計画の達成のため には進捗が著しく遅れ ており、重大な改善事項 がある。

Sheet ③評価（年度）
D1: ３ 小項目別評価
D2: （１）令和７事業年度の業務の実績に係る自己評価結果一覧表
D3: 大項目番号 | E3: 項目 | J3: 項目数 | S3: 平均値
K4: 4 | M4: 3 | O4: 2 | Q4: 1
K6: 年度計画を上回って実施している（上回る実施状況） | M6: 年度計画を順調に実施している（十分な若しくは概ね実施） | O6: 年度計画を十分に実施できていない（下回る若しくは実施が不十分） | Q6: 年度計画を大幅に下回っている（特に劣る若しくは実施していない）
D7: 1 | E7: 第４－１ 教育に関する目標を達成するための措置 | J7: =SUM(K7:R7) -> 31 | K7: 3 | M7: 28 | O7: 0 | Q7: 0 | S7: =ROUND((K7*4+M7*3+O7*2+Q7*1)/J7,1) -> 3.1
K8: =ROUND(K7/$J$7,3) -> 0.097 | M8: =ROUND(M7/$J$7,3) -> 0.903 | O8: =ROUND(O7/$J$7,3) -> 0 | Q8: =ROUND(Q7/$J$7,3) -> 0 | U8: =SUM(K8:R8) -> 1
D9: 2 | E9: 第４－２ 研究に関する目標を達成するための措置 | J9: =SUM(K9:R9) -> 11 | K9: 2 | M9: 9 | O9: 0 | Q9: 0 | S9: =ROUND((K9*4+M9*3+O9*2+Q9*1)/J9,1) -> 3.2
K10: =ROUND(K9/$J$9,3) -> 0.182 | M10: =ROUND(M9/$J$9,3) -> 0.818 | O10: =ROUND(O9/$J$9,3) -> 0 | Q10: =ROUND(Q9/$J$9,3) -> 0 | U10: =SUM(K10:R10) -> 1
D11: 3 | E11: 第４－３ 地域・社会貢献に関する目標を達成するための措置 | J11: =SUM(K11:R11) -> 10 | K11: 6 | M11: 4 | O11: 0 | Q11: 0 | S11: =ROUND((K11*4+M11*3+O11*2+Q11*1)/J11,1) -> 3.6
K12: =ROUND(K11/$J$11,3) -> 0.6 | M12: =ROUND(M11/$J$11,3) -> 0.4 | O12: =ROUND(O11/$J$11,3) -> 0 | Q12: =ROUND(Q11/$J$11,3) -> 0 | U12: =SUM(K12:R12) -> 1
D13: 4 | E13: 第５ 業務運営の改善及び効率化に関する目標を達成するための措置 | J13: =SUM(K13:R13) -> 7 | K13: 0 | M13: 7 | O13: 0 | Q13: 0 | S13: =ROUND((K13*4+M13*3+O13*2+Q13*1)/J13,1) -> 3
K14: =ROUND(K13/$J$13,3) -> 0 | M14: =ROUND(M13/$J$13,3) -> 1 | O14: =ROUND(O13/$J$13,3) -> 0 | Q14: =ROUND(Q13/$J$13,3) -> 0 | U14: =SUM(K14:R14) -> 1
D15: 5 | E15: 第６ 財務内容の改善に関する目標を達成するための措置 | J15: =SUM(K15:R15) -> 6 | K15: 0 | M15: 6 | O15: 0 | Q15: 0 | S15: =ROUND((K15*4+M15*3+O15*2+Q15*1)/J15,1) -> 3
K16: =ROUND(K15/$J$15,3) -> 0 | M16: =ROUND(M15/$J$15,3) -> 1 | O16: =ROUND(O15/$J$15,3) -> 0 | Q16: =ROUND(Q15/$J$15,3) -> 0 | U16: =SUM(K16:R16) -> 1
D17: 6 | E17: 第７ 自己点検・評価及び当該状況に係る情報の提供に関する目標を達成するための措置 | J17: =SUM(K17:R17) -> 2 | K17: 0 | M17: 2 | O17: 0 | Q17: 0 | S17: =ROUND((K17*4+M17*3+O17*2+Q17*1)/J17,1) -> 3
K18: =ROUND(K17/$J$17,3) -> 0 | M18: =ROUND(M17/$J$17,3) -> 1 | O18: =ROUND(O17/$J$17,3) -> 0 | Q18: =ROUND(Q17/$J$17,3) -> 0 | U18: =SUM(K18:R18) -> 1
D19: 7 | E19: 第８ その他業務運営に関する重要目標を達成するための措置 | J19: =SUM(K19:R19) -> 13 | K19: 1 | M19: 12 | O19: 0 | Q19: 0 | S19: =ROUND((K19*4+M19*3+O19*2+Q19*1)/J19,1) -> 3.1
K20: =ROUND(K19/$J$19,3) -> 0.077 | M20: =ROUND(M19/$J$19,3) -> 0.923 | O20: =ROUND(O19/$J$19,3) -> 0 | Q20: =ROUND(Q19/$J$19,3) -> 0 | U20: =SUM(K20:R20) -> 1
E21: 合計 | J21: =SUM(J7:J20) -> 80 | K21: =SUM(K7,K9,K11,K13,K15,K17,K19) -> 12 | M21: =SUM(M7,M9,M11,M13,M15,M17,M19) -> 68 | O21: =SUM(O7,O9,O11,O13,O15,O17,O19) -> 0 | Q21: =SUM(Q7,Q9,Q11,Q13,Q15,Q17,Q19) -> 0 | S21: =ROUND((K21*4+M21*3+O21*2+Q21*1)/J21,1) -> 3.2
K22: =ROUND(K21/$J$21,3) -> 0.15 | M22: =ROUND(M21/$J$21,3) -> 0.85 | O22: =ROUND(O21/$J$21,3) -> 0 | Q22: =ROUND(Q21/$J$21,3) -> 0 | U22: =SUM(K22:R22) -> 1
F71: ・令和元年度の志願時のアンケートでは志願のきっかけとして「高校教員」と記入したのが回答者の60.8％であり、例年の傾向からは変化はなかった。情報学部では「塾・予備校講師からのすすめ」との回答が数件見られた。また、高校教員からは、特に都市部の高校は塾・予備校の進路指導の影響が強いとの意見が聞かれたため、塾・予備校に対する資料送付や訪問を新たに行った（塾・予備校への訪問実績：18件）。新型コロナウイルス感染症の影響により訪問が難しい状況の中で、20校程度を訪問することができた。 ・社会貢献や地域貢献を兼ねた教員による出張講義は34回行った。 ・在学生の母校訪問については、新型コロナウイルス感染症の影響を考慮して在学生を募っていない。 ・1年次生を対象として入学後の新入生アンケートを実施した。これにより、本学に入学した学生の受験動向を把握した。

Sheet ③評価（中期）
D1: ３ 小項目別評価
D2: （２）中期目標期間（４年終了時）の業務の実績に係る自己評価結果一覧表
D3: 大項目番号 | E3: 項目 | J3: 項目数 | S3: 平均値
K4: 4 | M4: 3 | O4: 2 | Q4: 1
K6: 中期計画を上回って実施している（上回る実施状況） | M6: 中期計画を順調に実施している（十分な若しくは概ね実施） | O6: 中期計画を十分に実施できていない（下回る若しくは実施が不十分） | Q6: 中期計画を大幅に下回っている（特に劣る若しくは実施していない）
D7: 1 | E7: 第４－１ 教育に関する目標を達成するための措置 | J7: =SUM(K7:R7) -> 32 | K7: 5 | M7: 27 | O7: 0 | Q7: 0 | S7: =ROUND((K7*4+M7*3+O7*2+Q7*1)/J7,1) -> 3.2
K8: =ROUND(K7/$J$7,3) -> 0.156 | M8: =ROUND(M7/$J$7,3) -> 0.844 | O8: =ROUND(O7/$J$7,3) -> 0 | Q8: =ROUND(Q7/$J$7,3) -> 0 | U8: =SUM(K8:R8) -> 1
D9: 2 | E9: 第４－２ 研究に関する目標を達成するための措置 | J9: =SUM(K9:R9) -> 11 | K9: 2 | M9: 9 | O9: 0 | Q9: 0 | S9: =ROUND((K9*4+M9*3+O9*2+Q9*1)/J9,1) -> 3.2
K10: =ROUND(K9/$J$9,3) -> 0.182 | M10: =ROUND(M9/$J$9,3) -> 0.818 | O10: =ROUND(O9/$J$9,3) -> 0 | Q10: =ROUND(Q9/$J$9,3) -> 0 | U10: =SUM(K10:R10) -> 1
D11: 3 | E11: 第４－３ 地域・社会貢献に関する目標を達成するための措置 | J11: =SUM(K11:R11) -> 10 | K11: 6 | M11: 4 | O11: 0 | Q11: 0 | S11: =ROUND((K11*4+M11*3+O11*2+Q11*1)/J11,1) -> 3.6
K12: =ROUND(K11/$J$11,3) -> 0.6 | M12: =ROUND(M11/$J$11,3) -> 0.4 | O12: =ROUND(O11/$J$11,3) -> 0 | Q12: =ROUND(Q11/$J$11,3) -> 0 | U12: =SUM(K12:R12) -> 1
D13: 4 | E13: 第５ 業務運営の改善及び効率化に関する目標を達成するための措置 | J13: =SUM(K13:R13) -> 7 | K13: 0 | M13: 7 | O13: 0 | Q13: 0 | S13: =ROUND((K13*4+M13*3+O13*2+Q13*1)/J13,1) -> 3
K14: =ROUND(K13/$J$13,3) -> 0 | M14: =ROUND(M13/$J$13,3) -> 1 | O14: =ROUND(O13/$J$13,3) -> 0 | Q14: =ROUND(Q13/$J$13,3) -> 0 | U14: =SUM(K14:R14) -> 1
D15: 5 | E15: 第６ 財務内容の改善に関する目標を達成するための措置 | J15: =SUM(K15:R15) -> 6 | K15: 0 | M15: 6 | O15: 0 | Q15: 0 | S15: =ROUND((K15*4+M15*3+O15*2+Q15*1)/J15,1) -> 3
K16: =ROUND(K15/$J$15,3) -> 0 | M16: =ROUND(M15/$J$15,3) -> 1 | O16: =ROUND(O15/$J$15,3) -> 0 | Q16: =ROUND(Q15/$J$15,3) -> 0 | U16: =SUM(K16:R16) -> 1
D17: 6 | E17: 第７ 自己点検・評価及び当該状況に係る情報の提供に関する目標を達成するための措置 | J17: =SUM(K17:R17) -> 2 | K17: 0 | M17: 2 | O17: 0 | Q17: 0 | S17: =ROUND((K17*4+M17*3+O17*2+Q17*1)/J17,1) -> 3
K18: =ROUND(K17/$J$17,3) -> 0 | M18: =ROUND(M17/$J$17,3) -> 1 | O18: =ROUND(O17/$J$17,3) -> 0 | Q18: =ROUND(Q17/$J$17,3) -> 0 | U18: =SUM(K18:R18) -> 1
D19: 7 | E19: 第８ その他業務運営に関する重要目標を達成するための措置 | J19: =SUM(K19:R19) -> 14 | K19: 0 | M19: 14 | O19: 0 | Q19: 0 | S19: =ROUND((K19*4+M19*3+O19*2+Q19*1)/J19,1) -> 3
K20: =ROUND(K19/$J$19,3) -> 0 | M20: =ROUND(M19/$J$19,3) -> 1 | O20: =ROUND(O19/$J$19,3) -> 0 | Q20: =ROUND(Q19/$J$19,3) -> 0 | U20: =SUM(K20:R20) -> 1
E21: 合計 | J21: =SUM(J7:J20) -> 82 | K21: =SUM(K7,K9,K11,K13,K15,K17,K19) -> 13 | M21: =SUM(M7,M9,M11,M13,M15,M17,M19) -> 69 | O21: =SUM(O7,O9,O11,O13,O15,O17,O19) -> 0 | Q21: =SUM(Q7,Q9,Q11,Q13,Q15,Q17,Q19) -> 0 | S21: =ROUND((K21*4+M21*3+O21*2+Q21*1)/J21,1) -> 3.2
K22: =ROUND(K21/$J$21,3) -> 0.159 | M22: =ROUND(M21/$J$21,3) -> 0.841 | O22: =ROUND(O21/$J$21,3) -> 0 | Q22: =ROUND(Q21/$J$21,3) -> 0 | U22: =SUM(K22:R22) -> 1
F71: ・令和元年度の志願時のアンケートでは志願のきっかけとして「高校教員」と記入したのが回答者の60.8％であり、例年の傾向からは変化はなかった。情報学部では「塾・予備校講師からのすすめ」との回答が数件見られた。また、高校教員からは、特に都市部の高校は塾・予備校の進路指導の影響が強いとの意見が聞かれたため、塾・予備校に対する資料送付や訪問を新たに行った（塾・予備校への訪問実績：18件）。新型コロナウイルス感染症の影響により訪問が難しい状況の中で、20校程度を訪問することができた。 ・社会貢献や地域貢献を兼ねた教員による出張講義は34回行った。 ・在学生の母校訪問については、新型コロナウイルス感染症の影響を考慮して在学生を募っていない。 ・1年次生を対象として入学後の新入生アンケートを実施した。これにより、本学に入学した学生の受験動向を把握した。

Sheet ④小項目別評価
B1: （２）小項目別業務実績・自己評価結果
B2: 項 目 別 の 状 況
B4: 第４－１ 教育に関する目標 | G4: ※「業務の実績」における下線部分は、特筆事項とする。
B5: （１）教育の成果
B7: 中 期 目 標 | D7: ディプロマポリシー（学位授与方針）に基づき、グローバルな視野に立ち、高い専門性と論理的・批判的思考力や表現力、コミュニケーション力、そして生涯にわたり学び続ける力を涵養する。
B9: 中期計画 年度計画 番号 | C9: 中期計画 | D9: 業務の実績（中期計画） | E9: 自己評価 | F9: 年度計画 | G9: 業務の実績 | H9: 自己評価
B11: 第４－１ 教育に関する目標を達成するための措置
B12: （１）教育の成果
B13: 1 | C13: ・本学が共通教育と専門教育の両方によって育成すべき人材像として掲げる「グローカリスト」が持つべき具体的な資質・能力を、両学部が掲げる「学修のアウトカム」と関連付けてより明確に提示し、ディプロマポリシーだけでなく、アドミッションポリシー、カリキュラムポリシーにも反映させる。 | D13: 【令和４年度～令和７年度の総括】 ・地域経営学部では、令和４年度及び令和５年度の入学者には令和２年度カリキュラム、令和６年度及び令和７年度の入学者には令和６年度カリキュラムで教育を実施した。また、情報学部は令和２年４月に設置され、令和５年度に最初の卒業者を送り出すとともに、この４年間のカリキュラムを見直した令和６年度カリキュラムを実施してきた。このように各学部において教育の実施やカリキュラムの見直しを進める一方で、令和６年度及び令和７年度において、全学的なカリキュラムの再検討が別途なされた。その結果、両学部ともに令和８年度入学者より、新たな令和８年度カリキュラムで教育を実施することとなった。 ・この全学的なカリキュラムの再検討にあたり、本学が育成すべき人材像として掲げる「グローカリスト」育成を発展・深化させることによって、令和８年度の学士課程教育改編で、「情報学を基盤とした地域協働型教育」及び「汎用的学修能力育成」を二つの教育の柱として定めた。具体的には、「グローバル」な能力を、単なる国際交流や国際的知見の獲得にとどまらず、広く地球社会一般に通用する知見の創出や技術・方法論の開発・適用能力として再定義し、これを「汎用的学修能力」として育成することとした。なお、この能力は中期目標が掲げる「生涯にわたり学び続ける力」の基礎ともなる。他方、「ローカル」の側面を、データに基づき地域の実態を把握し、課題解決に取り組む実践的能力と定義し、「情報学を基盤とした地域協働型教育」を通じて育成することとした。上記の二つの方針を、全学及び両学部の三つのポリシー並びにかつての「学修のアウトカム」に相当する「学年ごとの到達目標」に一貫性を持って反映させた。 ・令和８年度カリキュラムを作成するにあたり、両学部の新しい三つのポリシーを作成するとともに、大学全体の三つのポリシーも新たに作成した。さらに、令和８年度から実施するカリキュラムの具体的内容について検討し、カリキュラムマップやカリキュラムツリーを策定するとともに、各科目の具体的授業概要を作成した。 【令和８年度・令和９年度の見込】 ・両学部及び基盤教育院において、令和８年度から適用する新しい教育方針に基づくカリキュラムを実施する。 ・地域経営学部では、上記に加え、基盤教育科目の学修成果を各専門教育科目及び卒業研究につなげる仕組みを構築する。 ・情報学部では、令和５年度入学者に対するカリキュラム、令和６年度、令和７年度入学者向けカリキュラム、そして令和８年度以降の入学者向けカリキュラムと三つのカリキュラムが並行した教育となるが、令和８年度のカリキュラムは、これまでの経緯を踏まえ、本学におけるディプロマ・ポリシー、カリキュラム・ポリシーをより明確に反映した改革であり、また、実施に向けた検討、準備も十分になされていることから大きな混乱はないと思われる。 | E13: 3 | F13: ・地域経営学部及び情報学部では、令和８年度から適用する新しい教育方針に基づくカリキュラムの実施に向けた準備を進める。 ・令和６年度までの成績にもとづき、両学部が掲げる「学修のアウトカム」について、カリキュラムマップに従い学生の「外国語科目群」、「一般教養科目群」における履修申請率、修得率、成績分布の把握・測定を行う。 | G13: ・学士課程教育刷新により、「情報学を基盤とした地域協働型教育」と「汎用的学修能力の育成」を教育の柱とし、新たに大学全体及び両学部のディプロマ・ポリシー（学位授与方針）、カリキュラム・ポリシー（教育課程編成・実施方針）、アドミッション・ポリシー（入学者受入方針）を決定し、令和8年度から実施する新たなカリキュラムを制定した。新しいカリキュラムにおいては、両学部ともに４年間を通じた学修プロセスを見直し、主要科目の設定、指導教員制度の導入等、令和８年度からの新カリキュラム実施に向け、それぞれ検討を行い、両学部の教授会において、以下のように検討状況やカリキュラムマップ等の報告・審議を重ね、令和８年４月からの実施に向けた準備を完了した。 【地域経営学部】 ①９月教授会：令和８年度カリキュラムの主旨について学長からの説明があり意見交換会を実施（Slackにおいても継続） ②10月教授会：令和６年度カリキュラム科目と令和８年度カリキュラム科目の読み替えについて審議 ③11月教授会：令和８年開講科目、担当者一覧について審議 ④12月教授会：令和８年開講科目、担当者一覧について審議し、授業概要が執行会議で承認・確定したことを報告 ⑤１月教授会：令和８年度カリキュラムにおける卒業研究の履修条件等について審議 【情報学部】 ①５月教授会：情報学部カリキュラムＷＧの設置を報告 ②８月教授会：令和８年度以降入学者のカリキュラムマップ及びカリキュラムツリー、情報専門基礎科目群（いずれも案）を報告、意見聴取 ③９月教授会：令和8年度カリキュラムの主旨について学長からの説明があり意見交換会を実施（Slackにおいても継続） ④10月教授会：2026カリキュラム実施WGからの提案（ＩＴ実習などの実習・演習の担当について、卒業研究の研究室配属・異動について）（Slackにおいても継続して意見交換） ⑤Slack審議：令和６年度カリキュラム科目と令和８年度カリキュラム科目の読み替えについて審議 ⑥11月教授会：令和８年開講科目、担当者一覧について審議 ⑦12月教授会：授業概要が執行会議で承認・確定したことを報告 ⑧１月教授会：卒業研究科目の履修条件について審議 なお、２月から３月にかけては、両学部において４月からのカリキュラム実施に向けてガイダンス資料の作成、授業資料の作成など具体的作業を行った。 ・令和２年度から令和６年度までの入学者の「外国語科目群」及び「一般教養科目群」の科目毎、入学年度毎、学部・学科毎の履修申請率、修得率を計測して比較するとともに、成績分布について、大学全体を母集団とした適合度の検定を行い、科目毎、入学年度毎、学部・学科毎の傾向を把握した。その結果、必修科目は履修申請率・修得率ともに高く、選択科目では履修状況に差が見られた。また、成績分布については、多くの科目で科目群全体とは異なる傾向が確認された。 | H13: 3
B16: 第４－１ 教育に関する目標
B17: （２）教育内容
B19: 中 期 目 標 | D19: カリキュラムポリシー（教育課程編成方針）に基づき、文理双方の学部間連携など大学の強みを活かし、教養教育から専門教育まで実践的でグローカルな学部教育を展開するとともに、社会情勢や地域ニーズなどを踏まえ、学部学科編成の最適化に取り組む。 また令和６年度を目処に、情報学部を中軸とした文理連携による地域協働型教育研究を展開するための新たな拠点となる大学院を設置して地域の発展を牽引する高度なＩＣＴ人材を育成する。
B21: 中期計画 年度計画 番号 | C21: 中期計画 | D21: 業務の実績（中期計画） | E21: 自己評価 | F21: 年度計画 | G21: 業務の実績 | H21: 自己評価
B23: 第４－１ 教育に関する目標を達成するための措置
B24: （２）教育内容
B25: 2 | C25: ①教育課程の編成
C26: ・地域経営学部については、「地域経営」の概念を整理して、「地域についての体系的な学修」ができるよう、教育内容の改善を行う。また、令和６年度に情報学部と共同で新たに設置を目指す大学院修士課程を視野に入れて、開講科目の再編成を行うとともに、これに合わせて教員組織のあり方を改善する。 | D26: 【令和４年度～令和７年度の総括】 ・地域経営学部では、学際的な特徴をもつ地域経営を公共経営、企業経営、交流観光、医療福祉経営という４系統から構成されるものとして概念を整理した。令和６年度から新たなカリキュラムを実施し、学部専門教育を４系統に沿って年次ごとに科目を配当している。系統ごとにカリキュラムマップとカリキュラムツリーを作成・公表し、学生の履修指導などにおいて活用することで地域経営の体系的な学修ができるよう、教育内容の改善を行った。大学院修士課程との接続を視野に入れた教育課程の具体的な編成内容については、大学院で開講される４科目（公共ガバナンス論、ベンチャー・アントレプレナーシップ論、経営学特論、地域福祉政策論）に接続する６科目（ガバナンス論、地域ベンチャー育成論（令和６年度カリキュラムにおけるベンチャー企業論）、経営組織論、人的資源管理論、介護福祉論（令和６年度カリキュラムにおける高齢者福祉論）、地域福祉論）を学部専門教育科目に設置した。また、令和６年度に設置した地域経営学部執行会議が、ディプロマ・ポリシー第５項に示した学修目標を達成するための授業の成果について、系統を展開する各学科及び学部全体の教学アセスメントを実施することで、教学マネジメントにおける組織的な対応力を強化した。 【令和８年度・令和９年度の見込】 ・令和６年度及び令和７年度に入学した学生に対し、ディプロマ・ポリシー及びカリキュラム・ポリシーに基づき、令和６年度カリキュラムの教育を実施する。 | E26: 3 | F26: ・地域経営学部では、学部専門教育を公共経営、企業経営、交流観光、医療福祉経営という４系統に沿って展開し、地域経営の体系的な学修を実現する。教員組織もこの４系統と対応する形で運営し、教学における組織的な対応力を強化する。 ・地域経営学部教員は、大学院では学部専門教育を深化・発展させた社会科学系科目と文理融合科目を担当し、学生が「地域社会に情報技術を還元するための実践活動に資する知識」を獲得できるようにする。 | G26: ・令和６年度から新たなカリキュラムを実施し、専門教育を４系統に沿って「学びを始める（初年次）」「学びを広げる（２年次）」「学びを深める（３年次）」「学びをまとめる（４年次）」という学年ごとの編成方針に基づき科目を配当している。これにより、座学による知識の伝授と地域現場における「地域協働型教育」を組み合わせることによって体系的な学修を実現するとともに、系統ごとにカリキュラムマップとカリキュラムツリーを作成・公表し、学生の履修指導などにおいて活用することで地域経営の体系的な学修を推進した。また、学部の教学について検討する目的で設置した地域経営学部執行会議の組織により、ディプロマポリシー第5項に示した学修目標を達成するための授業成果について、系統を展開する各学科及び学部全体の教学アセスメントを実施し、教学マネジメントにおける組織的な対応力を強化した。 ・地域経営学部では学士課程教育改編に伴い、令和８年度からさらに新しいカリキュラムによる教育を実施することになった。令和８年度以降の開講に向けて以下の点を中心に準備を進め、令和８年４月からの開講準備が整った。 ①科目担当者の割り当て（令和６年度カリキュラム科目担当とのすり合わせ） ②専門教育科目の科目群概要、科目概要、到達目標の確定 ③カリキュラムマップ・カリキュラムツリーの作成 ④令和８年度カリキュラムの令和６年度カリキュラム科目への読み替え ⑤担任制度及び指導教員制度の設計 ⑥卒業研究の評価の検討 ⑦令和８年度カリキュラムにおける「卒業研究Ⅰ～Ⅳ」の履修条件の設定 ⑧科目履修例（履修モデル）の設計 ⑨履修申請単位数の上限に含まれない科目や他学部学生による履修申請を認めない科目の設定 ・地域経営学部は、大学院地域情報学研究科において、地域社会に情報技術を還元するための実践活動に資する知識を修得するために配置している「文理融合科目」と「社会科学系科目」の科目担当および修士課程指導教員として新たに２人、兼任教員として配置した。 | H26: 3
B27: 3 | C27: ・情報学部については、令和５年度に完成年次を迎えることと令和６年度に地域経営学部と共同で設置する新たな大学院修士課程の設置予定を視野に入れて、令和６年度以降のカリキュラムポリシーを更新し、それに基づく教育課程の編成等を図る。 | D27: 【令和４年度～令和７年度の総括】 ・情報学部では、令和５年度に完成年次を迎え、令和６年度に地域経営学部と共同で設置する新たな大学院修士課程を設置した。大学院設置にあわせて令和６年度以降のカリキュラム・ポリシーを更新し、それに基づく教育課程を再編した。この見直しにおいては、４年間の実績を踏まえ、基礎技術力の充実と大学院の教育を見据えた専門知識、学修成果の向上を図ることをめざすものとし、以下のカリキュラム・ポリシーに変更した。 (カリキュラム・ポリシー) 下記の 4 つの側面からカリキュラムを編成し、座学と実践的学修を充実し、学修成果の向上を図る。 1. 帰納的な教育と実践的な学修を中心としたカリキュラムを編成する。本学の「地域協働型教育研究」を具体化した、プロジェクトベースの演習系科目等を配置し、地域社会における実践につながる教育を展開する。 2. 情報学の体系・知識・知見・技術を学びつつ、現場に応用・活用する「知」の総合化を図ることのできるカリキュラムを編成する。地域社会のさまざまな様相を理解し、社会に貢献できる人材を育成するために、地域関連科目を配置する。 3. 段階的に専門的な原理に近づいていくカリキュラムを編成する。専門科目を実践系科目、基盤系科目、理論系科目に分類するとともに実践から理論へと進む流れを基本とする。個々の概念間の関係や当該事例の中での位置づけを強く意識させることにより、堅固な基礎学力の獲得を図る。さらに、演習系科目である「プログラミング演習」「ＩＴ 実習」を１、２年次に配置し、基本技術力の獲得を図る。 4. 専門領域の知識習得、学修成果の向上を図るカリキュラムを編成する。数理・データサイエンス（データ解析やその活用について専門的に学習するトラック）、ＩＣＴ（情報システムの構築について専門的に学習するトラック）、人間・社会情報学（人間・社会が関わる様々な領域における情報技術について専門的に学習するトラック）を設ける。トラック別に高度な知識や知見を修得し、現場対応力の高い人材を育てる科目を配置する。 さらに、令和８年度からの全学的な学士教育課程改編に基づき、地域経営学部及び新たに設置される基盤教育院と連携した学部教育の実施を以下のような形で具現化した。 1. 基盤教育科目における「情報と社会」、「データサイエンス」などの両学の学生が共通に履修する情報科目群の設定 2. 「アカデミックリーディング」、「哲学」などの汎用的学修能力を育成するための基礎科目群の設定 3. 両学部の学生が同じグループで学びを進める地域協働演習の開講 【令和８年度・令和９年度の見込】 ・令和８年度は三つの異なる教育課程を並行して進めることとなったが、新たな教育課程は本学のディプロマ・ポリシー、カリキュラム・ポリシーをより明確に実装したものであり、また、その実施に向けての準備も順調に進められてきたことから、大きな混乱はないと考える。今後２年間についても、実施状況を詳細にチェックしていくことが重要と考える。 | E27: 3 | F27: 情報学部では、令和６年度開始のカリキュラムの実施状況を踏まえ、令和８年度開始のカリキュラムの開講準備を整える。 | G27: 情報学部では、令和５年度に完成年次を迎えてカリキュラムを再検討し、令和６年度から新しいカリキュラムでの教育を実施してきた。一方、学士課程教育改編に伴い、令和８年度からさらに新しいカリキュラムによる教育を実施することになった。令和６年度カリキュラムを進めながら、令和８年度からの新しいカリキュラム実施にむけてワーキンググループを設置し、開講準備を進めた。 ワーキンググループでは、令和８年度以降の開講に向けて以下の点を中心に準備を進め、令和８年４月からの開講準備が整った。 ①科目担当者の割り当て（令和６年度カリキュラム科目担当とのすり合わせ） ②専門教育科目の科目群概要、科目概要、到達目標の確定 ③カリキュラムマップ・カリキュラムツリーの作成 ④令和８年度カリキュラムの令和６年度カリキュラム科目への読み替え ⑤令和８年度カリキュラムにおける「卒業研究Ⅰ～Ⅳ」の履修条件の設定 ⑥科目履修例（履修モデル）の設計 ⑦履修申請単位数の上限に含まれない科目や他学部学生による履修申請を認めない科目の設定 | H27: 3
B29: 4 | C29: ・全学委員会としての教務委員会において、本学の２学部体制の利点を活かすために、大学院の設置をも視野に入れつつ、文理両分野にまたがる学修が可能となるように共通教育を再編成する。 | D29: 【令和４年度～令和７年度の総括】 ・令和６年度に情報学の深化をめざす研究開発に加え、その成果を地域にねざした実践活動に適用することをめざす大学院地域情報学研究科を設置した。また、学部においては、文理両分野にまたがる学修が可能となるよう令和８年度より共通教育を再編成し、新たに設置した基盤教育院による基盤教育科目を展開した。 ・両学部の学生が共に学ぶ基盤教育科目と各学部で展開する専門教育科目からなる令和８年度カリキュラムを策定するとともに、基盤教育科目の展開を担う基盤教育院の設計を行った。 将来にわたり多様な分野及び地域課題について広くかつ深く学び続ける力を学部横断的に育成することを目的とする基盤教育科目を編成し、その中の「地域協働基盤科目群」において、統計データの基本的な処理・分析力を身につけたうえで、地域が抱える具体的な課題を材料として地域協働の基本を学修する「地域協働演習」を、両学部１年次の必修科目として配置した。また、現代社会で活躍するために必要な情報学の基本的知識及びスキルを身につけることを目的として、「情報科目群」に両学部１年次の必修科目として「情報と社会」を配置するとともに、「データサイエンス」や「統計学Ⅰ」等の必履修科目を配置した。 両学部の学生が「論理的に考え表現する力」を身につけることを目的として、「論理学」や「数学的思考法演習」「論理的思考法演習」等の科目を基盤教育科目に配置した。 【令和８年度・令和９年度の見込】 ・令和８年度に設置された基盤教育院において、同年度から適用する新しい教育方針に基づくカリキュラムのもと、情報学部及び地域経営学部の学生を対象とした基盤教育科目を展開し、文理両分野にまたがる新たな教育を実施する。 | E29: 3 | F29: ・令和６年度までの成績にもとづき、全学共通科目群に配置されている両学部から提供されている科目について、履修申請率、修得率、成績分布の把握・測定を行う。 ・令和８年度カリキュラムにおいて、両学部の学生が共に学ぶ基盤教育を担う「基盤教育院」を整備し、具体的教育内容を検討する。 | G29: ・令和２年度から令和６年度までの入学者の「全学共通科目群」の科目毎、入学年度毎、学部・学科毎の履修申請率、修得率を計測して比較するとともに、成績分布について、大学全体を母集団とした適合度の検定を行い、科目毎、入学年度毎、学部・学科毎の傾向を把握した。その結果、令和２年度カリキュラムでは一部の３年次配当科目及び夏期集中講義で履修申請率・修得率が低い傾向が見られた。一方、令和６年度カリキュラムでは履修状況が極端に低い科目はなかった。また、成績分布は、両カリキュラムとも多くの科目で科目群全体とは異なる傾向を示した。 ・令和８年度カリキュラムにおいて、両学部の学生が共に学ぶ基盤教育科目を編成し、基盤教育を担う基盤教育院の設計を行った。令和８年度カリキュラムにおける「情報学を基盤とした地域協働型教育」と「汎用的学修能力の育成」の２つの教育目標のうち、「情報学を基盤とした地域協働型教育」の出発点となる講義科目「地域協働論」及び両学部が全員で共に学ぶ演習科目「地域協働演習」を１年次の必修科目として配置するとともに、それらを中心として、将来にわたり多様な分野及び地域課題について広くかつ深く学び続ける力を学部横断的に育成することを目的とする基盤教育科目の編成を行った。「地域協働演習」の設計にあたっては、専門委員会を立ち上げ、当該演習で扱うテーマの詳細や外部組織との連携等に関する調整を行った。また、基盤教育の質的向上及び充実を図る中心的な役割を担う「基盤教育院」を設置するに当たり、基盤教育院設置準備委員会を立ち上げ、基盤教育院の所属教員や所掌事項、基盤教育院教授会の運営方法等を定めた。 | H29: 3
B30: 5 | C30: ・共通教育と専門教育の両方にわたって、学生が「何を学び、何を身につけることができたのか」を意識し、理解できるような教育課程を編成する。 | D30: 【令和４年度～令和７年度の総括】 ・令和８年度カリキュラムを編成する際、共通教育を基盤教育として再編成し、専門教育といかに連携するかを検討するうえで、学生が「何を学び、何を身につけることができたのか」を意識し、理解できるような令和８年度カリキュラムを編成した。 ・令和８年度カリキュラムについて、基盤教育科目と専門教育科目からなるカリキュラムマップ及びカリキュラムツリーを作成し、学士課程教育の到達目標を明確に定めた。学士課程教育刷新委員会の下に地域経営学部カリキュラム検討ワーキンググループ（ＷＧ）を設置し、地域経営学部の専門教育科目の編成を行うとともに、その内容に基づきカリキュラムマップ及びカリキュラムツリーを策定し、学生が自らの学びの流れと目標を明確に理解し意識できるようにした。また、情報学部に設置された情報学部カリキュラム検討ワーキンググループ（ＷＧ）においても、同様に専門教育科目の編成を行い、その内容に基づき情報学部のカリキュラムマップ及びカリキュラムツリーを策定した。さらに、両学部の学生が共に学ぶ基盤教育科目と各学部で展開する専門教育科目からなる令和８年度カリキュラムを策定するとともに、基盤教育科目の展開を担う基盤教育院の設置を執行会議において、決定した。 【令和８年度・令和９年度の見込】 ・両学部の令和８年度カリキュラムにおける基盤教育科目と専門教育科目との関係性を検証するため、必要な教学データの項目や検証方法を検討し、教学データの取得及び蓄積を進める。 | E30: 4 | F30: ・共通教育と専門教育の両方にわたって、学生が「何を学び、何を身につけることができたのか」を意識し、理解できるような教育課程を編成するために、令和６年度の成績をもとに、令和６年度開講科目の履修申請率、修得率、成績分布の把握・測定を行う。 ・令和８年度カリキュラムにおいて両学部の学生が共に学ぶ基盤教育と各学部の専門教育から構成される学士課程教育の到達目標を各学部と調整しながら検討する。 | G30: ・令和６年度開講科目について、科目毎の履修申請率、修得率を計測して比較するとともに、成績分布について、大学全体を母集団とした適合度の検定を行い、科目毎の傾向を把握した。履修申請率及び修得率に科目間で大きなばらつきが見られた。成績分布については、科目全体と同様の傾向は示されなかった。 ・基盤教育と専門教育からなる令和８年度カリキュラムについて、体系的な教育課程を明確化するため、学修成果の達成にどの授業科⽬が寄与するかを⽰したカリキュラムマップ及び学修成果の達成に向けてどのような授業科⽬が連携し年次配当しているかを⽰したカリキュラムツリーを両学部において策定した。また、大学全体として、「情報学を基盤とした地域協働型教育」を通して、地域のさまざまな人々と協働し、情報学の知識と技術を地域の課題解決に向けて応用する力を身につけるとともに、「汎用的学修能力の育成」をふまえた教育を通して、多様に変化する社会の諸相について生涯にわたって学び、主体的に考え続ける力を修得し、新たな価値の創造や地域社会の発展に活かす能力を身に付けることを、学士課程教育の到達目標として策定した。 | H30: 4
B31: 6 | C31: ②教育職員免許状の課程の設置
C32: ・高等学校教育職員免許の情報の取得課程を設置する。 | D32: 【令和４年度～令和７年度の総括】 ・令和６年度末に高等学校教諭一種免許状（情報）、高等学校教諭一種免許状（数学）及び中学校教諭一種免許状（数学）の課程申請を提出し、令和７年12月に認定を受けた。 【令和８年度・令和９年度の見込】 ・令和８年度から教職課程を開始する。 入学時に教職課程履修の手引き（電子版）を配布し、学生向けガイダンスを実施するなど、教員免許を希望する学生の履修のための環境を整えていく。 今後、予定されている対象教科（中学校の数学、高等学校の数学及び情報）の指導要領の改訂の方向性を調査するほか、再課程認定に向けた準備を開始する。 | E32: 3 | F32: ・設置申請の内容について指摘事項があった場合に早急な対応ができるように準備を行う。 ・教職課程を実施するために必要な以下の項目等の準備を行う。 ①令和８年度入学生向けの「教職課程の手引き」を作成する ②履修者確保の観点から、高等学校向けの広報活動に協力する ③教職課程運営体制の検討を引き続き行う ④教職課程において必要な設備等の整備を行う ⑤採用試験対策をはじめとする学習支援の体制を計画する | G32: ・令和６年度末に文部科学省へ提出した設置申請書に対して、２度の審査意見が付されたが、その都度、迅速かつ適切な対応を行い、12月に高等学校教諭一種免許状（情報）、高等学校教諭一種免許状（数学）及び中学校教諭一種免許状（数学）の課程認定を受けた。 ・計画の各項目に対して、以下の通り準備作業を行った。 ①教職課程履修の手引きを作成し、情報学部の１年生向けに配布できるようにした。 ②高校訪問用に教職課程の履修に関するチラシを作成した。 ③令和８年度から教職課程運営委員会が活動できる体制を整え、新入生向けオリエンテーションでの説明等が実施できるようにした。 ④書籍を中心とした必要な設備等の整備を行った。 ⑤数理・データサイエンスセンターと協力して学習支援を行うことを検討した。 ⑥採用前倒しなど、教職採用の動向調査を行った。 | H32: 3
B33: 7 | C33: ・高等学校教育職員免許の数学と公民の取得課程の設置を目指した検討を行う。 | D33: 【令和４年度～令和７年度の総括】 ・令和６年度に教職課程準備委員会が発足するにあたり、事前のワーキンググループの検討に基づき、情報学部では高等学校教諭一種免許状（数学）に加え中学校教諭一種免許状（数学）の課程の設置をめざすことが確認された。 教職課程準備委員会では本検討結果に基づき、中学校及び高等学校の数学科の免許に必要な教職課程専任教員の構成を定め、数学科に関する専門的事項並びに教科教育法をカバーする科目群を設定することで、数学科の教職課程の認定を受けた。この点は計画を上回って実施できたと判断できる。 ・また、地域経営学部の検討により、高等学校の公民科の免許のための課程申請は行わないことを確認した。なお、公民科の課程申請を見送る主な理由は以下の２点である。 ①公民科の免許は教員採用試験の受験資格を満たすが、採用枠は地歴と公民がまとめられていることが一般的であり、採用試験でも両者が出題される傾向がある。このため、公民単独の免許の発行では実際に教職に就く教員養成には結びつきにくいこと。 ②地歴の教職課程を地域経営学科におくためには、さらに３人の科目適合性が認められる教職専任教員を配置する必要があるなど、現在の地域経営学科の教員配置では困難が予想されること。 これらにより、本計画は完了となった。 【令和８年度・令和９年度の見込】 ・計画完了につき、今後２年間の実施内容は計画番号６に統合される。 | E33: 4 | F33: ・対応済み。 | G33: ・対応済み。 | H33: 3
B34: 8 | C34: ③新しい大学院の設置
C35: ・情報学を中軸にしつつ地域経営学関連分野とも密接に連携する地域協働型教育研究を本学全体として展開するために、新たに大学院修士課程を、令和６年度を目途に設置する。 | D35: 【令和４年度～令和７年度の総括】 ・大学院の設置を令和６年度に完了し、順調に教育研究を進めている。本学大学院地域情報学研究科は、中期計画がめざしたように、情報学の深化とともに地域にねざした実践的な成果によって学位を認定することができるカリキュラム及び学位認定を行う研究科として令和６年度（第２期中期計画２年目）に設置された。 ・設置後２年間は設置申請書に記載された内容を適切に履行することを目標として、アドミッション（入学者選抜）～ディプロマ（学位授与）までの一連の事項を適正に実施した。当該期間中に実施された文部科学省による年次の審査において改善等を指示する意見を付されることはなく、適正な実施が行われたことが認められている（第２期中期計画３年目～４年目）。 設置開始から２年間は定員を充足できていない状況であった（１年目：15人、２年目：16人）が、大学院のことが学生に定着しつつある３年目では21人の入学者を確保し（合格者24人）、定員充足にも一定の目途がついたと考えられる。 ・さらに、大学院を取り巻く状況の変化と、入学者の確実な確保をめざして、設置から２年間（第２期中期計画３年目～４年目））に以下の取組みを実施した。 ①社会人入学者向け制度の整備（長期履修制度・入学者選抜における口頭試問免除制度・厚生労働省 教育訓練給付制度） ②主に内部学生向けの広報の取組み（学務ガイダンス・キャリアガイダンス・保護者向け講演） ③学外の大学生向け広報の取組み（大和大学） ④学部改編と並走して、カリキュラムの改善及び教員負荷低減のための大学院カリキュラム再編（令和８年度より実施分） 【令和８年度・令和９年度の見込】 ・大学を取り巻く状況に対応し、また教員負荷にも留意しつつ大学院修士課程の安定的な学生確保及びカリキュラム実施を継続する。 | E35: 3 | F35: ・設置認可申請書に定めたカリキュラム・ポリシーに従って、情報学を中軸にしつつ地域経営学関連分野（および文理融合分野）と密接に連携する教育カリキュラム（２年目）を実施する。 ・２年間の状況を踏まえ、大学院の今後のあり方を議論する。 | G35: ・設置認可申請書に定めたカリキュラム・ポリシーに従って、２年目の教育カリキュラムを滞りなく実施し、第１期入学者全員を修了させた。 ・大学院地域情報学研究科の２年間の教育実施状況を踏まえ、開講時期を適正に改善し、工学者倫理科目を独立科目として開講するなど、研究及びプロジェクト活動に寄り添った教育カリキュラムへの改善を検討し、令和８年度から実施することを決定した。 | H35: 3
B36: 9 | C36: ・大学院の博士課程設置に向けた方針を定める。 | D36: 【令和４年度～令和７年度の総括】 ・大学周辺を取り巻く状況を鑑み、以下の理由から喫緊での博士後期課程の設置は必要でないと判断した。 ①ここまでに入学した大学院生に、定員を適切に設置し、充足するほどの進学希望者が現れていないこと。（実績的にも学年に１人ないし２人の学生が進学又は進学を希望するにとどまっている。また、大学院博士後期課程の多くは研究科に３名以上の定員を定めている。） ②地域からの要望が仄聞されないこと。 加えて、博士課程の担当教員として適格と判定された教員の確保に代表される教育体制が整備されていないことも勘案し、十分な準備期間を欠いた性急な設置は期待される効果が得られないと判断したものである。 【令和８年度・令和９年度の見込】 ・今後の地域及び大学を取り巻く環境の変化に遅れることなく、博士後期課程設置の是非について調査検討と議論を継続する。 | E36: 3 | F36: ・大学院の今後のあり方を議論し、それに沿って、博士課程の設置の必要性が明らかになった際に改めて設置に関する議論を行う。 | G36: ・学生の進学希望状況及び現状の教員組織を踏まえ、喫緊での博士後期課程の設置の必要性はないと判断した。一方で、修了生に博士後期課程進学者がいること、博士後期課程進学希望学生が在学していることなどから、今後の設置の必要性については継続的に議論が必要であることも再確認した。 | H36: 3
B38: 第４－１ 教育に関する目標
B39: （３）地域協働型の教育の深化・充実
B41: 中 期 目 標 | D41: 持続可能な地域づくりに取り組む人材を育成する「福知山モデル」の具現化に向け、文理連携により、地域の課題や資源を教育に活かす仕組みを構築するとともに、フィールドワークや演習等の実践的な教育を充実する。
B43: 中期計画 年度計画 番号 | C43: 中期計画 | D43: 業務の実績（中期計画） | E43: 自己評価 | F43: 年度計画 | G43: 業務の実績 | H43: 自己評価
B45: 第４－１ 教育に関する目標を達成するための措置
B46: （３）地域協働型の教育の深化・充実
B47: 10 | C47: ①本学の特色である「地域協働型教育研究」の深化・充実
C48: ・「地域協働型教育」の深化・充実を図るために、地域経営学部ではフィールドワーク型演習系科目、情報学部ではＰＢＬ等の演習・実習科目の具体的な実態を把握しその学修成果を検討するための組織を両学部に設置する。 | D48: 【令和４年度～令和７年度の総括】 ・地域経営学部では、令和６年度に地域経営学部執行会議を設置し、実践教育実習費を活用したメディアセンターの一部改修及びメディアセンターによる紙媒体で現存する地域資料のデジタル化を教授会に提案・実施して、フィールドワーク型演習系科目の運営支援機能の強化を図った。 毎年度、フィールドワーク型演習系科目の学修成果を「地域協働型教育研究報告書」にまとめると同時に、例年２月に報告会を開催している。これらを通じて、当該科目の具体的な実態を把握し、学内外からの意見等を学修成果の改善に活かしてきた。 また、令和８年度カリキュラムにおいて、地域協働型教育の理論と実践を行う基盤教育科目として地域協働演習が開講される。地域協働演習の各クラス（チーム）は両学部の学生から構成され、科目担当者である地域経営学部、情報学部及び基盤教育院の教員は、学修成果の向上を図るために連携し、科目運営を実施する。 ・情報学部では、４年間で継続的に地域協働型教育、研究活動を実施してきた。特に、ＰＢＬ並びに近隣団体、地元高校と連携した活動の実態を学部内で把握、共有し、これらの活動の推進、拡大を図ってきた。具体的なテーマとして、 ①ジュニアＩＣＴ教室（福知山市、朝来市、丹波市との連携事業） ②ジュニアデジタルアカデミー（伊根町との連携事業） ③シニアワークカレッジ（福知山市との連携事業） ④消防活動におけるＡＩ支援（福知山市との連携事業） ⑤冠島オオミズナギドリの生態調査（京都府立西舞鶴高等学校との連携事業） ⑥音楽と情報技術をテーマとするインタラクティブ作品製作（みすずフェスタ、ＤＸでつながるワトクの学び、音のとびらを開く会inふくくるさんぽ） ⑦大江山パワーロード観光ガイド（京都未来人材育成プロジェクト） ⑧夜久野ウルシ苗木の根系解析（ＮＰＯ法人丹波漆との連携事業、京都未来人材育成プロジェクト） ⑨トレンドワードを用いた地域ＰＲ動画自動生成について ⑩飲食店におけるロボット・アバター連携による接客演出の効果 などが挙げられる。中期計画においては「学修成果を検討するための組織を両学部に設置する。」となっているが、現状では北近畿地域連携機構、学部長を中心に近隣団体、高校との要望に応じて、担当可能な教員を選考し、対応している状況である。中期計画後半では、これまで実施されたプロジェクトを中心に学修成果を検討する組織を設置し、評価を進めていく。 【令和８年度・令和９年度の見込】 ・１学年に両学部で連携した地域協働型教育プログラムとして、地域協働演習が設定されたことから、両学部及び基盤教育院と連携した地域協働型教育・研究の展開が見込める。 また、情報学部では、中期計画後半において、中間報告までに実施されたプロジェクトを中心に学修成果を検討する組織を設置し、評価を進めていく。 | E48: 3 | F48: ・地域経営学部では、地域協働型教育研究を推進するため、地域経営学部執行会議の活動を継続・強化し、フィールドワーク型演習系科目の効果的な運営を支え、授業内容の改善に関して教授会に提案する。 ・情報学部では大学院と連携した地域協働型教育研究を進める。 | G48: ・地域経営学部執行会議が教授会に提案し、実践教育実習費を活用してメディアセンターによる紙媒体の地域資料のデジタル化を行うことで、フィールドワーク型演習系科目の運営支援機能の強化を図った。 ・大学院生を含む地域協働型教育及び研究活動を積極的に実施された。具体的には、以下のようなテーマが大学院と連携した地域協働型研究として今年度に実施した。 ①消防活動におけるAI支援の研究 ②冠島オオミズナギドリの生態調査 ③Quality-Diversityに基づく多様な構造を持つ最適化問題の研究 ④飲食店におけるロボット・アバター連携による接客演出の効果 | H48: 3
B50: 11 | C50: ・共通教育については、教務委員会において、地域課題の解決や地域資源の活用に資する文理両分野にまたがる科目設定を図る。 | D50: 【令和４年度～令和７年度の総括】 ・令和８年度カリキュラムにおいて、共通教育は基盤教育として再編成し、新たに基盤教育院を設置した。基盤教育では、地域協働論、地域協働演習等の科目設定を行い、地域課題の解決や地域資源の活用に資する文理両分野にまたがる科目を設定した。 【令和８年度・令和９年度の見込】 ・令和８年度に設置された基盤教育院において、同年度から適用する新しい教育方針に基づくカリキュラムのもと、「地域協働基盤科目群」及び「情報科目群」を展開し、情報学部及び地域経営学部の学生を対象とした「情報学を基盤とした地域協働型教育」に取り組む。 | E50: 3 | F50: ・令和６年度までの成績にもとづき、全学共通科目群に配置された地域課題の解決に関する科目、地域資源の活用に資する科目について、履修申請率、修得率、成績分布の把握・測定を行う。 | G50: ・令和２年度から令和６年度までの入学者の全学共通科目群に配置された地域課題の解決に関する科目、地域資源の活用に資する科目について、科目毎、入学年度毎、学部・学科毎の履修申請率、修得率を計測して比較するとともに、成績分布について、大学全体を母集団とした適合度の検定を行い、科目毎、入学年度毎、学部・学科毎の傾向を把握した。その結果、令和２年度カリキュラムでは一部の３年次配当科目で履修申請率及び修得率が低く、成績分布も科目全体とは異なる傾向が見られた。一方、令和６年度カリキュラムでは履修状況は極端に低い科目はなく、成績分布も科目全体と同様の傾向を示した。 | H50: 3
B51: 12 | C51: ②インターンシップの充実
C52: ・地域協働の実践を経験しつつ、学生が自らのキャリアを考えるためのインターンシップを充実させる。 | D52: 【令和４年度～令和７年度の総括】 ・令和５年度の文部科学省・厚生労働省・経済産業省の合意による「インターンシップの推進に当たっての基本的考え方」の改正においては、常に就活市場の動向を注視し、学内ガイダンスで学生に周知するなど、前向きにインターンシップに参加できるよう支援を行った。また、学生だけではなく企業へのアプローチを強化し、インターンシッププログラムの充実に努めた。特に、令和５年度が初めての参加となった情報学部においては、より専門的な就業体験の場となるよう、学部限定のプログラム提供を企業に依頼し、プログラムの充実に努めた。 ・地域経営学部では、北近畿地域における事業所での実習経験を通じ、学生が北近畿地域の課題についての理解と、卒業後の進路を含む自身のキャリアについての考えを深めるため、「地域キャリア実習Ⅰ、Ⅱ」を実施し、受講を推奨してきた。インターンシップへ参加を希望する学生は、本学が提示する「地域キャリア実習 実習先リスト」に掲載された事業所の各実習内容から実習先を選定し、長期休暇期間などを活用して実習に参加している。 インターンシップの受入事業所は、北近畿地域の官公庁（市役所、警察署）、民間企業（製造業、運輸業、観光サービス、高齢者福祉施設等）である。 「地域キャリア実習Ⅰ、Ⅱ」では、実習後に学内で実施する報告会においてインターンシップに参加した学生が実習内容を報告し、その報告書及び発表内容を踏まえて単位を付与しており、毎年度20人程度の学生が単位を取得している。 ・情報学部では、地域協働の実践を経験しつつ、学生が自らのキャリアを考えるためのインターンシップを「インターンシップ実習Ⅰ、Ⅱ」科目として実施し、受講を推奨してきた。「インターンシップ実習Ⅰ、Ⅱ」では、インターンシップを希望する学生に対する受入先の紹介を、事務職員（キャリア支援係）、指導教員等が担当し、福知山市を中心に、毎年、官公庁（市役所、警察署）、民間企業（ソフトウェア開発、鉄道運輸、観光サービス、新聞社等）において20人程度の学生がインターンシップを行い、単位を取得している。単位取得にあたっては、Slackにおいてインターンシップ内容の報告及び質疑応答への参加を義務付けている。本科目は実際の業務を体験する貴重な機会であり、学生が進路を検討する上でも重要と考えられることから、令和８年度から開始する教育課程においても３年次の科目の一つとして設定した。 ・大学院地域情報学研究科では、大学院カリキュラムにインターンシップを科目として設定し、地域への大学院生のインターンシップへの参加を推し進めている。 【令和８年度・令和９年度の見込】 ・今後も学生の就職活動、とりわけインターンシップを取りまく環境は、さらなる早期化など大きな変化が予想される。常に最新のトレンドを注視し、充実したインターンシップ実現のため学生だけではなく企業にも呼びかけを継続する。 ・地域経営学部では、令和８年度カリキュラムにおいて、２・３年次開講のキャリア関連科目群として地域キャリア実習Ⅰ、Ⅱを設定しており、引き続き学生のインターンシップ支援を進めていく。 ・情報学部では、インターンシップを受け入れる企業は増えており、インターンシップに行く学生は増えていくことが予想される。このことから、令和８年度から実施する新しいカリキュラムにおいても、３年次開講のキャリア関連科目群としてインターンシップ実習Ⅰ、Ⅱを設定しており、引き続き学生のインターンシップ支援を進めていく。 ・大学院地域情報学研究科では、事務局のキャリア担当部局と連携し、地域企業の協力を得て、大学院生のインターンシップ先を継続的に確保する。 | E52: 4 | F52: ・インターンシップの実施方法等について、より学生がプログラムに興味を持つように、プログラム提供事業者向けのセミナーを開催するなど事業所にもアプローチし、学生と事業所間のマッチングを促進する。 ・京都府が運営する就職サイトとの連携を強化し、京都府内のインターンシップに参加しやすい体制に整備することで、府内のインターンシップ希望学生への案内を促進する。 | G52: ・初めての試みとして、４月にプログラム提供事業者向けに学生に選ばれるインターンシップ構築についてセミナーを実施し、事業所へのアプローチを行った。この研修には16社から参加があり、学生がインターンシップに求めている内容が知れたなど、非常に満足が約１割、満足が約６割の結果であった。 ・インターンシップの実績としては、実習先数は26事業所、参加学生は58人であった。１、２年次の学生の参加者が13人（前年度９人）に増加し、低学年次からキャリア観を醸成する機会として、本プログラムを提供できたと考える。 ・京都府と連携し、企業・学生双方に京都府が運営する就職サイトの案内を行い、サイトの利用を促進するとともに、インターンシップ情報の周知に努めた。特に学生向けには、学内イベントに参加した学生にチラシの配布や説明を実施した。 | H52: 3
B54: 13 | C54: ③教育における「福知山モデル」の提示
C55: ・地域と本学とが協働して持続可能な地域社会を創出する教育的試みを継続し、代表的実践例とその理論的背景を「福知山モデル」として取りまとめて提示する。 | D55: 【令和４年度～令和７年度の総括】 ・執行会議の下に「福知山モデル研究会」を設置し、令和４年度から令和６年度の間に計13回開催した。研究会では、第１期中期目標期間における取組みを振り返りながら、地域協働型教育、地域貢献、高大連携の在り方等について教職員で意見交換を行い、地域貢献を起点とする教育研究の基本的な方向性の整理を図った。令和６年度に開設した大学院地域情報学研究科においては、これらの議論を踏まえつつカリキュラム設計を進め、地域実践プロジェクトを重視した教育課程を構築した。 ・大学院地域情報学研究科の設置趣旨は、情報学を基盤として地域課題の解決に貢献する教育研究を進める点にあり、本学の地域協働型教育研究の新たな方向性を示すものとなった。こうした方向性を学部教育にも展開することで、教育研究を通じて地域社会に貢献する本学の独自性をより明確にするため、学長が示した組織改編案を基に、執行会議において学士課程教育の在り方について検討を重ねた。その結果、教育における「福知山モデル」と位置付ける「学士課程教育改編の方針」を令和６年３月に策定した。同方針では、「情報学を基盤とした地域協働型教育」及び「汎用的学修能力の育成」を新たな二つの教育目標として掲げるとともに、学部・学科の再編、共通教育を担う教員組織「基盤教育院」の設置、大学全体の三つのポリシーの策定等を示し、令和８年度以降の教育活動の基本的枠組みを明確化した。 ・令和６年度には学士課程教育刷新委員会を設置し、同委員会を中心に改編方針に基づく具体的な制度設計を進めた。全学及び各学部の三つのポリシーを策定し公表するとともに、令和８年度からの新たな教育課程の実施に向けた準備を整えた。併せて、執行会議における議論を通じて福知山モデルの具体化を進め、中間整理を行うなど、教育における「福知山モデル」の具現化を進めた。 【令和８年度・令和９年度の見込】 ・学士課程教育においては、令和８年度から適用する新しいカリキュラムを実施し、「学士課程教育改編の方針」を実質化する。「福知山モデル」については、中間報告案を基に内容の精緻化を進め、地域協働型教育の実践例と理論的背景との対応関係を整理した上で、第２期中期目標期間中に提示する。 | E55: 3 | F55: ・令和８年度からの学士課程教育改編案で示す「情報学を基盤とする地域協働型教育」及び「汎用的学修能力育成」の二つの教育目標を教育における「福知山モデル」に位置付ける。加えて、これまでの取組みを振り返り、「福知山モデル」に繋がる具体例を整理しながら、教育における「福知山モデル」の柱となりうる特徴を中間報告として取りまとめる。 | G55: ・「学士課程教育改編の方針」（令和６年３月策定）に基づく令和８年度カリキュラムの開講に向け、科目設計や実施方法等の具体的な内容について検討を進め、必要な準備を整えた。その中では、改編内容について全教職員の十分な理解を促進し、準備を円滑に進めることを目的として、学長文書「2026年度からの学士課程教育 ― これまでとは何が変わるのか」を作成し、学内で共有した。同文書では、従来の共通教育を再構築した基盤教育と専門教育の一体的かつ一貫的な運用、二つの教育目標の達成に向けた具体的な科目群の設置、従来の「ゼミ制度」を「指導教員制度」へ移行し、地域協働型教育の成果を学生の成長として結実させる仕組みの導入などを示し、教職員の理解を深めた。また、「福知山モデル」の構築に向け、その柱となりうる特徴をまとめた中間報告案を執行会議において協議し、同モデルの理論的フレームワークを中心に議論を深め、長期的な視点に立ったモデルの構築に向けて次年度に内容のさらなる精緻化を図ることを確認した。 | H55: 3
B56: 第４－１ 教育に関する目標
B57: （４）教育の質保証等
B59: 中 期 目 標 | D59: 教育の質を向上させるため、教員間、教職員間の連携・協働を強化するとともに、授業の改善とあわせて教育・学習成果の多面的な評価に基づく教育の自己点検・評価を継続的に実施する。
B61: 中期計画 年度計画 番号 | C61: 中期計画 | D61: 業務の実績（中期計画） | E61: 自己評価 | F61: 年度計画 | G61: 業務の実績 | H61: 自己評価
B63: 第４－１ 教育に関する目標を達成するための措置
B64: （４）教育の質保証等
B65: 14 | C65: ①教育の質保証等
C66: ・アドミッションポリシー・カリキュラムポリシー・ディプロマポリシーに基づいてアセスメントポリシーを策定し、学生の満足度を含めた学修成果を大学全体レベル、学部・学科レベル、科目レベルの３段階で検証を実施することとし、そのために必要なデータをＩＲ委員会が他の部門と共同で収集し、分析を行う。分析結果に基づく自己点検・評価委員会の検証結果を学内で共有するとともに、適切な範囲と方法で学外にも公表する。 | D66: 【令和４年度～令和７年度の総括】 ・学修成果の検証に向けたデータ収集のため、令和４年度よりこれまで実施してきた入学前アンケート及び卒業時アンケートに加え、２年次生を対象とした授業・学生生活・就職支援等に関する在学生満足度アンケートや外部アセスメントテスト（ＰＲＯＧテスト）を導入し、学生の満足度を含むデータの蓄積を図った。令和６年度にアセスメント・ポリシーとともに策定されたアセスメントチェックリストにおいて、ＩＲ委員会でこれまで蓄積してきた各種アンケートデータを学修成果測定の指標として使用するため、令和６年度及び令和７年度においてもデータの収集を行い、得られた結果を令和７年度から実施しているアセスメントの実施者に提供した。 ・令和６年度に策定されたアセスメント・ポリシーに基づき、大学全体レベル、学部・学科レベル、科目レベルのアセスメントチェックリストが作成された。アセスメントチェックリストには、ＩＲ委員会で実施している入学前アンケート、外部アセスメントテスト、在学生満足度アンケート、卒業時アンケートが含まれており、これらの収集した結果を令和７年度から実施しているアセスメントの実施者に提供した。 【令和８年度・令和９年度の見込】 ・今後は、収集した結果だけでなく、経年変化の追跡や傾向の抽出を加えて、アセスメント実施者に提供できることを検討するとともに、中期計画中にアセスメント方法をブラッシュアップすることにより、アセスメント報告書の質を向上させる必要がある。 | E66: 3 | F66: ・アセスメントテストとして、１年次生（入学時）及び３年次生（後学期初め）を対象にＰＲＯＧテストを実施する。特に３年次生については、１年次に受けたテスト結果と比較し、学修成果の可視化の一助とする。また、アセスメントチェックリストに基づく各種アンケートを実施する。 ・令和６年度の成績にもとづき、アセスメント・ポリシーを適用する令和６年度入学生を対象として、大学全体レベル、学部・学科レベル、科目レベルのアセスメントチェックリストに基づき、学修成果を把握・測定する。 | G66: ・４月に１年次の学生を対象としてＰＲＯＧテストを実施し、６月に解説会を行った。９月には３年次の学生を対象としてＰＲＯＧテストを実施し、11月に解説会を行った。２月には、ＰＲＯＧ結果の教職員報告会を行い、そのなかで今年度のＰＲＯＧ結果のほか、３年次の学生の１年次のＰＲＯＧ結果の比較も共有し、学修成果の可視化の一助とした。また、アセスメントチェックリストにある入学前アンケート、学生満足度アンケート、卒業時アンケートを実施した。学生満足度アンケートについては、経年変化から変化が顕著に見られた項目（食堂満足度・制度認知度・入学後の学修満足度等）を抽出し、背景にある要因を推察するなどの分析を行った。すべての集計結果、分析結果を教職員で共有した。 ・令和６年度入学者の令和６年度成績を対象に、大学全体レベル、学部・学科レベル及び科目レベルの３段階からなるアセスメント・チェックリストに基づき、学修成果の把握・測定を実施した。学部・学科レベルでは、選抜試験結果、入学前アンケート、ディプロマ・ポリシーに関連する科目の履修状況及び成績分布、ＧＰＡ、修得単位数並びに外部アセスメントテストの結果を総合的に分析・評価し、改善点を整理した。大学全体レベルでは、これらを全学的な観点から分析・評価した。また、科目レベルでは、履修登録状況（履修者の所属学部、学科）、成績分布及び授業評価アンケートに基づく学修状況（学修時間等）を確認した。 | H66: 3
B67: 15 | C67: ・本学の教育目的達成のための教学マネジメントを確立するために、「内部質保証の方針」並びに「内部質保証体制図」に示されたＰＤＣＡサイクルの適切な運用により、学修成果の検証結果を踏まえた教育内容と方法の全学的な改善を行う。 | D67: 【令和４年度～令和７年度の総括】 ・学修成果の検証を行うために、ＩＲ委員会が収集、分析してきた福知山公立大学データブック、卒業時アンケート、在学生満足度アンケート、外部アセスメントテスト等を活用し、教務委員会において学修成果の検証に資するデータの洗い出しを行った。その上で、アセスメントの目的、実施体制・方法並びに大学全体、学部学科、科目のレベルの３段階のアセスメントチェックリスト（評価指標を含む）を定め、令和６年度入学者から適用するアセスメント・ポリシーを策定した。 ・令和７年度には、令和６年度入学者の令和６年度成績を対象として、大学全体レベル、学部・学科レベル、科目レベルのアセスメントチェックリストに基づき、学修成果の把握・測定を行うとともに、科目毎に履修申請率、修得率、成績分布の把握・測定を行った。 ・教学関連の全学委員会の諸活動を横断的かつ俯瞰的な視点で一元的にモニタリングし、不断の改善・充実を図る体制として令和８年度から「全学教育企画室」を設置することとした。これに併せて、これまでの把握・測定結果を踏まえた教育内容及び教育方法の改善を一層推進するため、「内部質保証の方針」及び「内部質保証体制図」を見直した。 【令和８年度・令和９年度の見込】 ・令和７年度 福知山公立大学アセスメント報告書、各区分における履修申請率、修得率、成績分布集計一覧等をもとに、今後さらなる学修成果の把握・測定を行い、教育内容と方法の全学的な改善を行う必要がある。 | E67: 3 | F67: ・両学部の令和６年度の成績にもとづき、令和６年度開講科目の履修申請率、修得率、成績分布及び令和７年度の授業評価アンケートの把握・測定を行い、教育内容と方法を改善するためのデータ、資料を蓄積する。 ・令和８年度開講科目の教育の質を保証するため、シラバスチェックを継続する。 | G67: ・令和６年度開講科目について、科目毎の履修申請率、修得率を計測して比較するとともに、成績分布について、大学全体を母集団とした適合度の検定を行い、科目毎の傾向を把握した。また、令和７年度前学期・後学期に授業評価アンケートを実施した。 各科目の成績分布は、全体の成績分布とは異なる傾向を示した。 ・令和８年度に開講する全ての科目についてシラバスチェックを実施した。チェックリストにおいては、単位の実質化を担保する観点から、授業概要、到達目標、評価基準を重点確認項目として確認した。これらの事項が適切に設定され、学生に明確に示されていることを確認することにより、教育の質保証に取り組んだ。 | H67: 3
B68: 16 | C68: ②効果的なＦＤ活動
C69: ・教育の質の向上を目指し、効果的なファカルティ・ディベロップメント（ＦＤ）活動を実施する。 | D69: 【令和４年度～令和７年度の総括】 ・４年間を通じて、教員の資質向上を目的として継続的にＦＤ活動を実施した。全学ＦＤ及び学部ＦＤでは、地域住民組織の関係者や地方議員等を講師に招き、地域協働や地域課題解決に関する実践的知見を共有する研修を実施した。また、生成ＡＩの教育利用やＳＮＳ、メディアリテラシーに関する研修を通じ、教育研究環境の変化に対応した多面的なテーマを設定し、教員の能力向上に取り組んだ。さらに、教職員間のコミュニケーション、著作権、学生のメンタルヘルス、初年次教育、授業運営等に関する外部研修への参加を推進し、多様な教育課題への理解を深めた。 【令和８年度・令和９年度の見込】 ・今後の２年間も、教育の質の向上を目指し、効果的なファカルティ・ディベロップメント（ＦＤ）活動を実施していく。 | E69: 3 | F69: ・教員の資質向上を目的として、全学を対象としたＦＤ研修を実施する。 | G69: ・令和７年度は、地域課題への理解の深化及び外部資金獲得力の向上を活動の中心に据え、外部研修を効果的に活用しつつ以下のＦＤ活動を実施した。 ①第１回ＦＤ合同研修「明日の自分を軽くする 大学教職員のための心の整え方とZ世代との付き合い方」（大学コンソーシアム京都主催、６月４日実施）／受講者１人 ②第２回ＦＤ合同研修「科研費獲得のための申請書作成術〜コツと戦略を学ぶ～」（大学コンソーシアム京都主催、７月２日実施）／受講者６人 ③第３回ＦＤ合同研修「隣のゼミはどんなゼミ？」（大学コンソーシアム京都主催、９月26日実施）／受講者３人 ④ＦＤ学内研修会（神戸市会議員伊藤めぐみ氏）「地域課題への取り組み、めぐみ豊かな街つくりを目指して」(10月22日)／受講者21人（受講率47%） ⑤科学研究費助成事業（科研費）に関する学内説明会（11月18日）／受講者28人（受講率62%） ⑥研究倫理に関するＦＤ（12月１日）／受講者31人（受講率69%） | H69: 3
B70: 17 | C70: ③コロナ禍を経た大学教育のあり方の確立
C71: ・コロナ禍を経て今後予想される大学教育全般の変貌に対応するために、文部科学省等が提示する制度的枠組を見据えながら、本学にふさわしい教育内容と方法の確立に積極的に取り組む。 | D71: 【令和４年度～令和７年度の総括】 ・新型コロナウイルス感染症への対応として実施していた遠隔授業の経験を踏まえ、感染収束後もメディア授業の導入について継続的に検討を行った。各学部の専門科目については、中長期的な導入を視野に検討を継続するとともに、共通教育科目については、非常勤講師の確保や教育機会の拡充を目的として、令和６年度からの導入に向け、学則改正を行うなど必要な制度整備を進めた。 ・令和６年度からは、当該授業の全授業回をメディア授業とする場合を「メディア授業」に指定しているが、令和７年度までに実施している科目はない。一方で、対面授業でも授業回数の半数以下でメディアを取り入れた授業を実施できるようになったため、予めシラバスに記載するか、都度届け出ることにより実施を開始した。 メディア授業を実施する際は、いわゆる同時性又は即応性を持つ双方向性（対話性）を有し、面接授業に相当する教育効果を有すると認められる場合に限定し、実施方法等を教務委員会で確認することとした。 ・令和８年度カリキュラムにおけるメディア授業の活用について、各授業科目の内容に応じて、メディア授業を活用することとした。メディア授業は、いわゆる同時性又は即応性を持つ双方向性（対話性）を有し、面接授業に相当する教育効果を有するだけでなく、メディア授業でなければ達成できない教育効果があると認められる場合に活用する。 【令和８年度・令和９年度の見込】 ・メディア授業の実施の有無も含め、今後の導入について検討するとともに、導入する場合には必要な事務処理についても併せて検討する。 | E71: 3 | F71: ・両学部の令和６年度の成績にもとづき、メディア授業を実施した科目について、その教育成果を把握するために履修申請率、修得率、成績分布の測定・把握を行う。 ・両学部の令和８年度カリキュラムにおけるメディア授業等の活用について検討する。 | G71: ・令和６年度の開講科目でメディア授業指定された科目はなかったが、授業回数の半数以下をメディア授業として実施した科目が、シラバスに事前記載のあった科目が３科目、学期途中に臨時で実施した科目が14科目あった。これらについて、科目毎の履修申請率、修得率を計測して比較するとともに、成績分布について、大学全体を母集団とした適合度の検定を行い、科目毎の傾向を把握した。いずれも令和６年度開講科目全体と比較して顕著な差異は見られず、メディア授業による明確な影響は確認されなかった。 ・令和８年度カリキュラムにおけるメディア授業の活用について、各授業科目の内容に応じて、メディア授業を活用することとした。メディア授業は、いわゆる同時性又は即応性を持つ双方向性（対話性）を有し、面接授業に相当する教育効果を有するだけでなく、メディア授業でなければ達成できない教育効果があると認められる場合に活用する。 | H71: 3
B72: 第４－１ 教育に関する目標
B73: （５）学生支援の充実等
B75: 中 期 目 標 | D75: 学生一人一人の事情やニーズを踏まえた修学支援、生活支援をはじめ、課外活動、地域貢献活動、就職活動、健康管理、メンタルヘルスケアなど様々な支援に取り組む。
B77: 中期計画 年度計画 番号 | C77: 中期計画 | D77: 業務の実績（中期計画） | E77: 自己評価 | F77: 年度計画 | G77: 業務の実績 | H77: 自己評価
B79: 第４－１ 教育に関する目標を達成するための措置
B80: （５）学生支援の充実等
B81: 18 | C81: ①修学支援の充実
C82: ・厳しい経済状況にある学生が学業に専念できるように、国や自治体等が行う高等教育の修学支援新制度を活用するとともに、本学独自の授業料減免制度等の経済的支援の実施を目指す。 | D82: 【令和４年度～令和７年度の総括】 ・各奨学金制度の周知や手続きについては担当者が個別に丁寧に対応し、よりよい経済的な支援が受けられるように支援を行っている。また外部団体との連携や補助金事業等を活用し、以下のような学生に有効と考えられる経済的支援を図っている。 ①市民団体からの食糧支援（令和５年度～令和６年度） ②大学から食の支援として学生食堂及びキッチンカーの減額措置（令和４年度～令和６年度） ③教育後援会から食の支援として学生食堂及びキッチンカーの減額措置（令和７年度） ④日本学生支援機構の補助金を活用したお米券の配布（令和７年度） 【令和８年度・令和９年度の見込】 ・物価高騰対策の補助金事業が今後充実とすると考えられるため、それらを活用し学生への経済的な支援の充実を図る。 | E82: 3 | F82: ・令和７年度から新しく始まる高等教育の修学支援新制度の「多子世帯の授業料等無償化」の対応について学生への周知を行い、滞りなく対応する。 ・奨学金支援システムを活用し、奨学金手続き業務に関する学生の利便性向上と、事務の効率化を図る。 | G82: ・「多子世帯の授業料等無償化」については、独立行政法人日本学生支援機構による審査の遅れ等により、全国的に混乱が見られたが、学生及び保護者からの問い合わせに対して冷静かつ丁寧な対応を行った。また、審査の遅延状況に応じて授業料の徴収を担当する部署と連携し、学生の授業料納付への対応を行うとともに、学生ポータルサイトを通じた周知に努めた結果、本学においては特に大きな混乱はなく対応することができた。 ・奨学金支援システムを活用することで、事務作業面において奨学金関連の手続きに対する個別対応が減少し、業務の効率化及び管理の円滑化につながった。また、学生の利便性の面では、システムを通じて手続きの案内や通知を行うことで学生自身の確認漏れの防止につながり、利用学生にとっても各種手続きの管理が円滑化された。 | H82: 3
B83: 19 | C83: ・学生用図書やその他の資料を体系的に収集するための体制を整備し、メディアセンターの学修支援機能を強化する。 | D83: 【令和４年度～令和７年度の総括】 ・「選書指針」に基づき、学生用図書や学科専門書、シラバス掲載の参考書等を継続的に収集・整理した。蔵書数は90,000冊から95,000冊の規模で推移している。毎年「学生選書委員会」を組織し、学生の視点を取り入れた図書購入を通じて運営への参加を促進した。 ・メディアセンターに対するニーズ調査の結果を踏まえ、施設整備を段階的に実施した。令和４年度にメディアセンター内のカーテンを更新することで衛生的かつ快適な学修環境を整備するとともに、就職活動などの支援のためオンライン面接用「テレキューブ」の設置場所を提供した。令和５年度には情報集約実習室を自習スペースへ変更した。令和６年度には生涯実習室を「アカデミックルーム」へ改修し、より快適な学修環境を整えた。 ・新入生ガイダンスにおいて、福知山市立図書館との連携紹介を行うとともに、レポート作成支援、防災、本屋大賞受賞作等、多角的なテーマでの展示を年間通じて実施し、利用促進を行った。 【令和８年度・令和９年度の見込】 ・「廃棄指針」に基づいた計画的な資料整理を本格化させ、限られた書架スペースの有効活用を図る。 ・年間1,000冊から3,000冊程度の新規図書整備を継続し、カリキュラムの変更や学生・教員の最新ニーズに迅速に対応する。 | E83: 3 | F83: ・「選書指針」及び「廃棄指針」に基づき、学生の修学支援や地域貢献に資する図書及び資料の体系的整備を図る。 ・学生選書委員による選書や、教員選書、企画展示などに応じた図書整備を行う（１千冊程度）。 | G83: ・資料収集方針に基づき、学生用図書、学科の専門書、シラバスに掲載されている参考書や参考資料等、多様な図書等を体系的に選定し、収集・整理を進めた。また、既存の蔵書についても、図書及び資料の不用決定に関する要領に基づき、利用状況等を勘案し、廃棄指針に基づく適切な見直しを実施することで、蔵書構成の適正化を図った。更には、地域経営学部、情報学部及び大学院の学生８人で構成する学生選書委員会を設置し、８月４日から９月30日まで活動を行い、学生の視点を反映した図書37冊を新たに購入した。これにより、学生ニーズを踏まえた蔵書の充実を図るとともに、図書整備及びメディアセンター運営への学生参加を促進した。これらの取組みの結果、本年度の図書受入数は1,477冊、年度末の蔵書数は91,515冊となった。 ・地域社会に開かれた施設として、綾部中学校２年生の生徒２人に対して、９月18日から９月19日までの二日間、職場体験の機会を提供した。 ・新入生ガイダンス（４月１日）において、福知山市立図書館中央館館長から同図書館の利用方法や配架図書等の紹介を行い、メディアセンターの利用及び関連したサービスの案内を提供した。また、イベントスペースにおいて、６回の企画展示（６月「本屋大賞受賞作」、６月「大学生生活応援Book」、６月「お金」「レポート」、７月「ミステリー特集」、７月～９月「ひとときの涼を・・・」、11月「防災特集」）を行った。 ・メディアセンターに対するニーズ調査を実施し（12月１日から12月24日まで、有効回答数85人）、今後の運営方針と改善策を策定していくための情報を収集した。 | H83: 3
B84: 20 | C84: ・学修に困難を抱えている学生に対して、必要なリメディアル教育を実施する。 | D84: 【令和４年度～令和７年度の総括】 ・ＩＲ委員会において、ＧＰＡや外部アセスメントテストを活用した成績分析を実施した結果、情報学部では、「基礎数学科目」及び「コンピュータプログラミングⅠ・Ⅱ」の未修得が成績不良につながる傾向が見られた。この分析結果を踏まえ、令和６年度カリキュラムにおいて、リメディアル教育として「数学演習Ⅰ・Ⅱ」及び「コンピュータプログラミング演習Ⅰ・Ⅱ」を新設した。令和７年度までの２年間で、「数学演習Ⅰ・Ⅱ」（選択必修科目）は357人、「コンピュータプログラミング演習Ⅰ・Ⅱ」（必修科目）は444人が履修しており、学生の学修段階に応じた支援を行っている。 ・令和７年度から、数理・データサイエンスセンターの学修支援事業として、全学部生を対象に数学力向上のための補習を実施した。学生業務アシスタント（ＴＡ・ＳＡ）が、「微分積分」「線形代数」「数学基礎」「統計学」の履修に必要な高校数学の復習を指導する補習を31回実施し、延べ157人が受講した。 【令和８年度・令和９年度の見込】 ・令和８年度カリキュラムにも、リメディアル科目があるため、引き続き授業実施と履修申請率、修得率、成績分布集計一覧等による状況把握と改善を行う。 | E84: 3 | F84: ・令和６年度の成績にもとづき、令和６年度カリキュラム（情報学部）のリメディアル教育科目について、その教育成果を把握するために履修申請率、修得率、成績分布の測定・把握を行う。 | G84: ・令和６年度に実施した情報学部のリメディアル教育科目（数学演習Ⅰ・Ⅱ）の科目毎、入学年度毎の履修申請率、修得率を計測して比較するとともに、成績分布について学部全体を母集団とした適合度の検定を行い、科目毎、入学年度毎の傾向を把握した。その結果、全体の成績分布に対して両科目の分布が大きく異なり、数学演習Ⅰでは「良」、数学演習Ⅱは「優」が最頻値となるなど、科目間で異なる傾向が見られた。 | H84: 3
B85: 21 | C85: ・学生の下宿確保への支援として、不動産情報の提供と合わせて、福知山市や事業者等との連携により住居確保に取り組む。 | D85: 【令和４年度～令和７年度の総括】 ・学生の住居について問い合わせのある企業や団体に対して、学生の住居状況などを伝え、住居の建築等を依頼している。また近隣の不動産事業者に対しては、ホームページの案内文を最新のものに更新するなどの対応を行った。本学が実施したアンケートの結果によれば、学生の住居については、希望する要件を満たす住居が無い場合は見られるものの、住居の総数が不足している状況は認められなかった。 【令和８年度・令和９年度の見込】 ・これまでの支援に加え、住居の不足感があるのか等の調査を行い、学生の住居確保に取り組む。 | E85: 3 | F85: 本学ホームページに掲載されている不動産情報を含めた一人暮らしに関する案内ページについて、学生生活調査アンケート結果や入学案内等の掲載情報に基づき更新を行う。 | G85: ・令和６年度の学生生活調査アンケートの結果に基づいて、不動産情報を含めた一人暮らしに関するこれまでの情報に加え、住居状況や月々の生活費など、本学学生の住居に関する具体的な情報も本学ウェブサイトで公開した。 | H85: 3
B86: 22 | C86: ②メンタルヘルスを中心とした学生相談体制の整備
C87: ・学生が退学や休学に至る可能性のある課題である心身の健康とりわけメンタルヘルスの維持のため、専門家である校医やカウンセラー等の相談体制の充実を図る。 | D87: 【令和４年度～令和７年度の総括】 ・課題のある学生に対しては、カウンセラーや保健室、関係する教職員が連携をして対応に当たる体制を整備し、特に該当する学生の対応については、関係者による密なミーティングにより状況によっては、医療機関につなげるなど、最適と考えられる対応を行った。その他、保健室での健康相談の実施や、歯科医師会による歯科検診の実施、学内での献血の定期開催するなど学生の心身の健康を保つための活動や啓発の充実を図った。 【令和８年度・令和９年度の見込】 ・今後心理カウンセラーの新規雇用を検討し、カウンセリングの開室日を増やすことなど、学生の相談体制の充実について検討する。 | E87: 3 | F87: ・健康診断の結果を全学生に配布するように変更し、保健室において健康相談に対応する。 ・保健室、カウンセラーと各担当者が連携し、支援が必要な学生への多面的なアプローチを行う。 | G87: ・健康診断の個票を学生に配付し、配付の際に保健室での健康相談の案内を行った。保健室においては、保健師が健康診断結果に基づき、栄養面・生活面に関する指導を個別に実施した。 ・学業面では教務係及び教員、経済面では学生支援係、就職支援ではキャリア支援係、心理面では保健師やカウンセラー等、必要な支援内容に応じて各部署と連携を取りながら多面的な学生の支援に努めた。 | H87: 3
B88: 23 | C88: ・専門家による相談以外にも、教職員による相談および学生同士のピアサポートなどによる、学生が相談しやすい体制を構築する。 | D88: 【令和４年度～令和７年度の総括】 ・履修登録、アルバイト、サークル、一人暮らしの悩み等、新入生が抱える不安解消のため、学生同士で相談を行うピアサポーター体制の構築を行った。ピアサポーターとして、令和４年度：10人、令和５年度：10人、令和６年度：９人、令和７年度：７人の学生が、主に新入生の相談対応にあたった。また、ピアサポーターには事前に研修を実施し、相談者が相談しやすい環境整備を心がけた。担当する事務職員においても、各研修に参加し、研鑚を図っている。 【令和８年度・令和９年度の見込】 ・ピア・サポートの体制については今後の展開を検討中である。学生相談室などの整備を検討しているがハード面の課題が多い。 | E88: 3 | F88: ・ピア・サポーターとカウンセラーが連携することにより、学生がより相談しやすい環境を整備する。 | G88: ・ピア・サポーターは、年度当初に心理カウンセラーによる傾聴スキル講座の受講を通じて、心理カウンセラーとの交流を行っている。これにより担当事務職員はもちろん、傾聴スキル講座を担当した心理カウンセラーと連携しやすい体制の構築を行っている。 ・昨年度の利用した新入生が今年度はピアサポーターとして活動するなど、学生同士による支援の継続が期待される。 | H88: 3
B89: 24 | C89: ③キャリア支援の充実
C90: ・就職率１００％を目指して、就職情報の提供等にとどまらず、学生一人一人が自身の職業観・勤労観を明確にし、幅広い進路の可能性を提示するための取組みを実施する。 | D90: 【令和４年度～令和７年度の総括】 ・早期化、長期化、多様化など就職活動を取り巻く環境は年々大きく変化している。そのため、キャリアコンサルタント資格を有する専任事務職員をはじめ、有資格者に業務委託をし、キャリア支援体制を整えた。本学としては、令和６年３月に情報学部１期生、令和８年３月に大学院地域情報学研究科１期生を輩出した。低学年次から学部や研究科に特化したガイダンスなどの支援を実施し、対策を行った。令和４年度から令和７年度の４年間の就職希望者内定率は98.9％（地域経営学科：99.7％、医療福祉経営学科：98.0％、情報学科：98.6％※令和５年度以降のため３年間）となった。また、就職支援にとどまらず、大学院進学を促進するため、キャリアイベントにおいて研究科長より大学院進学に関する説明を行う機会を設けた。キャリアイベントにおいても、就職活動の動向に合わせ、開催内容を工夫し、学生が最新の情報を得られるように支援体制の構築を図った。京都府や近隣市町と協力した学内業界・企業研究会、学外大型イベント参加のためナビ会社と連携し無料バス運行を実施、公務員試験対策講座の実施、ＡＩの活用等、最新の内容を盛り込んだガイダンスやイベントを実施した。学生が自身の進路に希望を持ち、進路選択を行えるよう、キャリア形成支援を実施している。 【令和８年度・令和９年度の見込】 ・最新の就活動向に考慮しつつ、学生個人の希望に応じた進路選択支援に取り組む。 | E90: 4 | F90: ・大学院生の就職サポート体制およびキャリア支援の観点からメンタルケア等が必要と考えられる学生のサポート体制を整備する。 ・低年次から大学院進学に向けたキャリア観の養成を図る。 | G90: ・キャリア関連資格を有するキャリアカウンセラーに業務委託し、大学院生の就職サポートを行った。また大学院生の就職活動の支援策（進路先と就職活動等を大学に報告することで活動費を一律で支給するもの。）を行った結果、就職希望者13人の内、12人より就職活動に関するアンケートを回収し、後輩に向けた有意義な情報収集が行えた。またメンタルケア等が必要と考えられる学生への対応として、スクールカウンセラー、保健師、ゼミ担当教員、他部署と連携・情報共有し、学生の状況に合わせた支援体制を構築した。また必要に応じて、外部専門機関にリファーし、より専門的な知見から支援を行った。 ・キャリアイベントにおいて、研究科長より大学院進学を案内する機会を設けた。大学院進学をキャリアの選択肢に含められたことで、短期的な就職活動の成果だけでなく、自身の専門性をより高めてから社会に出るという中長期的なキャリア形成の視点を学生に持たせることができた。 ・令和７年度卒業生の就職内定者（学部）は162人（就職希望者の内定率98.2％）、進学者は23人であり、その内訳は、地域経営学部が就職内定者97人（就職内定率100％）及び進学者２人（うち本学大学院２人）、情報学部が就職内定者65人（就職内定率95.6％）及び進学者21人（うち本学大学院19人）であった。 ・また、今年度初めて修了生を輩出した大学院の就職内定者は、13人（就職希望者の内定率100％）、進学者は１人であった。 | H90: 3
B91: 25 | C91: ④国際化支援
C92: ・日本人学生がグローバルな視野を持つために、短期留学プログラムを充実させるとともに、長期留学制度についても確立を図る。 | D92: 【令和４年度～令和７年度の総括】 ・本中期計画の推進にあたって国際センターとしては、まず留学先の候補になる海外大学との交流を進め、包括的学術交流の覚書(ＭＯＵ)を締結している。過去４年間は新規で以下の３大学とＭＯＵを締結した。 ①台湾・国立台中教育大学(令和７年２月、5年間) ②ベトナム・銀行学院大学(令和７年２月、5年間) ③台湾・静宜大学(令和７年６月、5年間) また、これまでＭＯＵを締結していた２大学については交流の内容を深めながら期限を延長している。 ①オーストラリア・Edith Cowan University(令和５年12月に更新、５年間) ②中国・西南交通大学公共管理学院(地域経営学部との学部間協定)(令和７年９月に更新、５年間) 以下の大学については、ＭＯＵを継続中で令和８年６月に更新予定。 ①オーストラリア・Deakin University 次に、国際センターが本学学生のための留学プログラムを充実させている。現在、オーストラリアのDeakin University、台湾の静宜大学に滞在し、それぞれ英語と中国語を学ぶという短期語学留学プログラムを実施している。２つのプログラムはそれぞれ現地での授業時間数と内容が本学基準を満たすため、語学科目群科目として「海外語学研修Ⅰ」と「海外語学研修II」の単位認定を令和６年度から実施している。滞在期間が１ヶ月間60授業時間以上の英語プログラムは２科目、２週間30授業時間以上の中国語プログラムは１科目(最大２回まで)の単位が認定される。なお、両方の語学留学プログラムで、株式会社PILLAR提供の基金より、参加費用の２割程度の補助金が参加した学生に支給されている。 Deakin Universityで令和４年度に初めて実施し、令和７年度までの４年間で延べ25人の学生が参加している。静宜大学での中国語プログラムは令和５年度より実施しており、３年間で延べ17人の学生が参加している。 半期から１年間の単位履修を伴う交換留学協定については、台湾の静宜大学と国立台中教育大学と交渉を進めている最中であるが、前向きの意向を確認している。 一方、本学学生が英語に慣れ親しんでもらい、グローバルな視野を養成するために、国際センターでは令和３年度より英語サロンを開催している。授業期間内に約月１回のペースで開催している。近隣地域のＡＬＴ(外国語指導助手)をネイティブ講師として招き、海外の大学の教員、学生も誘って開催している。参加者はあらかじめテーマに沿ったプレゼン資料を作成し、当日は挙手制で、英語で交流できる場を提供した。令和４年度より一般市民にも開放し、学生や住民の英会話力や異文化理解の向上に寄与した。令和４年度〜令和７年度の４年間は、延べ28回の開催、延べ参加者数は、本学教員が54人、本学事務職員が16人、ＡＬＴが60人、本学学生が123人、市民が101人、海外(オンライン)からは243人だった。 英語サロン以外にも、本学学生の英語学習に対する意識向上につなげようと、英語によるスピーチコンテストを毎年の12月に開催している。国際センターが事前に用意したスクリプトを朗読または暗唱する形で、参加する学生の英語力、表現力を評価する形で、最優秀賞、優秀賞、准優秀賞で表彰する。それ以外の参加者は参加賞を授与する。審査員は国際センターの教職員や英語科目の教員、英語が堪能な本学事務職員が担当する。令和３年度の初めてのコンテストはコロナ禍の影響でオンラインで開催され、学生７人が参加した。令和４年度は中止になったが、令和５年度より対面での開催になった。令和５年度〜令和７年度の延べ参加学生数は29人だった。 ４年間の総括として、オーストラリア及び台湾を行き先とする２つの短期語学留学プログラムを立ち上げ、両プログラムを合わせて延べ42人の学生が参加した。留学プログラム参加後には、学生が積極的に英語によるスピーチコンテストへ参加したり、海外からの学生受け入れ時にバディを務めたりするなど、海外への関心や意識の向上が確認できている。さらに、参加学生の中から、その後１年間の留学を目的として文部科学省のトビタテ！留学JAPAN奨学金を獲得した学生も現れている。また、語学学習への意識向上を目的とした取り組みも継続的に実施してきた。短期留学プログラム参加者から、毎年のように長期留学プログラムに関する問い合わせが寄せられており、長期留学への関心や参加意欲の高まりが見られる。さらに、海外大学との包括的学術交流覚書の新規締結及び更新に際しては、この４年間に締結・更新したすべての覚書において、将来的な交換留学プログラムの実施検討を明文化している。今後の交換留学協定の実現に向けた基盤整備を進めている。 【令和８年度・令和９年度の見込】 ・学術交流覚書を締結している海外の大学等と、交換留学の実施に向けた具体的事項について協議を進めるうえで、協定を締結し、実施まで進めたいと考えている。短期語学留学プログラム、英語によるスピーチコンテスト、英語サロンなどの国際交流イベントは継続的に実施していく。 | E92: 3 | F92: ・学生・市民を交えた国際交流イベントを実施する。 ・海外の大学と単位互換協定の交渉を行う。 | G92: ・英語による交流イベントの英語サロンを４月25日、５月30日、６月27日、10月31日、11月28日、12月19日、１月23日の計７回実施した。延べ参加者は本学教員13人、本学職員２人、ネイティブ講師16人、学生11人、市民41人、海外の参加者52人であった。 ・福知山市教育委員会主催の中学生短期留学プログラム(８月６日から８月15日、カナダ・バンクーバー)に本学教員２人が協力した。５月７日及び６月11日の２回の事前教育会を担当し、８月30日に開催された成果発表会にも出席した。 ・国際センターが主催でスピーチコンテストを開催した。事前に用意したスクリプトを朗読または暗唱する形で本学学生８人が英語によるスピーチコンテストに参加した。その中から、最優秀賞、優秀賞、準優秀賞を国際センター担当の教員３人と職員１人が選出した。なお、12月４日に事前のリハーサルを行った。 ・本学の学生が長期留学できるよう、台湾の静宜大学と国立台中教育大学の担当部署と単位互換協定の交渉を進めており、すでに先方の了承を得ている。 令和６年度の３月に実施した台湾の静宜大学への短期語学留学プログラムの成果報告会を４月16日に実施した。 ・オーストラリアのDeakin Universityへの短期語学留学プログラムを８月12日から９月15日の間に実施した。４月９日に参加募集の説明会を実施し、５月14日から７月30日までの毎週水曜日の昼休みに参加者のための英語レッスンとオリエンテーションを実施した。参加した学生は５人であった。 ・台湾の静宜大学への短期語学留学プログラムを３月８日から３月21日に実施した。10月29日に参加募集の説明会を実施した。参加した学生は６人であった。 ・先輩による文部科学省の派遣留学生プログラム「トビタテ！留学JAPAN」の説明会を11月５日に実施した。 | H92: 3
B95: 26 | C95: ・外国人留学生の志望者と入学者を増加させるために必要な入試制度や学修・生活支援制度を改善する。 | D95: 【令和４年度～令和７年度の総括】 ・情報学部では、令和７年度入学者選抜から私費外国人留学生選抜を導入した。大学院においては令和８年度入学者選抜から一般選抜の募集人員に外国人留学生を含めて実施することを確認し、募集を行った。しかし、いずれの選抜区分においても出願者はなかった。地域経営学部では、以前から私費外国人留学生選抜を実施しているが、受験者及び合格者はいたものの、入学者はなかった。 ・外国人留学生の入学者の増加につながることを期待し、国際センターは学術交流協定校を増やしつつ、協定校からの短期留学生を受け入れるプログラムも実施している。令和５年11月末にEdith Cowan University(ＥＣＵ)との覚書を更新した際に両大学の交換留学プログラムを企画する内容が盛り込まれた。この合意に基づき、ＥＣＵから本学へ学生を招待するプログラムを先方に提示し、ＥＣＵ学内で募集をしたところ、心理学科３年次の学生１人が応募した。令和６年１月に来日し、帰国するまでの３週間は、本学では英語科目でゲストとして協力してもらい、受入れゼミの活動にも参加した。また、福知山市と近隣地域の施設の見学や文化体験も行った。さらに、小学校でも英語の授業にゲストティーチャーとして参加した。滞在期間は福知山市内でホームステイを行い、受け入れる市民の３家族と国際交流を行った。令和７年１月の来日をめざして、２回目のプログラムを計画したが、参加者の都合により中止になった。国際センターにおける検討の結果、冬期よりも夏期の実施が適当であると判断し、令和７年度については夏期実施へと切り替えた。令和７年４月に交流のある海外の５大学(静宜大学、国立台中教育大学、Deakin University、ＥＣＵ、ベトナム銀行学院大学)へ募集を行ったところ、静宜大学からは３人(希望者８人からの台湾側の選考)、国立台中教育大学からは１人の学生の参加申し込みがあったため、令和７年７月に２週間の短期留学プログラムを実施した。期間内に留学生は、福知山市内でホームステイをしながら、日本語研究、本学の授業体験、福知山盆踊り等の文化体験、本学の学生との交流、舞鶴市、福知山市夜久野町への小旅行を実施した。なお、本学学生のための短期語学留学のプログラムを実施する際は、引率の教員が留学先の国際交流担当経由で本学の入学案内と大学院の宣伝用チラシを配布した。 また、半期から１年間の単位履修を伴う交換留学協定を台湾の静宜大学、国立台中教育大学と交渉している。学生が行き来する双方向の協定のため、締結後に毎年数人の交換留学生が本学に滞在する見込みである。 【令和８年度・令和９年度の見込】 ・双方向の交換留学協定を締結し、実施をめざしている。実現する場合、毎年数人程度の留学生を本学に受け入れる見込みである。 | E95: 3 | F95: ・大学院入試では一般選抜の募集人員に外国人留学生を含めて実施する。 ・海外の大学生を受け入れる短期留学プログラムを実施する。 ・海外の大学からの交換留学生の受入制度を整備する。 | G95: ・大学院の入学試験を実施したが、外国人留学生の志願者はいなかった。 ・外国人留学生の志願者及び入学者を増加に向けて、昨年度から２週間の短期留学生を学術交流協定を締結している海外の大学から受け入れている。これまでの受入れ人数は、令和６年１月に１人、令和７年７月に２大学から４人となっている。これらの参加学生が将来大学院生として戻るか、帰国後の口コミが呼び水になり、本学大学院への志願者の増加につなげたい。 ・大学院のカリキュラムと入学方法などをまとめた中国語のチラシを制作し、令和８年度の大学案内とともに、静宜大学(10部)、台中教育大学(10部)、朝陽科技大学(５部)に配布し、関係者に宣伝を依頼した。 ・４月28日締め切りで交流のある海外の５大学(台湾の静宜大学及び国立台中教育大学、オーストラリアのDeakin University及びEdith Cowan University(ＥＣＵ)、ベトナムの銀行学院大学)に募集を掛けたところ、静宜大学からは８人、国立台中教育大学から１人の学生の参加希望があった。静宜大学から学生を受け入れ７月６日から7月19日までの２週間、短期留学プログラムを実施した。期間内に留学生は、市内でホームステイをしながら、日本語研究、本学の授業体験、福知山盆踊りなどの文化体験、本学学生との交流、舞鶴、夜久野への小旅行を実施した。 ・令和８年度も７月に定員４名で実施する予定で、今年度に準備を始めた。２月下旬に４月17日締め切りで台湾の静宜大学及び国立台中教育大学、オーストラリアのDeakin Universityの３大学にプログラムの募集をアナウンスした。 ・実際には長期留学生の受入れ計画や関連予算が十分に整っていない中、可能な範囲で準備を進めている。今年度は、留学生を受け入れる際に最も大きな課題と想定される居住面に着目し、住居に関する制度整備を検討した。福知山市内で学生寮として活用可能な物件を調査した。あわせて、現地見学や通学手段の確認も行い、具体的な受入れ体制について検討を進めた。 | H95: 3
B97: 27 | C97: ⑤学生主導の地域連携活動の強化
C98: ・「学生プロジェクト」等を継続して学生主導の地域連携活動への支援を強化するとともに、公立大学学生ネットワーク主催の LINKtopos（全国公立大学学生大会）への学生派遣を継続する。 | D98: 【令和４年度～令和７年度の総括】 ・令和４年度から令和７年度にかけて、学生の地域連携活動への支援を継続して実施した。令和４年度からは、学生自身が本学での学びを発展的に展開する取組みを支援する「学生プロジェクト」を学内公募し、活動経費等の支援を行った。従来の方式では事業計画と実績の乖離が散見されたことから選定方法を見直し、令和４年度は教務委員による審査方式を導入して応募16件のうち８件を採択した。令和５年度は書類審査とプレゼンテーションによる２段階審査を実施し、応募７件のうち６件を採択した。令和６年度からは、「ＳＴＬ（Students Launch）助成事業」として再編し、北近畿地域連携機構が所管する体制へ移行した。これにより、地域との密接な連携をより重視するとともに、学生の事業化・実装に向けた取組みを後押しする支援へと位置付けを明確化した。令和７年度からは新規・継続の２区分による支援制度を整備した。加えて、地域から寄せられた連携相談（スマホ教室の開催、広報支援等）を学生団体へ直接マッチングする仕組みを構築したことで、学生が地域課題に対して具体的に応答する取組みが進展した。さらに、北近畿地域連携機構が主催する交流イベント等への参画も促進し、学生の活動の認知度向上と地域との接点拡大を図った。採択件数は令和４年度：８件、令和５年度：６件、令和６年度：９件、令和７年度：11件と推移し、令和７年度には４年間で最多となった。 ・奨励金制度に規程を変更し、LINKtoposにより学生が参加しやすい体制に整備を図った。 【令和８年度・令和９年度の見込】 ・ＳＴＬ助成事業の継続・充実を図るとともに、学生団体と地域とのマッチングをさらに深め、学生が主体的に地域課題の解決に取り組む環境の整備を進める。 ・LINKtoposについては、継続して派遣する。 | E98: 4 | F98: ・学生の主体的な地域活動を支援するＳＴＬ助成事業を継続して行うとともに、地域からの相談と学生の活動をつなげることで活動の幅を広げる面での支援も行う。 ・例年に引き続きLINKtopos への学生の派遣を奨励する。 | G98: ・学生主導の地域連携活動を支援するＳＴＬ（Students Launch）助成事業を継続実施した。令和７年度は申請12件に対し11件を採択（継続７件、新規４件）した。採択プロジェクトへの延べ参加学生数は80人を超えた。 令和６年度から導入した新規・継続の２区分による支援制度を継続運用し、学生団体へのきめ細かな支援を実施した。その結果、多くの優れた成果が得られた。具体的には、北近畿の地域資源であるオリーブの未活用素材に着目し、B型就労支援施設と連携して焼き菓子「オリーブフリアン」の企画・開発や、地域資源を活用した商品の魅力発信としての「キキョウブランド」や美容ブランド「しるくのもと」などを活用したイベント企画・出展など顕著な実績を挙げたGrowSpiral、ハコカラをビジネスとして立ち上げたTsunaga Room、及び廃棄ロスを減らしたいという明確な問題意識から始まり、ビジネスにつなげたアグリサーキュラーデザイン in Fukuchiyamaなど、各プロジェクトが傑出した成果を収めた。また、「コラボスペース交流会」や「大学を支援する会」における活動発表機会を設け、ＳＴＬ活動の可視化・発信に努めた。 さらに地域から寄せられた連携相談（スマホ教室の開催や広報支援など）を直接ＳＴＬ団体に依頼・マッチングすることで地域ニーズと学生プロジェクトの効果的な接続を実現した。この取組みにより、大学が対応できる地域連携の幅が一層広がった。 ・LINKtoposの派遣学生を募り11人が参加した。このうち申請を行った10人に奨励金を支出した。 | H98: 4
B100: 第４－１ 教育に関する目標
B101: （６）入学者選抜
B103: 中 期 目 標 | D103: 高大接続と併せて多元的な評価に基づく入学者選抜制度の改革を継続的に進め、アドミッションポリシー（入学者受入方針）に掲げた様々な背景と価値観を持った目的意識や学習意欲が高い学生を確保する。特に北近畿地域からの入学者の増加に努める。
B105: 中期計画 年度計画 番号 | C105: 中期計画 | D105: 業務の実績（中期計画） | E105: 自己評価 | F105: 年度計画 | G105: 業務の実績 | H105: 自己評価
B107: 第４－１ 教育に関する目標を達成するための措置
B108: （６）入学者選抜
B109: 28 | C109: ①優秀で多様な学生を確保するための選抜制度の構築
C110: ・アドミッションポリシーに基づく目的意識や学習意欲の高い優秀で多様な学生を確保するために各学部が中心となって、修学後の状況を検証する。その結果に基づいて、現在の選抜区分の見直しを含めて、優秀な学生を確保するための適切な選抜制度を構築する。 | D110: 【令和４年度～令和７年度の総括】 ・過去４年間、アドミッション・ポリシーの具現化と多角的な評価体制の構築を段階的に進めてきた。 ①学部における入学者選抜では、地域経営学部において令和６年度入学者選抜より一般選抜を除く全選抜区分で個別面接を実施し、書類審査と組み合わせることで志願者の特性や学習意欲を多角的に評価する体制を構築した。情報学部では、令和７年度入学者選抜より新学習指導要領に対応しつつ、一般選抜３教科型を4教科型に変更し、さらに令和８年度入学者選抜より個別試験に数学試験を導入することで、アドミッション・ポリシーが掲げる「数学を中心とした堅固な基礎的学力」を持つ学生の確保を強化した。 ②令和８年度の選抜制度改革（アドミッション・ポリシーの改訂、総合型選抜の導入、募集人員変更等）に際しては、アドミッション・ポリシーの趣旨を具体的な評価内容へと反映させた評価の観点を学生募集要項等で公開した。評価者等への評価観点の一貫性確保を実現するための面接評価票の整備と併せ、客観的で公正性・妥当性の高い選抜運用を体系化した。また、大規模な制度改革に際し、高校教員向け説明会やオープンキャンパスで丁寧な説明を行うことで変更内容の周知徹底を図り、受験者や高校関係者に混乱を招くことなく安定的な移行を実現した。 ③大学院における入学者選抜では、令和５年度の設置認可時より、研究科の方針に基づいた口頭試問・面接での選抜体制を運用し、アドミッション・ポリシーに合致する入学者選抜を継続している。 ④ＣＢＴ（Computer Based Testing）入試導入の可能性については、関連するオンライン研修への参加等を通じて制度動向及び他大学の導入事例に関する情報収集を行った。導入にあたっては、システム運用体制の整備、公平性の確保、費用対効果の検証等が重要であるとの認識を共有した。 ・地域経営学部では、「地域経営学部アセスメントチェックリスト」に基づく教学アセスメントの実施により、修学後の状況を検証した。アドミッションポリシーに基づく目的意識や学習意欲の高い優秀で多様な学生を確保するための検討を重ね、令和８年度入学者選抜より総合型選抜を導入した。 ・情報学部では、１・２年次の学生を対象に担任制度を設け、選抜区分と修学状況との関連についてのデータ取得を始めた。目的意識、学習意欲の高い学生を確保するために、情報セキュリティ、生物・生態分野など教員の専門性を生かした独自性、多様性のあるテーマを幅広く設定し、低学年の段階から学生が多様な地域研究に参加できるカリキュラムによる教育を実施した。さらに、特定の分野に秀でた学生の確保を意識し、令和８年度入学者選抜より総合型選抜を導入した。 ・大学院地域情報学研究科では、設置認可申請書に基づき入学者選抜の実施を適切に行った。また、入学者確保のために社会人受験者向けの試験実施及び入学者支援制度の認定を受けた。 【令和８年度・令和９年度の見込】 ・アドミッション・ポリシーに基づき実施される各選抜区分の整合性や評価の妥当性を継続的に検証し、評価基準を適宜見直すことで、信頼性の高い選抜運用の改善を推進する。 ・ＣＢＴ入試導入の可能性については、全学教育企画室を中心に全学的な視点で検討が継続される予定である。 ・地域経営学部では、アドミッションポリシーに基づく目的意識や学習意欲の高い優秀で多様な学生を確保するために、全学教育企画室と連携し、現在の選抜区分、募集人員、試験問題の見直しを図る。 ・情報学部では、今後も、近隣高校との連携をさらに強化し、学部の多様な研究テーマや活動内容を出張講義等で紹介することで、本学の教育・研究の魅力を高校生に伝え、優秀で多様な学生を確保する取り組みを継続する。特に、アドミッションポリシーに掲げる地域社会に貢献する多様な入学者の受け入れを推進するため、地域社会の多様な関係者と主体的に協働しつつ、学習地域枠の受験者増加を図り、地域エリアからの志願者確保に向けた活動も継続的に進めていく。 ・受験者の定員確保をめざし、アドミッション・ポリシーに従って継続的に学生への受験を促進するとともに、定常の入学者選抜を適切に実施する。 | E110: 4 | F110: ・両学部の入学者選抜において、新たに策定されるアドミッション・ポリシーに基づいた評価可能な総合型選抜を実施する。 ・各選抜区分の募集人員の変更に伴い、実施体制の見直しを行いつつ、適切に実施する。 ・大学院研究科の指示のもと、大学院入学者選抜の適切な体制を検討し、実施する。 ・ＷＥＢ出願・入学手続に関し、入学料収納代行機能を新たに追加した新規システムを導入し、出願者の利便性および入試事務局業務の効率化を図る。 ・令和10 年度以降のＣＢＴ（Computer Based Testing）入試導入の可能性を引き続き検討する。 ・高大連携委員会の提案に基づいて、対象となる高校の事情に即したより効果的な内容の出張講義や支援を行う。北近畿地域の高校に対しては、探究学習支援型の高大連携事業を強化する。 ・入試委員会の下で、定常的なスケジュールに基づく大学院入試を実施する。 ・社会人に対する入試機会拡大のため、大学院の一般入試において、社会人受験生就業先所属長の推薦による口頭試験免除申請受付を行う。 ・大学院の今後のあり方を議論し、それに沿ってアドミッション・ポリシーおよび入試のあり方の検討を開始する。 | G110: ・両学部において、新アドミッション・ポリシーとの整合性を図り、求める能力を評価項目として具体化した評価基準を学生募集要項等で公開し、評価の可視化と透明性の確保を行った。また、定性的な評価となりやすい面接及びプレゼンテーションの評価票を整備することで、評価者の主観によるバラつきを抑制し、多角的な視点から能力を定量的・客観的に把握できる体制を整えた。併せて監督者説明会を実施し、評価基準の具体的な適用方法や採点プロセスの共有を図り、組織的な共有体制を構築した。制度設計から具体的な運用体制整備、評価者の意識統一までを一体的に進めることで、恣意性を排除した透明性の高い「評価可能な総合型選抜」を実現した。 ・各選抜区分の募集人員変更に伴い、学部の選抜方法に応じた実施体制の再構築を行った。地域経営学部では、総合型選抜（二段階選考）に対応するため、監督体制及び試験室運営体制を整備し、事前リハーサルを実施することで運営の確実性を高めた。さらに第１次選考合格者20人の第２次選考に向け、実施体制を整えた。情報学部では、一般選抜前期日程に数学が選択可能となることから、数学専門教員を実施本部に配置するなど統括体制を強化した。これにより、円滑かつ適切に入学者選抜を実施した。 ・大学院地域情報学研究科の方針の下、大学院入学者選抜の実施体制を検討・整備した。受験者数を勘案し、大学院一般選抜第１期を情報学部編入学選抜と同日に設定し、大学院一般選抜第２期を地域経営学部編入学選抜と同日に実施した。特に大学院一般選抜第２期においては大学院入学者選抜（口頭試問、面接）と学部編入学選抜（小論文、面接）を同時進行で実施するという複雑な条件の下、実施体制の整理及び業務分担の明確化を行い、混乱のない安定的かつ円滑な選抜運営を実現した。 ・ＷＥＢ出願・入学手続システムについては、８月までに構築を完了し、出願者への影響が生じることなく新システムを稼働させた。入学料収納代行機能を追加し、さらに大学入試センターとのWEBAPI連携を運用初年度から導入することで、出願者の利便性向上を図った。今年度は初年度構築であったため、入試業務における負荷は大きかったものの、次年度以降の業務効率化に資する成果を得ることができた。 ・令和10年度以降のＣＢＴ入試導入に向け、オンライン研修に参加し、制度動向及び他大学の導入事例を把握した。導入にあたっては、安定した運用体制の整備や公平性確保、費用対効果の検証が重要であるとの知見を得た。 ・地域経営学部及び情報学部では、近隣及び在学生の出身校に対する出張講義、学習支援を行った。今年度は、以下の高校に対し、出張講義、学習支援を行った。 【地域経営学部】 ①出張講義：京都府立福知山高等学校、京都府立大江高等学校、京都共栄学園高等学校、京都府立綾部高等学校、京都府立峰山高等学校、京都府立西乙訓高等学校、京都府立洛西高等学校、兵庫県立川西緑台高等学校、兵庫県立三田祥雲館高等学校、兵庫県立東播磨高等学校、兵庫県立生野高等学校、兵庫県立神戸商業高等学校、兵庫県立高砂南高等学校、兵庫県立三田西陵高等学校、愛媛県立伊予高等学校、京都府立田辺高等学校、徳島県立城北高等学校 ②探究学習支援：京都府立福知山高等学校、京都府立大江高等学校、京都府立宮津天橋高等学校宮津学舎、京都府立宮津天橋高等学校加悦谷学舎、京都府立丹後緑風高等学校久美浜学舎、京都府立鳥羽高等学校、兵庫県立姫路飾西高等学校、兵庫県立生野高等学校、兵庫県立佐用高等学校、兵庫県立八鹿高等学校、香里ヌヴェール学院高等学校、追手門学院高等学校、滋賀県立甲西高等学校、岡山県立林野高等学校、島根県立松江南高等学校 ③講座、教室： （次世代へつなぐ支援のバトンプロジェクト）京都府立福知山高等学校 （新時代に対応した高等学校改革推進事業）日星高等学校 （丹波市議会☆ミライプロジェクト）兵庫県立柏原高等学校、兵庫県立氷上高等学校、兵庫県立氷上西高等学校、兵庫県立氷上特別支援学校 （朝来市公共交通利用促進プロジェクト）兵庫県立生野高等学校 【情報学部】 ①出張講義：福井県立敦賀高等学校、京都府立西舞鶴高等学校、奈良学園高等学校、兵庫県立柏原高等学校、京都府立福知山高等学校、京都府立福知山高等学校三和分校、京都府立工業高等学校、関西大倉高等学校、兵庫県立神戸学園都市高等学校、日星高等学校、福井県立金津高等学校 ②受託研究：西舞鶴高等学校サイエンスキャンプ ③探究学習支援：京都府立西舞鶴高等学校 ④講座、教室： （3Dプリンタ教室）京都府立福知山高等学校、京都府立北嵯峨高等学校、京都府立亀岡高等学校 （みらい学習チュートリアル）京都府立福知山高等学校 （進路相談会）京都府立城南菱創高等学校 これらの高校と連携事業の成果は、京都府立福知山高等学校との包括的な高大連携協定の締結、さらに、京都府立工業高校との共創パートナーシップ・学びの連結に関する協定の締結など、北近畿における実践的教育・研究推進へと深化している。 ・令和８年度入学者向け大学院入試として一般選抜第１期及び第２期を実施した。両者とも定常スケジュールの試験である。選抜の結果、一般選抜第１期及び第２期で合計24人が合格し、21人が入学した。このことから、定常スケジュールに基づき定員確保可能な試験の運用が適切になされていることが確認できた。 ・令和８年度一般選抜において、社会人受験者に対する口頭試験免除申請の受付を実施した。なお、申請者はなかった。また、次年度以降の社会人受験者への周知を目的とし、社会人受験者向けのリーフレットを作成した。 今後、地域企業と共催するイベントや説明会などで当該リーフレットを配布することにより潜在的な社会人受験者の確保をめざす。 ・令和８年度入学者の一般選抜の実施状況（一般選抜合格者24人、入学手続き実施者21人）を鑑み、定員の20名を充足しており、今後も定員充足に足る状況が継続可能であると判断したため、現在のアドミッション・ポリシーを堅持して運用するものとした。 | H110: 4
B113: 29 | C113: ②入学志願者数の確保
C114: ・毎年度の定員充足率を１００％にするだけではなく、入試全体において受験倍率（受験者数／合格者数）が第２期中期計画期間中の平均で２倍以上となることを目指す。 | D114: 【令和４年度～令和７年度の総括】 ・地域経営学部では、本学及び地域経営学部の認知度を高めるため、高校への出張講義を継続的に行い、また、オープンキャンパスでは参加する高校生だけではなく、保護者にも訴求するように本学の地域協働型教育や地域経営学部のカリキュラムについての説明や質疑応答を行った。 ・情報学部では、開学後10年という本学の沿革を踏まえ、地元地域を中心とした認知度の向上を重要とし、地域との連携、小中学生向け、社会人向けの公開講座等、継続的な活動を進めてきた。オープンキャンパス、ミニオープンキャンパスに参加者も増えてきていることから、本学の認知度は増大していると思われる。 ・大学院地域情報学研究科では、定員確保をめざして、在学している学部生及びその保護者への積極的な大学院進学の勧奨、社会人及び近隣大学に対する大学院のアピールを続けた。結果として令和８年度時点で入学定員を確保することができた。 ・これまで定員充足率は100％を確保しているが、受験倍率は決して安心できる倍率が保持できているわけではない。志願者獲得に向けた活動と、受験者が本学を志願することへの因果関係を証明することは難しいが、出張講義、探究支援、キャンパス見学等の高大連携活動を通じて高校と継続的な関係を構築するなど効果があると考えられる活動を行うことで、主に学校推薦型選抜の志願者確保に努めている。出願実績高校を中心に訪問を継続するなど工夫を凝らす中で、広報活動は効率的に実施できている。 受験倍率（受験者数／合格者数）の推移は次のとおり。 令和５年度 2.5倍 令和６年度 2.5倍 令和７年度 2.3倍 令和８年度 1.8倍 【令和８年度・令和９年度の見込】 ・高校からの要望と教員とのスケジュール調整に課題が残るものの、同程度の連携活動が実施できる見込みである。また、キャンパス見学を、高校からの依頼に基づき実施に向け調整を行う。本学担当職員の減員により、訪問体制の維持が困難になっている。委託者の協力を得て、体制維持に努める。 ・地域経営学部では、高大連携委員会との連携により、北近畿地域をはじめとする本学への入学に高い関心を示す高校を調査し、出張講義などを通じて高校１年生の段階から本学の教育、研究を知ってもらう活動を実施する。 ・情報学部では、本学の志願者を増やすために、地元の高校との連携は不可欠であり、近隣高校との連携を深めていく。また、将来を見据えた小中学生向けの公開講座、福知山に大学があることを社会的に認知していただける教育・研究、地域協働活動の活性化を計っていく。 ・大学院地域情報学研究科では、在学している学部生及びその保護者への積極的な大学院進学の勧奨、社会人及び近隣大学に対する大学院のアピールを続け、定員が充足できるように入学者の確保をめざす。 | E114: 3 | F114: ・学部の安定的な入学志願者確保につなげるべく、北近畿を中心に出張講義や探究学習サポート等の高大連携活動を強化する。 ・北陸、東海以西の高校を訪問し、入学志願者確保のための広報活動を継続する。 ・高大連携のイベントやオープンキャンパスなどを通じて本学部のアピールを行う。 ・大学院の定員充足を目指し、潜在的な受験生へのアピールのために近隣工業高等専門学校および北近畿企業などの訪問および研究交流を行う。 ・社会人に対する就学機会拡大のため、大学院の長期履修制度の運用を開始する。 | G114: ・地域経営学部15件、情報学部29件（合計44件）の出張講義を実施したほか、探究学習のサポート等を33件行った。また、５校の本学見学を受け入れ、うち３校には模擬授業を合わせて提供した。 高校の希望日や本学の教員の授業の都合などにより件数を増やすことは困難であったが、高校とのコミュニケーションでお互いの理解を深めて調整した結果、昨年度と同等の活動数となった。 ・のべ1,378校の高校を訪問し、広報に努めた（本学職員３人208校、委託３人1,170校）。 少人数の職員では訪問数には限界があるが、訪問を進めながら職員間で高校の反応や本学の志望状況の情報を共有し、訪問先の地域やターゲットを調整しながら広報に努めた。 ・オープンキャンパスにおいて、研究室見学を実施し、多くの訪問者があった。11月には大学祭に合わせてミニ・オープンキャンパスが実施され、その際にも学内見学、バーチャルキャンパスなど、情報学部の特性を活かした企画により、本学部の魅力を伝えた。 ・受験者の充足状況と諸学校の潜在的な進学ニーズを踏まえて再検討し、もともと想定していた工業高等専門学校だけではなく近隣の大学院を有さない大学への広報及び研究交流活動にも重点を置く方向で検討を進めた。それを踏まえ、具体的な実績として、大阪府にある大和大学への訪問を行い、大学院の周知及び広報活動を実施した。 ・社会人学生向けのアピールの一環として、福知山市内で行われた「北近畿デジタルパーク」に出展し、学生及び教員の研究活動の展示により大学院における教育研究活動の周知及び広報活動を行った。 ・大学院における社会人を主な対象とした長期履修制度の運用を開始した。なお、初年度の制度利用者はなかった。また、次年度以降の社会人受験者への周知を目的とし、社会人受験者向けのリーフレットを作成した。今後、地域企業と共催するイベントや説明会などで当該リーフレットを配布することにより潜在的な社会人受験者の確保をめざす。 | H114: 3
B116: 30 | C116: ・高校訪問やオープンキャンパス等の入試広報活動だけではなく、高校生に本学の特色を十分に知ってもらった上で志願してもらうための「出張講義」や本学への訪問の機会等を充実させる。 | D116: 【令和４年度～令和７年度の総括】 ・計画は順調に進捗している。高大連携の窓口を一本化したことにより、出張講義等の連携活動が円滑に実施できるようになった。オープンキャンパスの開催を夏のみから令和７年度には夏・秋の２回とし、高校生に本学の特色を知らせる機会を増加させた。 出張講義を実施（令和７年度：44件）したほか、探究学習のサポート等（令和７年度：33件）を行った。また本学の見学を受け入れ、模擬授業も提供するなど、本学への訪問や本学に対する理解を深める機会の充実に努めた。 【令和８年度・令和９年度の見込】 ・高校からの要望と教員とのスケジュール調整に課題が残るものの、同程度の連携活動が実施できる見込みである。 各オープンキャンパスの開催内容の充実を図りながら、同規模の開催を維持できる見込みである。 | E116: 3 | F116: ・教員が提供する出張講義テーマをわかりやすくまとめ、北近畿の高校や京阪神・北陸等の高校に案内を行う。 ・夏季に加え、秋季にミニ・オープンキャンパスを開催し、本学の魅力を高校生等に伝える機会を増加させる。 | G116: ・教員の出張講義テーマをわかりやすくまとめた冊子を製作し、北近畿や京阪神・北陸等の高等学校に案内を行った。結果として、今年度は44件の出張講義を実施した。 ・７月20日に夏季オープンキャンパスを開催し、高校生と付添者を合わせて過去最高の731人の参加があった。事後アンケートでは満足・やや満足との回答が93.1％あり、当初の目標を達成した。また、11月１日に初めてとなる秋季ミニ・オープンキャンパスを大学祭と同時開催し、のべ145人の参加者を集めた。低学年の参加が多いと予想していたが、高校３年生も参加し、遠方からの参加もあった。 | H116: 3
B117: 31 | C117: ・１８歳人口の減少やコロナ禍を経た志願者状況の変化を踏まえて、高校等へのヒアリングなど入学志願者確保のための新たな方策を検討し、実施する。 | D117: 【令和４年度～令和７年度の総括】 ・北近畿の高校の教員との連携を密にするため、高校訪問時にヒアリングを実施し、高校側が抱える課題を把握した。一部の高校とは、ヒアリング通じて把握した課題への対策を検討し、本学のリソースを活用した３Dプリンタの実習を行うなど、ニーズに合わせた講義を実施した。また、高校生の大学への興味関心を引き出すため、出張講義など大学での学習に触れる機会を確保した。 さらに、入試に関するヒアリングの結果を踏まえ、令和８年度入学者選抜から「総合型選抜」を導入する運びとなった。 【令和８年度・令和９年度の見込】 ・高校からの要望と教員とのスケジュール調整に課題が残るものの、同程度の連携活動が実施できる見込みである。 ・今後の入学志願者確保のための方策については、全学教育企画室を中心に全学的な視点で検討が継続される予定である。 | E117: 3 | F117: ・高校へのヒアリング等を通じて収集した情報を基に、志願者確保のための活動強化を検討する。 ・北近畿を中心に、本学の特徴を活かした出張講義や高校の探究学習等への関わりを深める。 | G117: ・高校訪問等におけるヒアリング結果や、総合型選抜の出願状況が多いことを踏まえ、志願者は早期の選抜を選ぶ傾向があると判断した。これに基づき、令和９年度以降の学生募集の改善について、募集定員の変更などの案を策定し、入試委員会との協議を実施した。当該検討結果は、次年度に全学教育企画室における協議へと引き継ぐこととした。 ・北近畿の高校に対して、出張講義24件、探究活動支援等25件の取組みに講師を派遣した。本学教員が授業や取組みに参加し、大学の知見を提供することで、高校の教員及び生徒との関わりを深めた。 | H117: 3
B118: 32 | C118: ③北近畿地域内高校との関係強化
C119: ・北近畿地域（入学者選抜においては口丹地域を含む。）からの優秀な入学者が第２期中期計画期間中に学生定員の２０％以上となることを目指し、当該地域の高校等との関係を強化させることによって、最適な選抜制度を構築する。 | D119: 【令和４年度～令和７年度の総括】 ・高校との連携強化を推進してきたことで、京都府北部地域の理系高校生による研究発表会「海の京都サイエンスガーデン」を本学内で実施したことに加え、連携協定締結校の京都府立福知山高等学校の生徒が本学の能登半島地震災害ボランティア活動に参加するなど高校との連携活動の幅を広げることができた。さらに京都府立工業高等学校とも連携協定を締結できた。これらの関係性の中で、高校へのヒアリングを通じて本学を志望する生徒の状況を把握し、令和８年度入学者選抜では総合型選抜を導入した。 北近畿地域からの入学者数の推移は次のとおり。 令和５年度 26人（12.4％） 令和６年度 33人（14.9％） 令和７年度 40人（18.0％） 令和８年度 30人（13.0％） 【令和８年度・令和９年度の見込】 ・連携協定を締結した２校との多様な取り組みを行う見込みである。また、連携協定締結校との関係を強化し、高校生が大学を知り進学を意識してもらうこと等で志願者確保に努める。 | E119: 3 | F119: ・北近畿の高校の取組みに協力し、高大連携となるイベント等の強化を継続する。 ・学生募集の観点から、志願者確保のために、北近畿地域内の高校との関係強化に向けた活動を行う。 | G119: ・京都府北部地域の理系高校生によるポスターセッションを本学内で開催することに協力した。「府立高校サイエンスネットワーク事業」に参画する高校（京都府立西舞鶴高等学校、京都府立福知山高等学校、京都府立宮津天橋高等学校）と京都府立峰山高等学校の生徒約100人が参加し、大学生・教員同席のもと発表を行うことで高大連携を促進した。本学からは学生６人がポスター発表を実施し、情報学部の教員４人が参加するなど、交流の場を創出した。 ・北近畿の高校との関係性を深める取組みの中で、京都府立工業高等学校と新たに連携協定を締結した。また、昨年度に連携協定を締結した京都府立福知山高等学校とは、本学主催の能登半島地震災害ボランティア活動に高校生の参画を得るなど、連携の実践例を創出した。 | H119: 3
B121: 第４－２ 研究に関する目標
B122: （１）研究水準及び成果等
B124: 中 期 目 標 | D124: 様々な地域課題の解決に貢献する「福知山モデル」の具現化に向け、高度な地域協働型の研究を推進し、その成果を地域社会に還元する。
B126: 中期計画 年度計画 番号 | C126: 中期計画 | D126: 業務の実績（中期計画） | E126: 自己評価 | F126: 年度計画 | G126: 業務の実績 | H126: 自己評価
B128: 第４－２ 研究に関する目標を達成するための措置
B129: （１）研究水準及び成果等
B130: 33 | C130: ①研究における「福知山モデル」の提示
C131: ・個々の教員の自発的な研究だけでなく、学内外との共同研究により、本学の特色である「地域協働型研究」の実践を積み重ねる。そのことにより、代表的実践例とその理論的背景を「福知山モデル」として取りまとめて提示する。 | D131: 【令和４年度～令和７年度の総括】 ・情報学部を中核とした文理連携による地域協働型研究のさらなる発展を目的として令和６年度に大学院を開設し、福知山市をはじめとする北近畿地域との協働のもと、地域を巻き込んだ実践的なプロジェクト及び研究活動を推進する体制基盤を構築した。北近畿地域の企業を含む国内外の企業との共同研究を積極的に進めるとともに、産業界やＮＰＯ等の地域組織との連携を強化し、地域課題の解決に向けた取組みを推進した。 ・本学教員の多様な専門領域を活かした個々の研究に加え、小規模大学としての機動性を活かし、地域課題に向けた学内外との共同研究（４年間で37件7,894千円）に取り組み、本学の特色である「地域協働型研究」の実践を積み重ねた。地域防災研究センターによる中小河川における雨量観測ネットワークの構築及びデータ分析、市街地の浸水想定区域における住民の防災意識調査二次分析、消防活動におけるＡＩ支援、数理・データサイエンスセンターによる福知山ラーニングイノベーション・プロジェクト等の附属機関における研究活動や、両学部の教員が参画する「ＡＩが介護保険行政を代行する際のルールに関する研究」、内閣府戦略的イノベーション創造プログラム（ＳＩＰ）におけるフィールドワーク拠点とした「学校組織レジリエンス」等、地域社会の基盤に関わる課題を中心に共同研究を展開した。これらの取組を通じて、地域課題を起点として研究が発展し、その成果が地域に還元される循環を形成するとともに、地域と大学が相互に発展する枠組みとして「福知山モデル」の代表的実践例の蓄積を図った。 ・これまでの取組みに関して、執行会議における議論を通じて福知山モデルの具体化を進め、中間整理を行うなど、研究における「福知山モデル」の具現化を進めた。 【令和８年度・令和９年度の見込】 ・「福知山モデル」については、中間報告案を基に内容の精緻化を進め、地域協働型研究の実践例と理論的背景との対応関係を整理した上で、第２期中期目標期間中に提示する。 | E131: 3 | F131: ・学内外との共同研究を実施するとともに、これまでの取組みを振り返り、「福知山モデル」に繋がる具体例を整理しながら、研究における「福知山モデル」の柱となりうる特徴を中間報告として取りまとめる。 | G131: ・北近畿地域連携機構のリエゾン機能を活用し、民間企業、自治体、研究機関等との連携による共同研究を推進した。令和７年度は、自治体との持続可能なまちづくり調査研究、安心・安全なまちづくりに資するデジタルコンテンツの制作、地域資料のデジタル化、土壌水分量の可視化を目的としたＩｏＴの研究等、12件（受入総額219万円）の共同研究を実施し、地域課題を起点に着想された地域協働型の研究活動を展開した。 ・第２期中期目標期間中における「福知山モデル」の構築に向け、同モデルの特徴を学長がまとめた中間報告案について執行会議で確認した。理論的フレームワークを中心に議論を深め、長期的な視点に立ったモデルの構築に向けて次年度以降も検討を継続していくことを確認した。 | H131: 3
B132: 34 | C132: ②「数理・データサイエンス教育研究センター」（仮称）の設置
C133: ・現行の「数理・データサイエンス教育研究拠点」を発展させ、「数理・データサイエンス教育研究センター」（仮称）を本学の附属機関として設置し、数理・データサイエンスの理論研究を行うとともに、当該分野に基づく手法を地域協働型教育研究のなかで機能させることを目指す。 | D133: 【令和４年度～令和７年度の総括】 ・令和４年度に福知山公立大学に数理・データサイエンスセンターを設置した。 ・令和４年から３年間で、特任研究員１人を中心に数理科学分野の基礎研究を行い、量子ウォークの性質に関する論文２編を発表した。 ・令和７年度には、特任研究員が行った福知山市のふるさと納税に関する口コミを分析した研究成果を発表した。 ・令和５年度から毎年「福知山数理・データサイエンス研究会」を開催し、本学学生の数理・データサイエンス分野の研究発表の機会を創出するとともに、外部から講師の講演を企画し、同分野の学術交流を深めた。 ・令和３年度に本学の数理・データサイエンス・ＡＩ教育プログラムリテラシーレベルが文部科学省の認定プログラムとして認められた。 ・令和４年度に情報学部のカリキュラムの中に、数理・データサイエンス・ＡＩ教育プログラム応用基礎レベルを設定し、同プログラムが文部科学省の認定プログラムとして認められた。 ・令和８年度からはじまる本学の新しい学士課程のカリキュラムにおいて、基盤教育科目の情報科目群に数理・データサイエンス・ＡＩ教育プログラムリテラシーレベルに対応する科目を配置し、地域協働演習科目との連携をはかる準備が整った。 【令和８年度・令和９年度の見込】 ・リテラシーレベルの数理・データサイエンス・ＡＩ教育プログラムは、情報学を基盤とした地域協働型教育の一翼を担うため、履修認定の合格率の向上に取り組む。 応用基礎レベルの教育の効果を評価し、地域経営学部における展開が可能か否か判断する。可能であればプログラムの提供法について、他大学の事例などを調査し、実施方法を提案する。 ・特任研究員による研究活動を継続し、地域社会に関わる種々のデータ分析を行い、ステークホルダに報告する。 | E133: 3 | F133: ・数理・データサイエンス・ＡＩモデルカリキュラム（リテラシーレベル）の認定者数増のため、履修の推奨活動を行う。 ・数理・データサイエンス・ＡＩモデルカリキュラム（リテラシーレベル）の必修化も視野に、学習支援体制を検討する。 ・数理・データサイエンス・ＡＩモデルカリキュラムの応用基礎コースの履修を情報学部の協力を得て推進する。 ・学内向けのデータ分析スキル向上策について引き続き検討する。 | G133: ・前学期のオリエンテーションで数理・データサイエンス・ＡＩ教育プログラムについて説明を行い、履修者数増に努めた。 リテラシーレベルについては令和７年度は132人が認定を受けた。内訳は情報学部101人、地域経営学部31人であった。 ・令和８年度からのカリキュラムでは、基盤教育科目の情報科目群の２科目「情報と社会（必修科目）」と「データサイエンス（必履修科目）」でリテラシーレベルを構成し、必履修化を実現した。必履修にすることで、リテラシーレベルの認定者数が増加すると期待できる。 ・応用基礎レベルは情報学部を対象としている。応用基礎レベルの認定者数は令和７年度の前学期終了時点で在籍者のうち４人があらたに認定されている。 ・今年度はExploratoryを試用した。このアプリケーションは、探索的データ分析に強みがありデータ可視化にも優れることから、Institutional Researchにおいては、Tableauとともに利用が進んでいる。令和７年度は導入説明を受け、導入の可能性を検討した。 しかし、Microsoft365が全学導入されることが決まったことから、BIツールとしては、今後はPower BIの活用が想定されるため、学内で個々にデータ分析を行う際に用いることに適したアプリケーションの選定は終了する。 | H133: 3
B134: 35 | C134: ③学際的な地域協働型研究の推進
C135: ・本学教員の学術的バックグラウンドの多様性を活かし、地域の課題の発見と課題解決に資する学際的な地域協働型研究を推し進める。 | D135: 【令和４年度～令和７年度の総括】 ・地域経営学部では、地域経営学部と情報学部の教員が共同して科研費による学術研究を実施するとともに、地域経営学部を卒業した地域情報学研究科の大学院生の研究指導を実施するなど、文理融合による学際的な地域協働型研究を推進した。 また、情報学を基盤とした地域協働型教育の一環として、地域経営学部と情報学部の１年生が共に学ぶ基盤教育科目である地域協働演習の開講にあたり、福知山市との協働による各クラス（チーム）のテーマの検討を通じて、地域課題の解決に資する文理融合型の実践的な研究テーマの探索を行った。 ・情報学部では、本学教員の学術的バックグラウンドの多様性を活かし、地域の課題の発見と課題解決に資する学際的な地域協働型研究が進められた。教員の専門分野を活かした地域研究の一環として、オリジナルの部品、機材を３Dプリンタなどにより製作するものづくり工房FabLabの活動、地域イベントにおける音楽と情報技術をテーマとしたインタラクティブ作品の出展、情報技術を利用した本地域の生物・生態調査、研究が実施された。例えば、 ①京都未来人材育成プロジェクト：丹波ウルシ苗木の育苗環境と根系成長状況の計測 ②京都未来人材育成プロジェクト：大江山パワーロード観光ガイド 知の継承プロジェクト ③観光情報学会第29回研究発表会：トレンドワードを用いた地域 ＰＲ 動画自動生成について ④第３回みすずフェスタ和田山特別支援学校（ＤＸでつながるワトクの学び）音のとびらを開く会 in ふくくるさんぽ（新町商店街） などがある。さらに、学生の関わった地域協働型研究の成果は令和７年度に第１期生が修了した大学院の修士論文やプロジェクト報告書として報告されたものもある。具体的には、 ①大江地域でのコミュニティ活動におけるＤＸの推進に関するプロジェクト ②地域観光資源への興味関心向上のためのインタラクティブシステムの開発 などがあり、今後、ますますの活動推進が期待できる。 ・大学院地域情報学研究科では、プロジェクトコースがめざした地域課題に関する問題解決に資する活動を行った学生が令和７年度に１期生として修了し、地域協働研究の成果を地域に還元する基盤の構築が出来ていることが確認できた。 【令和８年度・令和９年度の見込】 ・令和８年度カリキュラムにおいて、両学部及び基盤教育院と連携した地域協働演習が開講されることから、両学部の学生が連携する新しいプロジェクトの実施が期待できる。また、情報学部では、現在、地域協働型の研究、プロジェクトが進められており、今後も多くの成果が期待できる。 ・大学院地域情報学研究科では、継続的に地域協働研究を推し進め、大学院として学生が地域に寄り添った形で研究・プロジェクトを実施できるように支援しつつ、その成果を適切に地域に還元できるようにすることをめざす。 | E135: 4 | F135: ・地域経営学部では、学際的な地域協働型研究を推し進めるため、新たな基盤教育の検討を通じて、地域課題の解決に資する文理融合型の実践的な研究テーマに、地域経営学部と情報学部が共同で取り組めるよう、テーマ探索を継続する。 ・情報学部では、教員の専門性を活かした地域研究の取組みを支援し、地域協働型研究を推進する。 ・地域情報学研究科では、学部から行われてきた地域課題に対する研究を継続するなど、大学院での知をベースとした地域協働型研究を推進する。 | G135: ・地域経営学部と情報学部の教員で構成された専門委員会において、情報学を基盤とした地域協働型教育の一環として、地域経営学部と情報学部の１年生が共に学ぶ基盤教育科目である「地域協働演習」の開講にあたり、各クラスのテーマの検討を通じて、地域課題の解決に資する文理融合型の実践的な研究テーマの探索を行った。 実際に検討された具体的な研究テーマは、以下のとおりである。 ①街の賑わい計測（福知⼭市内の観光施設における賑わいや混雑度合いに関するデータを収集し、可視化する ） ②集まりと場づくり（テクノロジーを用いて、福知山市の公民館を始めとした地域住民が集う公共施設の利用実態の分析を行い可視化する） ③外国人が暮らしやすいまちづくり（データやＩＣＴを活用して外国人が利用する施設の案内等の課題を発見し、外国人にとってわかりやすく魅力的な情報の表示や発信の提案を行う） ④空き家と住環境（福知山市の空き家に関する調査結果の分析を行うことによって、福知山市の空家状況の経時変化を明らかにする） ⑤市民課窓口の混雑状況（福知山市役所市民課窓口の混雑状況を調査し、カレンダー情報（例：月、日、曜日、祝日など）との相関を分析する。得られた相関関係をもとに、混雑傾向を明らかにし、その分析結果を可視化する ） ⑥環境保全と生物多様性（福知山市内の自然公園における自然環境や生物分布を、ＩＣＴ技術を活用して記録し、可視化する。フィールドワークを通じて、身近な自然とふれあう機会や地域協働の場を創出し，生物多様性に関する理解に根ざした環境学習を進める） ・情報学部では、教員の専門分野を活かした地域研究の一環として、オリジナルの部品、機材を3Dプリンタなどにより製作するものづくり工房FabLabの活動、地域イベントにおける音楽と情報技術をテーマとしたインタラクティブ作品の出展、情報技術を利用した本地域の生物・生態調査や研究が推進、実施された。一連の地域協働研究活動は、本学部スタッフが有する多様な専門性を反映した取り組みとして、展開されたもので、外部資金を活用した活動も並行して進められた。当初計画を上回る成果と実績を挙げることができたと評価している。 ・令和７年度は、地域課題に対する研究を多数実施し、大学院生の関わった地域協働型研究の成果は修士論文・プロジェクト報告書という形で報告した。具体的には、①大江地域でのコミュニティ活動におけるＤＸの推進に関するプロジェクト、②地域観光資源への興味関心向上のためのインタラクティブシステムの開発 などの地域と協働した研究が実施された。 | H135: 4
B137: 36 | C137: ・本学教員は、附属機関である北近畿地域連携機構、メディアセンター、地域防災研究センター、国際センター、数理・データサイエンス教育研究センター（仮称）と連携して、本中期計画期間中に取り組むべき適切な研究課題を設定して共同研究を実施する。 | D137: 【令和４年度～令和７年度の総括】 ・令和４年度に北近畿地域連携機構のリエゾン・連携機能を整備して以降、各附属機関と本学教員が連携し、北近畿地域ならではの課題に向き合った地域協働型研究を継続的に推進してきた。京丹後市・夕日ヶ浦エリアを対象としたマーケティング・リサーチに基づく地域ブランディング構築手法の研究、大江町毛原地区の地域通貨「けーら」を活用したハイブリッド型電子地域通貨システムの実証実験など、地域の現場の声を拾いながら実践的な知見を蓄積してきた。また、福知山市との「安全安心なまちづくりと地域ＩｏＴの研究」、京都府中丹広域振興局との「Ｕターン者数等の分析研究」など、行政課題に直結した受託研究・共同研究も展開した。さらに、地域防災研究センターと数理・データサイエンスセンターが連携して福知山市消防本部と進めた「消防活動におけるＡＩ支援」研究では、約46,000件の実データを用いた救急車運用シミュレーションに取り組み、学会発表及び消防本部への成果報告を行った。４年間を通じ、複数の附属機関が連携して地域の現場課題に向き合う研究体制が定着した。 【令和８年度・令和９年度の見込】 ・これまでの取組みを他地域にも展開可能な先進モデルとして発信しながら、附属機関と連携した地域課題解決型研究をさらに深化させていく。 | E137: 3 | F137: ・北近畿地域連携機構のリエゾン・連携機能を利用して外部機関との連携を推進し共同研究、受託研究、受託事業に発展させる。 | G137: ・大学内の取組みの手厚い情報発信、北近畿コラボスペースの交流イベントを通した実質的なコミュニケーション機会の拡充、商工会議所及び福知山市との連携強化に加え、丁寧な連携相談対応を行った。これらの取組みの結果、令和７年度の連携相談件数は88件となり、前年度（68件）から大幅に増加し、共同研究12件、受託研究９件、受託授業９件に発展した。地元金融機関からの紹介・連携相談が増加するなど、リエゾン機能の認知が着実に広がった。また、高等教育機関との共同研究の芽も生まれつつあり、学際的な地域協働型研究の土台が形成されつつある。 | H137: 3
...

Sheet ⑤用語集（年計）
B2: 用語説明
B3: 小項目 番号 | C3: 用語 | D3: 用語解説
B4: 1 | C4: 三つのポリシー | D4: ディプロマ・ポリシー（学位授与方針）、カリキュラム・ポリシー（教育課程編成方針）、アドミッション・ポリシー（入学者受入れ方針）の３つのポリシーのこと。
B5: 1 | C5: ディプロマ・ポリシー（学位授与方針） | D5: 大学の教育理念を踏まえ、どのような力を身に付ければ学位を授与するのかを定める基本的な方針であり、学生の学修成果の目標ともなるもの。
B6: 1 | C6: カリキュラム・ポリシー（教育課程編成方針） | D6: ディプロマ・ポリシーの達成のために、どのような教育課程を編成し、どのような教育内容・方法を実施し、学修成果をどのように評価するのかを定める基本的な方針。
B7: 1 | C7: アドミッション・ポリシー（入学者受入れ方針） | D7: 大学・学部等の教育理念、ディプロマ・ポリシー、カリキュラム・ポリシーに基づく教育内容等を踏まえ、入学者を受け入れるための基本的な方針であり、受け入れる学生に求める学習成果（学力の三要素（１）知識・技能、（２）思考力・判断力、表現力等の能力、（３）主体性を持って多様な人々と協働して学ぶ態度）を示すもの。
B8: 8 | C8: 教育訓練給付金制度 | D8: 働く方々の主体的な能力開発やキャリア形成を支援し、雇用の安定と就職の促進を図ることを目的として、厚生労働大臣が指定する教育訓練を修了した際に、教育訓練経費の一部が支給される制度。 | E8: 追加
B9: 12 | C9: インターンシップ | D9: 学生が在学中に、企業等において自らの専攻や将来のキャリアに関連した就業体験を行うこと。
B10: 14 | C10: アセスメント・ポリシー（学修成果の評価方針） | D10: 学生の学修成果の評価（アセスメント）について、その目的、達成すべき質的水準及び具体的実施方法などについて定めた方針。
B11: 14 | C11: ＰＲＯＧテスト | D11: 専攻・専門に関わらず、社会で求められる汎用的な能力・態度・志向（ジェネリックスキル）について、リテラシーとコンピテンシーの２つの観点から測定する河合塾と㈱リアセックが共同開発したテスト。
B12: 14 | C12: ＧＰＡ | D12: 客観的な成績評価を行うため、授業科目ごとに０～４などのポイントを付した上で、学生ごとの成績の平均を算出すること。Grade Point Averageの略。本学では、成績評価を５段階（秀、優、良、可、不可）で評価し、それぞれに対してグレード・ポイント（４、３、２、１、０）を付与し、単位あたりの平均値を算出している。
B13: 15 | C13: シラバス | D13: 各授業科目の詳細な授業計画のこと。一般に、大学の授業名、担当教員名、講義目的、各回ごとの授業内容、成績評価方法・基準、準備学修等についての具体的な指示、教科書・参考文献、履修条件等が記されており、学生が各授業科目の準備学修等を進めるための基本となるもの。また、学生が講義の履修を決める際の資料になるとともに、教員相互の授業内容の調整、学生による授業評価等にも使われる。
B14: 16 | C14: ファカルティ・ディベロップメント（ＦＤ） | D14: 教員が授業内容・方法を改善し向上させるための組織的な取組の総称。具体的な例としては、教員相互の授業参観の実施、授業方法についての研究会の開催、新任教員のための研修会の開催等を挙げることができる。なお、大学設置基準等においては、こうした意味でのＦＤの実施を各大学に求めているが、単に授業内容・方法の改善のための研修に限らず、広く教育の改善、更には研究活動、社会貢献、管理運営に関わる教員団の職能開発の活動全般を指すものとしてＦＤの語を用いる場合もある。
B15: 20 | C15: リメディアル教育 | D15: 大学教育を受ける前提となる基礎的な知識等についての教育をいう。補習教育とも呼ばれる。
B16: 23 | C16: ピア・サポーター制度 | D16: 同じ立場の仲間（＝学生）同士が助け合い、支え合う学生による相互支援活動のこと。
B17: 34 | C17: 数理・データサイエンス・ＡＩ教育プログラム | D17: 学生の数理・データサイエンス・ＡＩへの関心を高め、それを適切に理解し活用する基礎的な能力（リテラシーレベル）や、課題を解決するための実践的な能力（応用基礎レベル）を育成するため、数理・データサイエンス・ＡＩに関する知識及び技術について体系的な教育を行う大学等の正規の課程（教育プログラム）を文部科学大臣が認定及び選定して奨励する制度。
B18: 35 | C18: Fab Lab（ファブラボ） | D18: ３Ｄプリンタやレーザーカッターなどデジタル制御された多様な工作機械を取り揃え、モノをつくる技術を地域住民が身につけることで、個人や地域レベルの課題を住民自身が解決できるようになるための市民参加型の次世代実験工房。
B19: 41 | C19: 科学研究費助成事業 | D19: 人文学、社会科学から自然科学まで全ての分野にわたり、基礎から応用までのあらゆる「学術研究」（研究者の自由な発想に基づく研究）を格段に発展させることを目的とする「競争的研究資金」であり、ピアレビューによる審査を経て、独創的・先駆的な研究に対する助成を行うもの。
B20: 41 | C20: ＵＲＡ（ユニバーシティー・リサーチ・アドミニストレーター） | D20: 大学などの研究組織において研究者および事務職員とともに、研究資源の導入促進、研究活動の企画・マネジメント、研究成果の活用促進を行って、研究者の研究活動の活性化や研究開発マネジメントの強化を支える業務に従事する人材のこと。 | E20: 追加
B21: 47 | C21: リカレント教育 | D21: 「学校教育」を、人々の生涯にわたって分散させようとする理念であり、その本来の意味は「職業上必要な知識・技術」を修得するために、フルタイムの就学とフルタイムの就職を繰り返すことである。一般的に「リカレント教育」を諸外国より広くとらえ、働きながら学ぶ場合、心の豊かさや生きがいのために学ぶ場合、学校以外の場で学ぶ場合もこれに含めている（この意味では成人の学習活動の全体に近い）。
B22: 48 | C22: デジタルファブリケーション技術 | D22: デジタルデータをもとに創造物を制作する技術のことである。３Ｄスキャナーや３Ｄ ＣＡＤなどの測定機械により、自分のアイデアや個人の身体データ等をデジタルデータ化した上で、そのようなデジタルデータを3Dプリンターやレーザーカッターなどのデジタル工作機械で読み込んで造形する。 | E22: 追加
B23: 51 | C23: Slack | D23: アメリカの企業が提供しているビジネス用のメッセージングアプリ。グループチャット、１対１のメッセージング（Direct Message）、音声通話をWebサービスとして提供している。
B24: 40 | C24: FUJIN(Fukuchiyama Universal Joint Information Nexus) | D24: 学内のＤＸ化を推進するために設置された「ＤＸ推進タスクフォース」が構築を進めている、学内データを集約し学内外に共有するためのデータ統合システム。
B25: 59 | C25: スタッフ・ディベロップメント（ＳＤ） | D25: 職員全員を対象とした、管理運営や教育・研究支援までを含めた資質向上のための組織的な取組を指す。なお、「職員」には教授等の教員や学長等の大学執行部、技術職員等も含まれる。
B26: 65 | C26: ERINGI | D26: 学内業務のＤＸ化の一環として、稟議決裁の電子化とペーパーレス化の推進を目的に、情報学部が開発した稟議決裁システム。
B27: 67 | C27: 認証評価制度 | D27: 学校教育法に基づき、全ての大学が７年以内に１回、文部科学大臣の認証を受けた評価機関（認証評価機関）による第三者評価（認証評価）を受けることが義務付けられる制度。国による事前規制を弾力化しつつ、大学等の教育研究の質の担保を図るため、設置後の大学等の組織運営や教育研究活動等の状況を定期的に事後確認する体制を整備する観点から導入された。
B28: 77 | C28: ＢＣＰ（事業継続計画） | D28: 自然災害、大火災、テロ攻撃などの緊急事態に遭遇した場合において、事業資産の損害を最小限にとどめつつ、中核となる事業の継続あるいは早期復旧を可能とするために、平常時に行うべき活動や緊急時における事業継続のための方法、手段などを取り決めておく計画のこと。
B29: 78 | C29: eduroam | D29: 初等・中等・高等教育機関や研究機関の間でキャンパス無線 LAN の相互利用を実現する、国際的なネットワークローミング利用の仕組み。

Sheet （参考）評価（年度）★
D1: ３．小項目別評価
D2: （１）2019年度の業務の実績に係る自己評価結果一覧表
D3: 大項目番号 | E3: 項目 | J3: 項目数 | K3: 自己評価 | U3: 平均点
K4: 5 | M4: 4 | O4: 3 | Q4: 2 | S4: 1
K6: 年度計画を大幅に上回って実施している（特に優れる若しくは顕著な成果がある） | M6: 年度計画を上回って実施している（上回る若しくは十分な実施状況） | O6: 年度計画を概ね実施している（実施） | Q6: 年度計画を十分に実施できていない（下回る若しくは実施が不十分） | S6: 年度計画を大幅に下回っている（特に劣る若しくは実施していない）
D7: 1 | E7: 第４ 教育研究等の質の向上に関する目標を達成するための措置 １ 教育の質の向上に関する目標を達成するための措置 | J7: =SUM(K7:T7) -> 31 | K7: =COUNTIF('(参考)第1期中期小項目別評価'!$I$14:$I$108,K$4) -> 1 | M7: =COUNTIF('(参考)第1期中期小項目別評価'!$I$14:$I$108,M$4) -> 12 | O7: =COUNTIF('(参考)第1期中期小項目別評価'!$I$14:$I$108,O$4) -> 18 | Q7: =COUNTIF('(参考)第1期中期小項目別評価'!$I$14:$I$108,Q$4) -> 0 | S7: =COUNTIF('(参考)第1期中期小項目別評価'!$I$14:$I$108,S$4) -> 0 | U7: =ROUND((K7*5+M7*4+O7*3+Q7*2+S7*1)/J7,1) -> 3.5
K8: =K7/$J$7 -> 0.032258065 | M8: =M7/$J$7 -> 0.38709677 | O8: =O7/$J$7 -> 0.58064516 | Q8: =Q7/$J$7 -> 0 | S8: =S7/$J$7 -> 0
D9: 2 | E9: 第４ 教育研究等の質の向上に関する目標を達成するための措置 ２ 研究の質の向上に関する目標を達成するための措置 | J9: =SUM(K9:T9) -> 10 | K9: =COUNTIF('(参考)第1期中期小項目別評価'!$I$123:$I$150,K$4) -> 0 | M9: =COUNTIF('(参考)第1期中期小項目別評価'!$I$123:$I$150,M$4) -> 3 | O9: =COUNTIF('(参考)第1期中期小項目別評価'!$I$123:$I$150,O$4) -> 6 | Q9: =COUNTIF('(参考)第1期中期小項目別評価'!$I$123:$I$150,Q$4) -> 1 | S9: =COUNTIF('(参考)第1期中期小項目別評価'!$I$123:$I$150,S$4) -> 0 | U9: =ROUND((K9*5+M9*4+O9*3+Q9*2+S9*1)/J9,1) -> 3.2
K10: =K9/$J$9 -> 0 | M10: =M9/$J$9 -> 0.3 | O10: =O9/$J$9 -> 0.6 | Q10: =Q9/$J$9 -> 0.1 | S10: =S9/$J$9 -> 0
D11: 3 | E11: 第４ 教育研究等の質の向上に関する目標を達成するための措置 ３ 地域協働（地域貢献）の質の向上に関する目標を達成するため の措置 | J11: =SUM(K11:T11) -> 10 | K11: =COUNTIF('(参考)第1期中期小項目別評価'!$I$164:$I$213,K$4) -> 0 | M11: =COUNTIF('(参考)第1期中期小項目別評価'!$I$164:$I$213,M$4) -> 2 | O11: =COUNTIF('(参考)第1期中期小項目別評価'!$I$164:$I$213,O$4) -> 8 | Q11: =COUNTIF('(参考)第1期中期小項目別評価'!$I$164:$I$213,Q$4) -> 0 | S11: =COUNTIF('(参考)第1期中期小項目別評価'!$I$164:$I$213,S$4) -> 0 | U11: =ROUND((K11*5+M11*4+O11*3+Q11*2+S11*1)/J11,1) -> 3.2
K12: =K11/$J$11 -> 0 | M12: =M11/$J$11 -> 0.2 | O12: =O11/$J$11 -> 0.8 | Q12: =Q11/$J$11 -> 0 | S12: =S11/$J$11 -> 0
D13: 4 | E13: 第５ 業務運営の改善及び効率化に関する目標を達成するための措置 | J13: =SUM(K13:T13) -> 20 | K13: =COUNTIF('(参考)第1期中期小項目別評価'!$I$222:$I$347,K$4) -> 0 | M13: =COUNTIF('(参考)第1期中期小項目別評価'!$I$222:$I$347,M$4) -> 5 | O13: =COUNTIF('(参考)第1期中期小項目別評価'!$I$222:$I$347,O$4) -> 15 | Q13: =COUNTIF('(参考)第1期中期小項目別評価'!$I$222:$I$347,Q$4) -> 0 | S13: =COUNTIF('(参考)第1期中期小項目別評価'!$I$222:$I$347,S$4) -> 0 | U13: =ROUND((K13*5+M13*4+O13*3+Q13*2+S13*1)/J13,1) -> 3.3
K14: =K13/$J$13 -> 0 | M14: =M13/$J$13 -> 0.25 | O14: =O13/$J$13 -> 0.75 | Q14: =Q13/$J$13 -> 0 | S14: =S13/$J$13 -> 0
D15: 5 | E15: 第６ 財務内容の改善に関する目標を達成するための措置 | J15: =SUM(K15:T15) -> 13 | K15: =COUNTIF('(参考)第1期中期小項目別評価'!$I$360:$I$443,K$4) -> 1 | M15: =COUNTIF('(参考)第1期中期小項目別評価'!$I$360:$I$443,M$4) -> 3 | O15: =COUNTIF('(参考)第1期中期小項目別評価'!$I$360:$I$443,O$4) -> 9 | Q15: =COUNTIF('(参考)第1期中期小項目別評価'!$I$360:$I$443,Q$4) -> 0 | S15: =COUNTIF('(参考)第1期中期小項目別評価'!$I$360:$I$443,S$4) -> 0 | U15: =ROUND((K15*5+M15*4+O15*3+Q15*2+S15*1)/J15,1) -> 3.4
K16: =K15/$J$15 -> 0.076923077 | M16: =M15/$J$15 -> 0.23076923 | O16: =O15/$J$15 -> 0.69230769 | Q16: =Q15/$J$15 -> 0 | S16: =S15/$J$15 -> 0
D17: 6 | E17: 第７ 自己点検・評価及び情報公開に関する目標を達成するための措置 | J17: =SUM(K17:T17) -> 11 | K17: =COUNTIF('(参考)第1期中期小項目別評価'!$I$456:$I$505,K$4) -> 0 | M17: =COUNTIF('(参考)第1期中期小項目別評価'!$I$456:$I$505,M$4) -> 3 | O17: =COUNTIF('(参考)第1期中期小項目別評価'!$I$456:$I$505,O$4) -> 8 | Q17: =COUNTIF('(参考)第1期中期小項目別評価'!$I$456:$I$505,Q$4) -> 0 | S17: =COUNTIF('(参考)第1期中期小項目別評価'!$I$456:$I$505,S$4) -> 0 | U17: =ROUND((K17*5+M17*4+O17*3+Q17*2+S17*1)/J17,1) -> 3.3
K18: =K17/$J$17 -> 0 | M18: =M17/$J$17 -> 0.27272727 | O18: =O17/$J$17 -> 0.72727273 | Q18: =Q17/$J$17 -> 0 | S18: =S17/$J$17 -> 0
D19: 7 | E19: 第８ その他業務運営に関する重要目標を達成するための措置 | J19: =SUM(K19:T19) -> 7 | K19: =COUNTIF('(参考)第1期中期小項目別評価'!$I$517:$I$555,K$4) -> 0 | M19: =COUNTIF('(参考)第1期中期小項目別評価'!$I$517:$I$555,M$4) -> 1 | O19: =COUNTIF('(参考)第1期中期小項目別評価'!$I$517:$I$555,O$4) -> 6 | Q19: =COUNTIF('(参考)第1期中期小項目別評価'!$I$517:$I$555,Q$4) -> 0 | S19: =COUNTIF('(参考)第1期中期小項目別評価'!$I$517:$I$555,S$4) -> 0 | U19: =ROUND((K19*5+M19*4+O19*3+Q19*2+S19*1)/J19,1) -> 3.1
K20: =K19/$J$19 -> 0 | M20: =M19/$J$19 -> 0.14285714 | O20: =O19/$J$19 -> 0.85714286 | Q20: =Q19/$J$19 -> 0 | S20: =S19/$J$19 -> 0
D21: 8 | E21: 第14 福知山市の規則で定める業務運営に関する事項 | J21: =SUM(K21:T21) -> 4 | K21: =COUNTIF('(参考)第1期中期小項目別評価'!$I$596:$I$603,K$4) -> 0 | M21: =COUNTIF('(参考)第1期中期小項目別評価'!$I$596:$I$603,M$4) -> 1 | O21: =COUNTIF('(参考)第1期中期小項目別評価'!$I$596:$I$603,O$4) -> 3 | Q21: =COUNTIF('(参考)第1期中期小項目別評価'!$I$596:$I$603,Q$4) -> 0 | S21: =COUNTIF('(参考)第1期中期小項目別評価'!$I$596:$I$603,S$4) -> 0 | U21: =ROUND((K21*5+M21*4+O21*3+Q21*2+S21*1)/J21,1) -> 3.3
K22: =K21/$J21 -> 0 | M22: =M21/$J$21 -> 0.25 | O22: =O21/$J$21 -> 0.75 | Q22: =Q21/$J$21 -> 0 | S22: =S21/$J$21 -> 0
E23: 合計 | J23: =SUM(J7:J22) -> 106 | K23: =K7+K9+K11+K13+K15+K17+K19+K21 -> 2 | M23: =M7+M9+M11+M13+M15+M17+M19+M21 -> 30 | O23: =O7+O9+O11+O13+O15+O17+O19+O21 -> 73 | Q23: =Q7+Q9+Q11+Q13+Q15+Q17+Q19+Q21 -> 1 | S23: =S7+S9+S11+S13+S15+S17+S19+S21 -> 0 | U23: =ROUND((K23*5+M23*4+O23*3+Q23*2+S23*1)/J23,1) -> 3.3
K24: =K23/$J$23 -> 0.018867925 | M24: =M23/$J$23 -> 0.28301887 | O24: =O23/$J$23 -> 0.68867925 | Q24: =Q23/$J$23 -> 0.0094339623 | S24: =S23/$J$23 -> 0

Sheet （参考）評価（中期）★
D2: （２）中期目標期間（4年終了時）の業務の実績に係る自己評価結果一覧表
D3: 大項目番号 | E3: 項目 | J3: 項目数 | K3: 自己評価 | U3: 平均点
K4: 5 | M4: 4 | O4: 3 | Q4: 2 | S4: 1
K6: 中期計画を大幅に上回って実施している（特に優れる若しくは顕著な成果がある） | M6: 中期計画を上回って実施している（上回る若しくは十分な実施状況） | O6: 中期計画を概ね実施している（実施） | Q6: 中期計画を十分に実施できていない（下回る若しくは実施が不十分） | S6: 中期計画を大幅に下回っている（特に劣る若しくは実施していない）
D7: 1 | E7: 第４ 教育研究等の質の向上に関する目標を達成するための措置 １ 教育の質の向上に関する目標を達成するための措置 | J7: =SUM(K7:T7) -> 16 | K7: =COUNTIF('(参考)第1期中期小項目別評価'!$E$14:$E$108,K$4) -> 1 | M7: =COUNTIF('(参考)第1期中期小項目別評価'!$E$14:$E$108,M$4) -> 8 | O7: =COUNTIF('(参考)第1期中期小項目別評価'!$E$14:$E$108,O$4) -> 7 | Q7: =COUNTIF('(参考)第1期中期小項目別評価'!$E$14:$E$108,Q$4) -> 0 | S7: =COUNTIF('(参考)第1期中期小項目別評価'!$E$14:$E$108,S$4) -> 0 | U7: =ROUND((K7*5+M7*4+O7*3+Q7*2+S7*1)/J7,1) -> 3.6
K8: =K7/$J$7 -> 0.0625 | M8: =M7/$J$7 -> 0.5 | O8: =O7/$J$7 -> 0.4375 | Q8: =Q7/$J$7 -> 0 | S8: =S7/$J$7 -> 0
D9: 2 | E9: 第４ 教育研究等の質の向上に関する目標を達成するための措置 ２ 研究の質の向上に関する目標を達成するための措置 | J9: =SUM(K9:T9) -> 7 | K9: =COUNTIF('(参考)第1期中期小項目別評価'!$E$123:$E$150,K$4) -> 0 | M9: =COUNTIF('(参考)第1期中期小項目別評価'!$E$123:$E$150,M$4) -> 1 | O9: =COUNTIF('(参考)第1期中期小項目別評価'!$E$123:$E$150,O$4) -> 6 | Q9: =COUNTIF('(参考)第1期中期小項目別評価'!$E$123:$E$150,Q$4) -> 0 | S9: =COUNTIF('(参考)第1期中期小項目別評価'!$E$123:$E$150,S$4) -> 0 | U9: =ROUND((K9*5+M9*4+O9*3+Q9*2+S9*1)/J9,1) -> 3.1
K10: =K9/$J$9 -> 0 | M10: =M9/$J$9 -> 0.14285714 | O10: =O9/$J$9 -> 0.85714286 | Q10: =Q9/$J$9 -> 0 | S10: =S9/$J$9 -> 0
D11: 3 | E11: 第４ 教育研究等の質の向上に関する目標を達成するための措置 ３ 地域協働（地域貢献）の質の向上に関する目標を達成するため の措置 | J11: =SUM(K11:T11) -> 8 | K11: =COUNTIF('(参考)第1期中期小項目別評価'!$E$164:$E$213,K$4) -> 0 | M11: =COUNTIF('(参考)第1期中期小項目別評価'!$E$164:$E$213,M$4) -> 5 | O11: =COUNTIF('(参考)第1期中期小項目別評価'!$E$164:$E$213,O$4) -> 3 | Q11: =COUNTIF('(参考)第1期中期小項目別評価'!$E$164:$E$213,Q$4) -> 0 | S11: =COUNTIF('(参考)第1期中期小項目別評価'!$E$164:$E$213,S$4) -> 0 | U11: =ROUND((K11*5+M11*4+O11*3+Q11*2+S11*1)/J11,1) -> 3.6
K12: =K11/$J$11 -> 0 | M12: =M11/$J$11 -> 0.625 | O12: =O11/$J$11 -> 0.375 | Q12: =Q11/$J$11 -> 0 | S12: =S11/$J$11 -> 0
D13: 4 | E13: 第５ 業務運営の改善及び効率化に関する目標を達成するための措置 | J13: =SUM(K13:T13) -> 19 | K13: =COUNTIF('(参考)第1期中期小項目別評価'!$E$222:$E$347,K$4) -> 0 | M13: =COUNTIF('(参考)第1期中期小項目別評価'!$E$222:$E$347,M$4) -> 3 | O13: =COUNTIF('(参考)第1期中期小項目別評価'!$E$222:$E$347,O$4) -> 16 | Q13: =COUNTIF('(参考)第1期中期小項目別評価'!$E$222:$E$347,Q$4) -> 0 | S13: =COUNTIF('(参考)第1期中期小項目別評価'!$E$222:$E$347,S$4) -> 0 | U13: =ROUND((K13*5+M13*4+O13*3+Q13*2+S13*1)/J13,1) -> 3.2
K14: =K13/$J$13 -> 0 | M14: =M13/$J$13 -> 0.15789474 | O14: =O13/$J$13 -> 0.84210526 | Q14: =Q13/$J$13 -> 0 | S14: =S13/$J$13 -> 0
D15: 5 | E15: 第６ 財務内容の改善に関する目標を達成するための措置 | J15: =SUM(K15:T15) -> 12 | K15: =COUNTIF('(参考)第1期中期小項目別評価'!$E$360:$E$443,K$4) -> 1 | M15: =COUNTIF('(参考)第1期中期小項目別評価'!$E$360:$E$443,M$4) -> 2 | O15: =COUNTIF('(参考)第1期中期小項目別評価'!$E$360:$E$443,O$4) -> 9 | Q15: =COUNTIF('(参考)第1期中期小項目別評価'!$E$360:$E$443,Q$4) -> 0 | S15: =COUNTIF('(参考)第1期中期小項目別評価'!$E$360:$E$443,S$4) -> 0 | U15: =ROUND((K15*5+M15*4+O15*3+Q15*2+S15*1)/J15,1) -> 3.3
K16: =K15/$J$15 -> 0.083333333 | M16: =M15/$J$15 -> 0.16666667 | O16: =O15/$J$15 -> 0.75 | Q16: =Q15/$J$15 -> 0 | S16: =S15/$J$15 -> 0
D17: 6 | E17: 第７ 自己点検・評価及び情報公開に関する目標を達成するための措置 | J17: =SUM(K17:T17) -> 10 | K17: =COUNTIF('(参考)第1期中期小項目別評価'!$E$456:$E$503,K$4) -> 1 | M17: =COUNTIF('(参考)第1期中期小項目別評価'!$E$456:$E$503,M$4) -> 2 | O17: =COUNTIF('(参考)第1期中期小項目別評価'!$E$456:$E$503,O$4) -> 7 | Q17: =COUNTIF('(参考)第1期中期小項目別評価'!$E$456:$E$503,Q$4) -> 0 | S17: =COUNTIF('(参考)第1期中期小項目別評価'!$E$456:$E$503,S$4) -> 0 | U17: =ROUND((K17*5+M17*4+O17*3+Q17*2+S17*1)/J17,1) -> 3.4
K18: =K17/$J$17 -> 0.1 | M18: =M17/$J$17 -> 0.2 | O18: =O17/$J$17 -> 0.7 | Q18: =Q17/$J$17 -> 0 | S18: =S17/$J$17 -> 0
D19: 7 | E19: 第８ その他業務運営に関する重要目標を達成するための措置 | J19: =SUM(K19:T19) -> 6 | K19: =COUNTIF('(参考)第1期中期小項目別評価'!$E$517:$E$555,K$4) -> 0 | M19: =COUNTIF('(参考)第1期中期小項目別評価'!$E$517:$E$555,M$4) -> 1 | O19: =COUNTIF('(参考)第1期中期小項目別評価'!$E$517:$E$555,O$4) -> 5 | Q19: =COUNTIF('(参考)第1期中期小項目別評価'!$E$517:$E$555,Q$4) -> 0 | S19: =COUNTIF('(参考)第1期中期小項目別評価'!$E$517:$E$555,S$4) -> 0 | U19: =ROUND((K19*5+M19*4+O19*3+Q19*2+S19*1)/J19,1) -> 3.2
K20: =K19/$J$19 -> 0 | M20: =M19/$J$19 -> 0.16666667 | O20: =O19/$J$19 -> 0.83333333 | Q20: =Q19/$J$19 -> 0 | S20: =S19/$J$19 -> 0
D21: 8 | E21: 第14 福知山市の規則で定める業務運営に関する事項 | J21: =SUM(K21:T21) -> 4 | K21: =COUNTIF('(参考)第1期中期小項目別評価'!$E$596:$E$603,K$4) -> 0 | M21: =COUNTIF('(参考)第1期中期小項目別評価'!$E$596:$E$603,M$4) -> 1 | O21: =COUNTIF('(参考)第1期中期小項目別評価'!$E$596:$E$603,O$4) -> 3 | Q21: =COUNTIF('(参考)第1期中期小項目別評価'!$E$596:$E$603,Q$4) -> 0 | S21: =COUNTIF('(参考)第1期中期小項目別評価'!$E$596:$E$603,S$4) -> 0 | U21: =ROUND((K21*5+M21*4+O21*3+Q21*2+S21*1)/J21,1) -> 3.3
K22: =K21/$J21 -> 0 | M22: =M21/$J21 -> 0.25 | O22: =O21/$J21 -> 0.75 | Q22: =Q21/$J21 -> 0 | S22: =S21/$J21 -> 0
E23: 合計 | J23: =SUM(J7:J22) -> 82 | K23: =K7+K9+K11+K13+K15+K17+K19+K21 -> 3 | M23: =M7+M9+M11+M13+M15+M17+M19+M21 -> 23 | O23: =O7+O9+O11+O13+O15+O17+O19+O21 -> 56 | Q23: =Q7+Q9+Q11+Q13+Q15+Q17+Q19+Q21 -> 0 | S23: =S7+S9+S11+S13+S15+S17+S19+S21 -> 0 | U23: =ROUND((K23*5+M23*4+O23*3+Q23*2+S23*1)/J23,1) -> 3.4
K24: =K23/$J$23 -> 0.036585366 | M24: =M23/$J$23 -> 0.2804878 | O24: =O23/$J$23 -> 0.68292683 | Q24: =Q23/$J$23 -> 0 | S24: =S23/$J$23 -> 0

Sheet (参考)第1期中期小項目別評価
B1: （３）小項目別業務実績・自己評価結果
B2: 項 目 別 の 状 況
B4: 第４ 教育研究等の質の向上に関する目標
B5: １ 教育の質の向上に関する目標 （１）教育の成果に関する目標
B7: 中 期 目 標 | D7: 教育研究において、地域、自国、そして世界に対する理想を持ち、教養・専門的知識を生涯にわたって学修し、それを実践する力を涵養する。 特に、地域協働型教育研究を通して、創造的思考力、課題解決力、協働・協調力、コミュニケーション力など、社会人に必要となる基礎能力を涵養する。地域社会そのものを教育の場としたフィールドワークやインターンシップに主体的に取り組み、地域の人や資源を教材とした教育研究を実践する中で、地域社会が抱える様々な課題解決に向け、関係者や関係機関等との協議調整、企画立案や提案を行うことができる人材を育て、地域社会に還元する。
B9: 中期計画番号 | C9: 中期計画 | D9: 業務の実績（中期計画） | E9: 自己 評価 | F9: 年度計画番号 | G9: 年度計画 | H9: 業務の実績（年度計画） | I9: 自己 評価
B11: １ 教育研究等の質の向上に関する目標を達成するための措置
B12: （１）教育の成果に関する目標を達成するための取組
B13: 1 | C13: ①自由な発想と行動力、分析企画力、実行力、公共マインドの涵養
C14: 大学の理念の実現と発展に必要な長期的な戦略を計画し、地域に根ざし、世界に通用する高い専門能力と多角的な視点を持ち、さらに、地域社会の様々な分野におけるニーズに対応した指導的役割を果たせる人材を育成するための自由な発想と行動力、分析企画力、実行力、公共マインドを涵養する。 | D14: 【2016年度～2019年度の総括】 ・大学の理念を実現するため、2017年度に地域経営学部のカリキュラムを改定し、地域と協働でフィールドワーク等を行う演習科目を必修化するとともに、幅広い知識、多角的な視点を養うために教養科目の充実を図った。2020年度の情報学部設置に向けて、カリキュラムを作成するとともに既存学部のカリキュラムの体系化を進めるため、ナンバリング、履修モデル、カリキュラムツリーの作成を行い、また、シラバスの充実を図り、地域人財（グローカリスト）の育成における方向性の確立に努めた。 【2020年度・2021年度の見込】 ・2017年度に策定したカリキュラムの卒業生を2020年度に輩出するため、本カリキュラムの検証を行う。また、教養科目や地域協働型教育研究など、地域経営学部と情報学部の教育・研究上の具体的な連携の方法について検討する。 | E14: 4 | F14: 1 | G14: ・新学部の設置に伴い、既存学部のカリキュラムを見直し、ディプロマポリシーの実現を意識しつつ、2020年度新カリキュラムを策定する（編成実施方針、科目配置表等）。 新学部の開設に合わせた教学体制の整備の一環として、カリキュラムにナンバリングを付し、新学部も含めて大学全体で教育課程の体系性を確保する。ナンバリングの体系化は2019年末に完成させ、2020年度には学生に公開し、完全施行する。ナンバリングを付すことにより、学生にとっては、体系的、計画的に履修することができ、教員は体系的で効果的な履修指導を行うことができる。 | H14: ・情報学部の設置に伴い、両学部間で調整の上、共通教育科目の見直しを行った。また、専門科目についても見直しを行い、新設する情報学部に対応した2020年度カリキュラムを作成した。 ・共通教育科目及び地域経営学部と情報学部の専門教育科目に科目ナンバリングを付し、大学全体の教育課程の体系を確保した。これに加え、体系的かつ計画的な履修を促すため地域経営学部は履修モデルの見直しやシラバスの充実（シラバス項目の見直し、教務委員会によるシラバスチェック）、演習科目のルーブリックや修学カルテの試行的導入などを行った。また、学部学科ごとのカリキュラムツリーも作成した。 | I14: 4
F15: 2 | G15: ・一部の授業では、学外講師を招聘することにより、自由な発想と行動力、分析企画力、実行力、公共マインドを養成する。その適切性は、学生の授業評価アンケートなどから検証する。学外講師にも本学の３ポリシーを意識頂くよう努める。教務委員会で学外講師のカリキュラム上の必要性と位置づけを明確にする。また、FD委員会とも協力し専任教員への大学の理念の浸透を図る。 | H15: ・学外講師を招聘した結果、学生の授業評価アンケートで、「ゲストスピーカーの話を聞くことで学んだことの理解が深まった」「様々な視点や考え方を知ることができた」などの声があり、様々な業種の現場の生の声を取り入れることで深い学びに繋がり、自由な発想と行動力、分析企画力、実行力、公共マインドを養成した。 ・学外講師にも本学の理念や3ポリシーを周知するため、選考時の説明や毎年度の始めの履修の手引きの配布など、本学の理念の共有を図った。 ・専任教員には､入職時のガイダンスの説明や履修の手引きの配付等により周知している。 | I15: 3
B16: 2 | C16: ②行動・実践の基盤である生きていくための総合力(人間力)を涵養する教養教育の重視
C17: 幅広い視野と豊かな人間性を涵養し、創造的思考力、課題解決力、協調・協働力、コミュニケーション力といった社会人基礎力など、行動･実践の基盤である生きていくための総合力(人間力)を涵養するためにインターンシップ等も取り入れた教養教育を実践する。 | D17: 【2016年度～2019年度の総括】 ・社会とのつながりの中で学びを深め、社会人基礎力を養うため、2017年度及び2020年度の二度にわたるカリキュラムの改定により、本学ではインターンシップ（グローカル特別講義（地域キャリア実習））や国際フィールドワーク、病院実習といった実習科目を積極的に取り入れた授業を実施してきた。これにより、課題解決力、協調・協働力、コミュニケーション力などを涵養している。 【2020年度・2021年度の見込】 ・地域経営学部では、これまでと同様にインターンシップ（地域キャリア実習）や国際フィールドワーク、病院実習といった実習科目の履修を積極的に促す。情報学部ではPBL（課題解決型学習）を実施するとともに、3年次生に配当されているインターンシップの実施に向けて、実習先を確保する。 | E17: 3 | F17: 3 | G17: ・授業科目である「国際フィールドワーク」においては、海外における地域事情を知ることを目的とし、中国でのフィールドワークを行う。現地学生との交流を行い、世界的視野で考え、足元から行動する能力やコミュニケーション力を養う。 | H17: ・授業科目「国際フィールドワーク」において、9月2日から7日に3人の学生が中国研修を行った。中国の農村地域を訪問し、中国型地域づくりの手法を学び、農村社会の発展の現状を把握できた。現地の若者達と地域づくりの課題解決を巡って日中両国の知見を交換した。国際フィールドワークの全体を通して、学生達は広い視野を身につけ、自ら行動する能力やコミュニケーション能力を養った。 | I17: 3
F18: 4 | G18: ・課題解決型の実習を｢地域キャリア実習｣という科目名で、2019年度も引き続き実施する。座学で学んだことを現場で実践する機会を与えることで学士力、社会人基礎力の養成に努める。 | H18: ・学士力・社会人基礎力を養成するため、インターンシップ協力先の開拓を強化し、北近畿地域の事業所を中心に52事業所からプログラムの提供を受けた。その結果、22事業所に延べ61人の学生がグローカル特別講義Ⅲ（地域キャリア実習Ⅰ）に参加した。学生にとって、「地域で働くこと」｢仕事観･人生観を醸成｣ ｢残りの学生生活ですべきことを明確にする｣という点で貴重な機会となった。実習後は、実習参加者全員が報告書（A4・2枚）や実習日誌の提出、ポスター報告を実施し、10日以上の実習参加者14人（23％）に対して単位認定をした。 ・11月28日には実習の内容と成果をまとめて、ポスターセッション形式の報告会を実施した。 | I18: 3
B19: 3 | C19: ③理論と応用の学びを踏まえた実践・実習による学びの徹底
C20: 様々な地域課題に対し、質の高い理論による専門教育と地域協働型の実践教育を通じ課題解決能力を養成し、協議調整や企画立案を行うことができる人材を育て、地域社会に還元する。 | D20: 【2016年度～2019年度の総括】 ・地域協働型教育の実践を行い、地域の課題と直接向き合うフィールドワークを福知山市をはじめとした北近畿地域で展開してきた。2016年度から地域協働型実践教育成果報告会を毎年2月に開催し、連携先による講評の機会を設けている。また、現地報告会を実施するなど、プレゼンテーション能力や課題解決能力の向上に努めた。 ・地域協働型の教育での学びは、修学カルテによる自己評価に加え、演習科目ではルーブリックを活用し、演習における知識・技能・遂行能力の習熟度の評価を明確化した。 【2020年度・2021年度の見込】 ・情報学部を設置したことで、幅広い分野で地域連携を行うことが期待されていることから、連携先の開拓を随時行う。地域経営学部においては、引き続き積極的に地域との接点を持ち、地域課題と向き合う教育を実践していく。 | E20: 4 | F20: 5 | G20: ・理論と応用の学びを踏まえた実践・実習による学びを強化し、学修アウトカムの達成度を見るためにルーブリックを作成する。ルーブリックは、学生の課題を確認し、その成長に資するものであり、webシステムの導入とも合わせて、1年生科目「地域経営演習Ⅰ、Ⅱ」で試行的に導入する。 | H20: ・理論と応用の学びを踏まえた実践・実習による学びを強化し、学修アウトカムの達成度を見るためにルーブリックを作成した。1年次生科目「地域経営演習」の成績評価にあたって、「知識」「技能」「遂行能力」について、作成したルーブリックを用いてその習熟度を測ることにより、従来のクラスによる評価のばらつきを一定程度抑制する効果があった。1年次生科目「地域経営演習Ⅰ・Ⅱ」で試行的に実施し、さらに効果の検証を行った。 | I20: 4
B21: 4 | C21: ④主体的な学びの支援・推進
C22: 学生のリーダーシップやモチベーションを向上させる取り組みを進めるとともに、ワークショップ等のグループ学修を含め、共感性を養いながら学生自らが主体的に学修を進めるアクティブ・ラーニングを推進する。 | D22: 【2016年度～2019年度の総括】 ・地域で活躍するキーパーソンを一部の授業のゲスト講師として招いたほか、行政職員の現場の声を聞く機会を設け、授業内容を深めるだけでなく学生のモチベーション向上に取り組んだ。 ・授業に適宜グループワークやグループディスカッションを取り入れることで、学生の主体性やコミュニケーション能力を養った。 ・教育効果を検証するため、2019年度後学期から学生の自己評価により学修の習熟度（プロジェクトの実施経験やリーダーシップ、他者とのコミュニケーション等）を修学カルテに蓄積している。 【2020年度・2021年度の見込】 ・学生が学びを深めるために、引き続き、適切な形でゲスト講師の招聘やグループワーク、グループディスカッションを授業に取り入れていく。 | E22: 4 | F22: 6 | G22: ・学生プロジェクトへの単位付与を実施する。2020年度より本格実施に向けて見直しを行う。単位認定の基準としては2単位に相当する時間数を確保することとした。（科目はグローカル特別講義である） | H22: ・2019年度前学期に10件の学生プロジェクトを採択した。そのうち、学生プロジェクト「キャリアパス0.1」について単位を認定した（1件・7人）。 | I22: 3
F23: 7 | G23: ・ポートフォリオは、導入する学務システムの機能を用いて、2019年度前期中に詳細を決定するとともに、2年生から試行的に導入する。 | H23: ・教育効果の検証とプロジェクトの実施経験やリーダーシップなど学生自身の学修の習熟度や大学生活での学びや経験を記録するためのツールとして「修学カルテ」という名称で本学におけるポートフォリオを作成した。ポートフォリオは、教学情報システム「WebClass」の修学カルテ機能を用いて試案を作成し、後学期のオリエンテーションにおいて、2年次生を対象に試行的に実施し、学びを振り返る機会を設けた。 ・試行実施の結果を踏まえて内容を修正し、新年度に向けたオリエンテーションにて、新2年次生から4年次生を対象にポートフォリオを実施する。 | I23: 4
B25: 第４ 教育研究等の質の向上に関する目標
B26: １ 教育の質の向上に関する目標 （２）教育の内容等に関する目標 ①学位授与に関する目標
B28: 中 期 目 標 | D28: 基本理念・目的を踏まえ、どのような人材を育成し、どのような力を身に付けた者に学位を授与するのかを定める基本方針として、ディプロマ・ポリシー（学位授与の方針）を明確化し、学生の学修成果目標を明示する。
B30: 中期計画番号 | C30: 中期計画 | D30: 業務の実績（中期計画） | E30: 自己 評価 | F30: 年度計画 番号 | G30: 年度計画 | H30: 業務の実績（年度計画） | I30: 自己 評価
B32: １ 教育研究等の質の向上に関する目標を達成するための措置
B33: （２）教育の内容等に関する目標を達成するための措置
B34: 5 | C34: ①学位授与の明確化
C35: 本学が育成する人材像に基づき、ディプロマ・ポリシーを明確に定め、教育の成果に関する目標に基づく教育と評価により、学生及び社会に対して教育の質を保証する。 | D35: 【2016年度～2019年度の総括】 ・本学の理念に基づくディプロマ・ポリシー（学位授与方針）を明確にし、学生の学位授与に係る学修アウトカム目標を設定した。未確立の「地域経営学」の定義等の研究を深め、ディプロマ・ポリシーを2016年度及び2019年度に見直しを行い、2017年度及び2020年度に改定した。 ・学位授与方針と科目との関連性をカリキュラムマップとしてまとめ、それぞれのシラバスにも明記し、科目の位置づけを明確化した。 ・成績評価にあたってはGPA評価制度を採用しており、履修指導時に活用するとともに、成績優秀者には履修登録上限単位数を広げる等の活用をしている。 【2020年度・2021年度の見込】 ・ディプロマ・ポリシーに基づき、卒業までに学生が学ぶべき内容を保証するために、2020年度カリキュラムに基づいた授業の実施を行うとともに、成績評価の厳格化についての検討を進めていく。 | E35: 3 | F35: 8 | G35: ・授業評価アンケート結果に基づき、シラバス通りに授業が展開されているか検証するとともに、実態把握のために教員間の授業参観を実施する。 ・シラバスの作成においては、以下の記入を徹底する。 予習、復習の内容と注意事項 試験・レポート等に対するフィードバックの方法 到達目標、成績評価の方法、基準 卒業認定、学位授与方法との関係 ・成績評価の分布状況について、2019年度より教員間で公表する。教員間・科目間で偏りがないよう、成績評価の割合などについて検討する。 | H35: ・授業評価アンケートでは、授業がシラバス通りに展開されているかという項目に対して、評価の全体平均が前学期4.08で後学期4.01となり、概ね良い評価となった。 ・後学期の授業中において授業参観を実施し、教員相互に授業を観ることによって自身の授業改善に努めるようにした。 ・2020年度シラバス作成要領を見直し、成績評価と到達目標の関連性を組織的にチェックする体制を取るとともに、シラバスの内容充実を図った。 ・2018年度に作成した評価基準を基にした成績評価の分布状況を2019年度より教員間で公表し共有することで、担当科目以外の成績評価状況を把握することができる体制とした。 | I35: 4
B37: 第４ 教育研究等の質の向上に関する目標
B38: １ 教育の質の向上に関する目標 （２）教育の内容等に関する目標 ②教育内容・手法の充実に関する目標
B40: 中 期 目 標 | D40: ディプロマ・ポリシーの達成のために、どのような教育課程を編成し、どのような教育内容・方法を実施し、学修成果をどのように評価するのかを定める基本的な方針として、カリキュラム・ポリシー（教育課程編成・実施の方針）を明確化する。 また、社会や学生のニーズに照らして、教育内容とその手法について常に最適化を図るため、カリキュラム（教育課程）の見直しとファカルティ・ディベロップメント授業方法・内容を改善・向上させるための組織的な取り組みの総称をいう。）を推進する。
B42: 中期計画番号 | C42: 中期計画 | D42: 業務の実績（中期計画） | E42: 自己 評価 | F42: 年度計画 番号 | G42: 年度計画 | H42: 業務の実績（年度計画） | I42: 自己 評価
B44: １ 教育研究等の質の向上に関する目標を達成するための措置
B45: （２）教育の内容等に関する目標を達成するための措置
B46: ②教育内容･手法の充実
B47: 6 | C47: ア カリキュラムの充実等
C48: ディプロマ・ポリシーを踏まえた明確なカリキュラム・ポリシーを策定する。併せて、各授業の到達目標、授業計画、成績評価の方法と基準等を明示したシラバスの充実化を図る。 | D48: 【2016年度～2019年度の総括】 ・ディプロマ・ポリシー（学位授与方針）を踏まえた明確なカリキュラム・ポリシーを2017年度に改定し、これに基づくカリキュラムを2017年度から改定した。未確立の「地域経営学」の定義等の研究を深め、ディプロマ・ポリシーを2016年度および2019年度に見直し作業を行い、2017年度及び2020年度に改定した。 ・カリキュラムに配当された科目の講義概要（シラバス）の作成にあたっては、授業内容や到達目標、評価基準などをチェックし、その質を保証している。 ・年2回実施している授業評価アンケートにおいて、シラバスと授業内容の整合性を確認するために、2017年度から「シラバスどおりに授業が展開されているか」の項目を追加した。 ・2018年度よりカリキュラムの検証・見直しを行い、2020年度カリキュラムを策定するとともに、シラバスの内容を充実させた。 【2020年度・2021年度の見込】 ・講義概要（シラバス）作成時のチェックと授業評価アンケートにより、授業内容の質を保証していく。 | E48: 3 | F48: 9 | G48: ・シラバスの入力及び閲覧についてシステムの導入によりオンライン上で可能とし、シラバスの作成をより迅速に行い確認ができるようにする。シラバスに当該科目とディプロマポリシーの関係を明示し、併せてシラバスの点検を行う。 | H48: ・シラバスの作成にあたってはオンライン上で可能とし、その作成を迅速に行うとともに、シラバス作成チェックリストに基づき教務委員会により組織的に点検を行うことができた。シラバスに当該科目とディプロマ・ポリシーの関係を明示した。併せてシラバスの点検結果をフィードバックすることで改善が見られた。 | I48: 3
B49: 7 | C49: イ ファカルティ・ディベロップメント（FD）の推進
C50: 教育に関する自己点検･評価を行うとともに、外部評価を定期的に受審する。また、組織的なファカルティ・ディベロップメント（FD）に関する研修、他大学教員との交流等を実施し、その成果を教育内容や教育手法の改善に活用する。併せて、学生の授業評価を定期的に実施し、教育活動の改善に反映する。 | D50: 【2016年度～2019年度の総括】 ・開学より、教員研修や教員同士の交流の機会を設けるために月1回程度のFDフォーラムを実施した。授業改善や情報セキュリティ、地域経営学、教学情報システム「WebClass」の活用方法など、外部講師も招聘しながら研修を行った。 ・2016年度より無記名の授業アンケートを実施し、講義担当教員にその集計結果を返却してリフレクションペーパー（振り返りシート）を記入することで、学生の理解度や講義の改善点を自覚させるよう工夫した。集計は2018年度より教学情報システムを導入し、スマートフォンを活用したWebアンケートを実施するなど、事務負担を削減するとともに集計の迅速化を図った。 ・2019年度には、全教員が他の教員の授業参観を実施し、参観者との意見交換を行い相互の指導技術の改善に取り組んだ。 【2020年度・2021年度の見込】 ・情報学部に導入するPBLや帰納的学習などの新しい教育手法について、評価の方法を検討する。 ・学生も含めた学部間の交流を図り、教育技能の向上に資するFDフォーラムを年に複数回実施する。 | E50: 3 | F50: 10 | G50: ・ ファカルティ・ディベロップメント（FD活動を授業の工夫内容等に関する内容のものを含めて定期的に開催する（月１回程度）。 ・アクティブラーニングやPBL、ルーブリック評価などについての研修会、勉強会を実施する。（2018年度にかなり集中的におこなったので、2019年度は年間１回程度）アクティブラーニングや PBL については、教員間の授業参観を含む多様な形で取り組みを増進するよう努める。 ・授業評価アンケート結果及びリフレクションペーパーを学生に公表することで授業改善に努める。科目ごとに整理して、教員に配付することで、さらなる授業改善につなげる。また、教学システムの導入に伴い、授業評価アンケートのWeb化及びアンケート項目の見直しも検討する。 ・学生から評価の高い授業について、担当教員の授業参観を実施し、他の教員が参観する。以前に実施した時より参加者、参観授業の数が増えるよう教員側のスケジュールを再調整する。 ・実践教育専門委員会での2018年度の議論のまとめと、地域経営学研究会のその後の進展も踏まえて、遅くとも2019年度後期には大学全体での方向づけについてFD委員会主催のフォーラムで話し合う。 | H50: ・ファカルティ・ディベロップメント（FD）活動として、「研究倫理講習、研究費不正防止、研究不正防止」「地域協働型実践教育研究のあり方」「科学研究費獲得、大学評価と研究活性化」「ポートフォリオの実施状況」「地域経営研究の情報交換」など年間10回の活動を行った。 ・教学情報システムを導入したことで、授業評価アンケートを全面的にWebアンケートに移行し、その結果に対して全教員がリフレクションペーパー（振り返りシート）を作成した。 ・指導技術等を学び合うことを目的に、全教員による授業参観を実施した。計14科目（交流観光政策論や交流居住論など）を教員が参観し、報告書を共有し、指導技術などの改善に取り組んだ。 ・地域協働型教育を実践する科目である「地域経営演習Ⅰ～Ⅳ」「地域経営研究Ⅰ・Ⅱ」の指導方法等を共有する場を設定し、演習状況や学生指導等に関し、意見交換を行い、改善に繋げた。 ・FDフォーラムにおいて、地域経営学の体系と展望等の内容で教員発表（副学長、各学科長）を行い、北近畿地域連携機構の今後の体制や大学の方向性、地域経営学・地域協働型教育研究のあり方等の討議を行い認識の共有を図った。 | I50: 3
B53: 8 | C53: ウ 内部質保証への取り組みの推進
C54: 自己点検・評価の実施及び外部評価の受審に向けた内部質保証への取り組みを推進する。 | D54: 【2016年度～2019年度の総括】 ・受審に向けた取り組みとして、カリキュラム・ポリシーの明確化と教育課程への反映をするため、2016年度に見直し作業を行い、2017年度からのカリキュラムを改定（カリキュラムは2019年度にも見直し作業を行い、2020年度にも再度改定）したほか、内部質保証の方針や教員組織の編成方針を作成した。 ・2016年から2017年にかけて認証評価機関である（公財）大学基準協会の評価を受審し、「適合」の認定を受けた。 ・2018年度以降は、2017年度に受審した証評価機関の評価結果等を踏まえた対応状況を点検及び検討した。 ・2019年度に自己点検・評価の体制を見直し、半期ごとに教育の成果や内容、実施体制になど、年度計画の進捗状況を点検し、点検結果を学内にフィードバックして年度計画の各取組を着実に達成するよう促す体制を取り、PDCAサイクルを構築した。 ・各分野の業務改善に活かすために2019年度からIR専門委員会を発足し、各部署から基礎データを収集した。 【2020年度・2021年度の見込】 ・2019年度から実施した自己点検・評価について、2020年度以降も実施し、その方法、効果等を検証し、点検・評価における客観性・妥当性を確保する。 | E54: 4 | F54: 11 | G54: ・自己点検評価委員会で毎年度の自己点検評価の方法等を検討する。 大学基準協会等の点検・評価項目、評価の視点、根拠資料を参考に本学としての点検・評価のシステムを検討する。 2020年度の年度計画、予算作成時（8月）に合わせて簡易な自己点検評価を実施することを目指す。 | H54: ・自己点検・評価の体制を見直し、半期ごとに教育の成果や内容、実施体制にするなど、年度計画の進捗状況を点検し、点検結果を学内にフィードバックして年度計画の各取組を着実に達成するよう促す体制を取り、PDCAサイクルを構築した。 ・認証評価機関である（公財）大学基準協会等の点検・評価項目と本学の中期目標、中期計画及び年度計画の対応表を作成して点検を実施した。ここで出た課題を受けて、第2期中期目標や中期計画では、認証評価機関の点検・評価項目と合致するよう取り組むことを確認した。 ・自己点検・評価委員会内にIR（Institutional Research）専門委員会を発足させ、教務、学生生活、教職員等の基礎データを収集・分析することにより、各分野の業務等の改善に活かすこととした。 | I54: 4
B57: 第４ 教育研究等の質の向上に関する目標
B58: １ 教育の質の向上に関する目標 （２）教育の内容等に関する目標 ③入学者の受け入れに関する目標
B60: 中 期 目 標 | D60: 基本理念・目的、ディプロマ・ポリシー、カリキュラム・ポリシーに基づく教育内容等を踏まえ、入学者を受け入れるための基本方針としてアドミッション・ポリシー（入学者受入れの方針）を明確化し、目的意識や学修意欲の高い入学者を確保するとともに、社会人をはじめ多様な人材の積極的な受け入れを行うため、広報活動の充実や入試選抜方法の最適化を図る。
B62: 中期計画番号 | C62: 中期計画 | D62: 業務の実績（中期計画） | E62: 自己 評価 | F62: 年度計画 番号 | G62: 年度計画 | H62: 業務の実績（年度計画） | I62: 自己 評価
B64: １ 教育研究等の質の向上に関する目標を達成するための措置
B65: （２）教育の内容等に関する目標を達成するための措置
B66: ③入学者の受入れに関する目標を達成するための措置
B67: 9 | C67: ア アドミッション・ポリシーの周知
C68: ディプロマ・ポリシー、カリキュラム・ポリシーを踏まえて明確なアドミッション・ポリシーを定め、公開する。 | D68: 【2016年度～2019年度の総括】 ・2016年度にディプロマ・ポリシーおよびカリキュラム・ポリシーを踏まえたアドミッション・ポリシーを定め、これに基づく多様な人財を確保するための選抜方法を定めた。学生募集要項やホームページで公開するとともに、高校訪問を延べ1,000校程度実施して周知した。 ・2019年度は情報学部の学生募集に伴い、ディプロマ・ポリシー、カリキュラム・ポリシーに基づくアドミッション・ポリシーを改定し、学生募集要項やホームページ等で広く公開した。 【2020年度・2021年度の見込】 ・アドミッション・ポリシーの積極的な公開に努め、これに基づく適正な入学者選抜を実施する。 | E68: 4 | F68: - | G68: ・2017（平成29）年度で対応済み | H68: - | I68: -
C69: イ 入学者選抜方法の策定
C70: （ア）優秀で多様な人材の確保
B71: 10 | C71: 優秀で多様な人材を確保するため、入学後の追跡調査結果を踏まえ、地域に根ざした公立大学として、地域枠を含む入学者選抜方法を策定する。 | D71: 【2016年度～2019年度の総括】 ・地域経営学部は、一般入試および推薦入試（地域枠を含む。）入学者の1年次前学期のGPAを調査している。例年、入試区分別入学者のGPAに差異がないことを確認しており、現状の入学者選抜方法は適切となっている。なお、2019年度には定員減に伴い、過去の志願実績を考慮した上で、地域枠の募集人員を変更した。 ・地域経営学部の推薦入試（地域枠）の内訳 募集人員 2018年度以前 推薦入試43人のうち20人程度 2019年度 12人 志願者数 2016年度9人、2017年度18人、2018年度15人、 2019年度10人 ・地域経営学部では、多様な学生確保を目的に簿記やICTに関する資格保有者を評価する専門学科枠を設けており、2019年度に地域枠同様に募集人員を変更した。 募集人員 2018年度以前 推薦入試43人のうち4人程度 2019年度3人 志願者数 2016年度1人、2017年度4人、2018年度6人、 2019年度3人 ・情報学部は、地元の優秀な学生確保のための地域枠をはじめ、工業科や商業科の高校生を対象とした専門学科枠を設け、多様な人材確保のための入学者選抜方法とした。 ・情報学部の推薦入試（地域枠）の内訳 募集人員 2019年度 10人 志願者数 2019年度 12人 ※年度は入試の実施年度を記載 【2020年度・2021年度の見込】 ・入学後の追跡調査を継続的に行い、データを蓄積することにより、適正な入学者選抜方法のあり方を検討する。 | E71: 4 | F71: 12 | G71: ・内閣府地方創生推進事務局、京都府、福知山市の後援を得て、地域活性化コンテスト「田舎力甲子園」を実施しているが、この「田舎力甲子園」と学生募集状況との関係を分析し、学生募集広報の一つの手段として、その意義を再検討する。 | H71: ・全国の高校生たちが田舎を元気にするアイデアを競う地域活性化策コンテスト「2019田舎力甲子園」では、北近畿地域を始めとする地方都市の抱える社会課題に問題提起し、全国から地域活性化策322策（133個人、189グループ）の前年度57策を大幅に上回る応募があった。応募者の内、本学入試出願校との関係性を分析したところ、2017年度から2019年度の期間で入試出願校51校（福島から鹿児島）の応募が確認でき、学生募集との一定の関係性を見出せた。 ・コンテスト表彰式の実施にあたっては、オープンキャンパスに合わせて実施するなど、学生募集の広報手段として位置づけた。本学に来ていただき、地域課題に対する意識が高い学生の応募に繋げる手段であるとの意義を確認できた。 | I71: 3
F72: 13 | G72: ・全体として志願者 850 名を目指す中で、推薦入試（地域枠）の活用を促し、三たん地域内に在籍する地元学生の志願者確保に努める。特に本学の教学内容、地域への取り組みを理解してもらうこと、高校教員との関係を強化することを目的に以下のように対策する。 (1)大学窓口の一本化 京都府北部と兵庫県北部の高校からの窓口として、それぞれに専任職員を配置する。 (2)地元の高校への出張講義や大学説明、本学見学等への対応 教員による出張講義や大学説明、本学見学への対応等により、本学の教学内容や本学の学修環境の周知に努める。三 たん域内で 1 年間にのべ 25 回程度の出張講義や大学説明会へ対応を目標とする。 (3)きめ細かい高校訪問 窓口となる専任職員が京都府北部と兵庫県北部の高校を高校の状況と時期に応じて訪問活動を充実させる。その他の地区に関しても特に志願実績の多い府県については、各職員が年度当初より訪問を担当し高校教員との関係強化を図る。 (4)地域の高校訪問 退職された高校教員等の協力を得る。 | H72: ・三たん地域内から志願者が47人（内、入学者は26人）となり、推薦入試（地域枠）で定める入学者22人を4人上回った。 ・三たん地域の高校に対しては担当の職員を配置し、その担当者が延べ148回（概ね1校につき年3回程度）訪問を行い、教員との関係強化に努めた。なお、出張講義や大学説明を計55回（出張講義20回、大学説明35回）対応した。（新型コロナウィルス感染症の影響により2回が中止となった。） ・三たん地域以外の近畿地区については専任職員が年2回の訪問を行い、特に情報学部の案内と高校教員との関係強化に努めた。志願実績が多い東海、北陸、中四国については外部委託者がこまめな訪問を行った。 | I72: 4
F74: 14 | G74: ・ 入学者の成績分布と入試区分との関係を分析し、現行の入学者選抜方法を点検する。 | H74: ・入試区分ごとに1年次前学期のGPA成績を確認し、入試区分による差異がないことを確認した。これにより現行の入学者選抜の方法に特に問題がないことを確認している。なお、その後の在学生の成績状況は、本人の意志等に影響するものと考えられるため、教学やIR面からの一貫した追跡が必要と考えられる。 | I74: 3
F75: 15 | G75: ・新学部入試について、設置申請の後、学生募集要項を作成する。 新学部設置に伴って入試区分ごとの募集人員を変更し、入学者選抜要項および募集要項を作成する。特に推薦入試については、地元学生の志願者確保に努めるとともに、適切な志願倍率が確保できるよう検討する。 教研審の結果を受けて文言を調整する。 | H75: ・両学部合冊の入学者選抜要項は6月下旬に完成させ、ホームページに公開するとともに、全国の高校や資料請求者に対して配付し、早期の告知に努めた。 ・地域経営学部の募集要項は9月下旬に作成した。地域経営学部の推薦入試は、全体で35人の募集人員に対して61人が志願した（志願倍率1.74倍）。推薦入試（地域枠）は、12人に対して10人が志願となった。 ・情報学部の募集要項は11月下旬の作成・公表となった。短い募集期間であったが、推薦入試は全体で35人の募集人員に対して64人が志願した（志願倍率1.82倍）。推薦入試（地域枠）は、10人の募集人員に対して12人が志願となった。 | I75: 3
C76: （イ）高大接続
B77: 11 | C77: 高大接続システムの動向及び学力の３要素、３ポリシーを踏まえた入試制度を検討する（平成29年度～）。 | D77: 【2016年度～2019年度の総括】 ・高大接続改革の動向を把握しつつ、この改革に対応する入試の変更予告を2019年度に行った。 【2020年度・2021年度の見込】 ・入試の変更予告を踏まえ、適正な入学者選抜を実施する。また高大接続改革の動向把握に引き続き努める。 | E77: 3 | F77: 16 | G77: ・「学力の三要素」を軸とした高大接続改革の中で、大学入学共通テストに基づいた 2020 年度入学試験の入学者選抜要項を作成する。 | H77: ・高大接続改革に関する情報を収集し、学力の三要素を評価する選抜とするべく入学者選抜の変更予告を行った。 ・大学入学共通テストに基づく入学者選抜要綱は2020年度中に作成する。 | I77: 3
C78: ウ 学生募集活動の充実・体制強化
B79: 12 | C79: 高校や受験生の動向を把握し、出前講義を導入する等学生募集活動の改善に努める。 | D79: 【2016年度～2019年度の総括】 ・志願者から聴取したアンケート結果に基づき、特に一般入試においては、受験校決定に高校教員が大きな影響力を持つことを確認している。地域経営学部では、志願者・入学者の動向から、比較的全国の小規模自治体出身者が多いことが特徴であり、情報学部では、地域経営学部に比べ特定の府県（近畿、愛知県等）からの志願者が多い傾向にある。 この結果をもとに、東海北陸から中四国にかけた広範囲での高校訪問を、例年延べ1,000校程度行い、各地域の高校教員の認知度向上に努める活動を実施した。また、依頼があった高校への出張講義対応やホームページ上での授業動画の公開、高校内での進路説明会等に積極的に参加し、生徒への直接的な募集も継続的に行った結果、地域経営学部の志願倍率は国公立大学・人文社会系の平均値を毎年上回っている。 【2020年度・2021年度の見込】 ・地域経営学部は、志願者の動向に大きな変化が見られず、概ね志願者層が固定化されてきたと考えられる。2020年度は本格的な高大接続改革が始まる年度であるため、前年度の活動を基本としつつ、各年度で有効と考えられる方策を実施する。 ・情報学部は、志願者の動向を引き続き確認しつつ、データを蓄積することで、有効と考えられる方策を選択し実施する。 | E79: 4 | F79: 17 | G79: ・地元三たん地域をはじめ、志願実績の高いエリア（近畿、東海、北陸、中国）や、国公立大学で地域系の学部を設置するエリア（山陰、四国）に対して、職員を中心とした高校訪問活動（目標は延べ 900 校）ならびに受験媒体等を活用しながら、特に高校教員への訴求を中心としたより計画的な高校訪問を展開し、志願者 850 名を目指す。高校訪問においては本学の特徴のアピールをはじめ、教員紹介冊子を活用した研究内容の紹介から出張講義の獲得を目指す。 | H79: ・専任職員が近畿地区の高校を年2回訪問した。 ・3人の外部委託者が兵庫、東海、北陸、中国、九州を主に訪問し、延べ1,412校を訪問した。 ・三たん地域以外の地域についても教員の出張講義に対応し（19回）、学問に対する高校生の興味の喚起に努めた。 ・受験媒体は、情報学部設置のための広報強化を目的に、年度当初から早期の告知を行った。 ・2020年度入学試験結果では、情報学部設置に係る広報を含めた効果的な志願者確保のための学生募集活動を充実強化したが、情報学部の設置認可が2か月遅れたため、目標人数を割り志願者数が763人となった。 | I79: 3
F80: 18 | G80: ・志願時アンケ－ト、入学後の新入生アンケートを実施し、受験生の動向を把握する。 ・社会貢献や地域貢献を兼ねた出張講義（15 回）を実施する。 ・1 年生を中心とした在学生（30人程度）が夏休み期間に出身校を訪問し、高校教員に学生生活や学習状況を伝える。併せて、高校教員に本学への印象についてアンケート調査を行う。 | H80: ・地域経営学部において実施した志願者・入学者アンケートは、共に例年の傾向から大きな変更はなく、特に一般入試の志望校決定には「高校教員の指導」による影響が大きいことを確認した。 ・出張講義は39回（三たん地域20回、その他地域19回）実施し、高校生に対して学問への興味の喚起に努めた。 ・母校訪問は23人の学生が各高校を訪問した。高校教員は主にアクセスや学びの内容、就職状況等について関心が高いことが分かった。 | I80: 4
F81: 19 | G81: ・出願者の利便性の向上および事務作業の効率化のために、Web出願システムを導入し、全面的に運用する。 | H81: ・Web出願システムを導入し、願書受付期間中の事務処理が大幅に効率化した。利用者は夜に出願登録や入学検定料の入金をしており、いつでも利用できるWeb出願の利便性が発揮されたと考えられる。 | I81: 3
B83: 第４ 教育研究等の質の向上に関する目標
B84: １ 教育の質の向上に関する目標 （３）教育の実施体制に関する目標
B86: 中 期 目 標 | D86: 基本理念・目的に基づいた人材を育成するため、必要な教育体制を充実・強化するとともに、基本構想を踏まえ、現行の学部学科の再編成を視野に入れながら、適正な教員組織、事務組織の配置を行う。
B88: 中期計画番号 | C88: 中期計画 | D88: 業務の実績（中期計画） | E88: 自己 評価 | F88: 年度計画 番号 | G88: 年度計画 | H88: 業務の実績（年度計画） | I88: 自己 評価
B90: １ 教育研究等の質の向上に関する目標を達成するための措置
B91: （３）教育の実施体制に関する目標を達成するための措置
B92: 13 | C92: ①将来構想の策定
C93: 自己点検・評価や、教育研究審議会及び経営審議会等での意見を踏まえ、学部・学科の再編や大学院の設置等について将来構想を策定し、その実現を目指す。 | D93: 【2016年度～2019年度の総括】 ・福知山市が設置した「知の拠点」整備構想検討委員会が、本学が2020年度に情報学部を新設することを含めた「知の拠点」整備構想を取り纏め、2018年1月に福知山市に提出した。本学もこの構想策定に参画し、同委員会の検討資料の作成や本学と京都工芸繊維大学との文理連携、地域連携、キャンパス整備等について検討を行った。 ・2018年6月に新学部設置準備室を発足させ、情報学部の設置認可申請に取り組み、2019年11月19日に情報学部設置の認可を受けた。これにより「帰納的教育方法」という先進的な取組みを特色とする情報学部の開設を実現した。 【2020年度・2021年度の見込】 ・「知の拠点」整備構想に基づき本学のキャンパスプランの作成を検討する。 ・大学院の設置等について検討する。 | E93: 5 | F93: 20 | G93: ・ 2018年2月に福知山市が策定した「知の拠点」整備構想に基づき、福知山市、他大学と連携して推進する。 また、2020年4月に設置を予定している情報学部（仮称）の許認可について、確実に取り組むとともに、認可後は、設置計画の円滑な遂行に努め、同整備構想の実現に向けた取り組みと検討を進める。 併せて、既存学部のカリキュラムを改革し、分野の充実と見直しを行い、学修成果の向上を図る。 | H93: ・「知の拠点」整備構想に基づき、2019年3月に情報学部の設置認可申請書を文部科学省に提出し、11月に認可された。情報学部の設置準備については、施設等の整備や教員採用など、開設に必要な事項を着実に実施した。 ・地域経営学部においては、カリキュラムの改革を実施し、情報学部との文理連携の充実を図るとともに、「地域経営学」の明確化を通して学修の意義の周知並びに学修成果の向上を目指した。また、北近畿地域を対象として、地域経営学の学修成果の検証を行った。 | I93: 5
C94: ②学生支援
B95: 14 | C95: ア 生活支援
C96: 学生の心身の健康増進と安心・安全な学生生活への支援の充実を図る。 | D96: 【2016年度～2019年度の総括】 ・学生の課外活動に対する支援、奨学金・アルバイト情報等の経済支援および不動産業者情報と食堂等を含めた生活環境や保健室とカウンセリングルームの開室等健康管理に関する相談と支援を行った。 ・退学・休学の予防のため、著しく出席が不良である学生については、自宅訪問や保護者への連絡を行った。 【2020年度・2021年度の見込】 ・課外活動の支援、経済支援および生活環境と健康管理に対する相談と支援を強化する。また、退学・休学の予防等の修学支援を行うため、各ゼミ担当者・教務委員会との情報共有と連携を強化する。 | E96: 3 | F96: 21 | G96: ・学生の課外活動に対する支援、奨学金等の経済支援、および生活環境や健康管理等に関する相談、支援を実施する。また、学生からの意見・要望等を直接的に汲み上げる仕組みを、学生の代表たる学友会との会合にて検討する。 | H96: ・課外活動支援として、学友会執行部主催行事及び大学祭実行委員への助言と運営支援を行った。この中には、学友会主催で約40人が参加した宿泊行事「学生交流会（9/28-29宮津市）」の引率も含まれる。 ・奨学金について、日本学生支援機構等の説明会や個別相談を実施し、学生の経済支援を行った。 ・生活環境の啓発について、学生ガイダンスにおいて、SNSの利用や飲酒等に関する諸注意を行った。 ・学生の健康管理として、保健室を週2日開室した。 ・学生要望の汲み上げについて、学友会執行部とランチミーティングで意見交換を行い、これを受けて通学時の危険箇所改善を福知山市に要望した。 | I96: 3
F97: 22 | G97: ・教職員間で学生情報の共有を図るため、学籍管理や学生支援関連業務と教務関連業務等が連動可能な教務系システムを導入する。 | H97: ・修学カルテを試行的に稼働させ、指導教員が学修指導への利用を開始した。 | I97: 3
F98: 23 | G98: ・臨床心理士によるカウンセリングルームの開室を継続する。カウンセリングルームは原則授業のある月に2回開室するが、開室の曜日に可変性を持たせ、必要に応じてカウンセリングを実施するなど柔軟に対応できるようにする。学生便覧に「障がい学生への支援について」の項目を設け、支援が必要な学生の相談窓口を明確にする。 またLGBT等、目に見えない悩みを抱えた学生への対応については、可能な範囲内で情報を収集し、学生委員会で適宜対応を検討する。 | H98: ・臨床心理士によるカウンセリングルームを月2回開室し、11件（前年度10件）の相談を受け付けた。開室日は、月曜もしくは水曜とした。 ・学生便覧に「障がい学生への支援について」の項目を加え、相談窓口を明確にした。 ・LGBT等、目に見えない悩みを抱えた学生の相談等はなかった。 | I98: 3
F99: 24 | G99: ・福知山市や不動産業者と連携して市内の学生用アパート・マンションを把握し、ホームページでの学生への情報提供などを継続して行う。 | H99: ・ホームページで学生への住宅情報を提供した。 ・情報学部設置に伴い新入生が増えることから、全不動産事業所に住宅供給増を呼びかけ、2件の新規不動産事業所を紹介先に加えた。 ・学生数の増加に伴う学生の住宅確保への対応として、福知山市と連携し、福知山市営住宅跡地（土地賃借料なし）を活用した学生向け住宅建設・運営事業に係る土地利用事業者についての公募型プロポーザルを実施し、委託事業者が決定した。 | I99: 4
F100: 25 | G100: ・2019年度より教学情報システムの運用を開始し、サークル活動への関わりや奨学金の状況を把握し、成績の情報も含めて情報を共有し、退学・休学の予防などの修学支援を強化する。 | H100: ・学生基本情報として、現住所、健康診断結果、課外活動参加状況及び奨学金受給状況のデータを整備した。 ・退学・休学の予防などの修学支援については、著しく出席が不良である学生に、自宅訪問や保護者への連絡等を行った。 | I100: 3
F101: 26 | G101: ・2018年度「学生生活に関する調査」（アンケート）結果等と 食堂が独自に回収したアンケートを資料として、学生委員会、学生、および食堂業者と運営について、検討を行う体制を構築する。年3回程度会議を持ち継続的な改善に取り組む。 | H101: ・食堂委託事業者との会合を2度実施し、学生のアンケート結果や要望をもとに販売商品の種類を増加させた。 ・食堂業務委託に係る公募型プロポーザルにより、2020年4月から3年間の委託事業者が決定した。新委託事業者には、学生からの意見・要望を伝え、メニュー等に反映した。席数を80席増やして300席とし、混雑緩和を図った。 | I101: 4
B102: 15 | C102: イ キャリア支援
C103: 専任の担当者によるキャリア形成及び就職活動支援を実施する。 | D103: 【2016年度～2019年度の総括】 ・卒業年次を迎える学生が旧私学時代の入学者から公立大1期生(2016年度入学者)へ変化する中で、学生の人数や志向・能力等の変化に応じて担当者が3年次の後学期から学生全員に面談を複数回実施するとともに、ゼミ担当教員による個別面談も実施した。この結果、就職希望者は4年連続内定率100％を達成した。4年間で卒業生138人（うち北近畿地域出身者40人）のうち32人が北近畿地域に就職した。 ・出身地別の就職状況を分析すると、北近畿地域への就職者数が増加（2016年度7人⇒2019年度12人）したほか、金融（7人）・公務（5人）の就職者が増えたことも影響し、地方出身者が地方に就職する人材還流システムの前進に繋がった。 【2020年度・2021年度の見込】 ・ゼミ担当教員と協力しながら、自走できる学生を育成する。就職活動に悩みを抱える学生に対しては、学内専任担当のキャリアカウンセラーが個々の相談に応じ、個々のキャリア実現支援をする。新型コロナウイルスの影響が予想されるため、社会状況に応じた支援策を実施する。 | E103: 4 | F103: 27 | G103: ・キャリアサポート委員会を中心として就職支援活動の充実に取り組む。公務員試験対策講座の充実及び求人WEB登録システムを強化する。キャリアセミナーの開催（月1～2回程度実施）や各種情報の提供を実施する。セミナーへの参加は全体平均で3年生の25％以上を目指す。さらに、キャリアコンサルタントおよびキャリア委員だけでなく、ゼミ担当教員が面談に同席することも含めて協働し、キャリア面談を、3年生全員を対象に主に後学期に実施する。4年生に対しては、個別指導を実施する。加えて、3年生前期と2年生後期については、正課科目「キャリアデザイン」と連携し、その中でもキャリア支援を実施する。1年生、2年生前期については、ガイダンスを中心にキャリア支援を実施する。 | H103: ・公務員試験対策講座をより早く実施できるように、前学期の6月に講座を開講し、64人（1年次生11人・2年次生12人・3年次生41人）が受講した。専門科目については、昨年度の経済科目に続き、本年度は法律科目を新たに開講した。また、民間採用試験として、初めてSPI対策試験講座を7月に全8回実施し、公務員試験対策講座とは別に56人が受講した。 ・キャリアセミナーについては、前学期は計15講座を実施し、延べ1,074人が参加した。後学期は計13講座を実施し、延べ740人が参加した。さらに大手企業を目指すための「少人数・特化型セミナー」の受講人数を限定し初めて実施した。計10講座を実施し、計206人が参加した。 ・キャリアコンサルタントによるキャリア面談については、前学期は3年生ゼミと連携し、ゼミごとの面談を67人（約45％）実施した。後学期については、キャリアコンサルタントが3年次生ゼミ教員全員に面談し、各ゼミ教員とゼミ学生の進路情報について共有するとともに、双方向によりキャリア支援ができる体制とした。 | I103: 4
F104: 28 | G104: ・【再掲7】 ポートフォリオは、導入する学務システムを用いて、2019年度前期中に詳細を決定するとともに、2年生から試行的に導入する。 | H104: 【再掲7】 ・教育効果の検証とプロジェクトの実施経験やリーダーシップなど学生自身の学修の習熟度や大学生活での学びや経験を記録するためのツールとして「修学カルテ」という名称で本学におけるポートフォリオを作成した。ポートフォリオは、教学情報システム「WebClass」の修学カルテ機能を用いて試案を作成し、後学期のオリエンテーションにおいて、2年次生を対象に試行的に実施し、学びを振り返る機会を設けた。 ・試行実施の結果を踏まえて内容を修正し、新年度に向けたオリエンテーションにて、新2年次生から4年次生を対象にポートフォリオを実施する。 | I104: 4
F105: 29 | G105: ・課外の公務員試験対策講座を教養科目以外に専門科目（法律）の講座を新たに開講する。また、行政職等に就いた本学卒業者による就職講話を実施するとともに、地元企業の説明会、「京都北部合同企業説明会」を実施し、3年生の過半を参加させる。 | H105: ・6月に専門科目の法律を開講した。 ・近年の就職活動早期化に合わせ、少しでも就職活動本番前に業界・企業理解を進めるため「学内業界・企業研究会」を12月7日に3年次生のキックオフと合わせ初めて実施し、3年次生121人（出席率80.1%）が参加し、例年より早期に就職活動を開始させた。 ・例年3月に行う「京都北部合同企業説明会」は、3月9日に繰り上げて実施する予定だったが、新型コロナウィルスの影響で中止した。 | I105: 3
F106: 30 | G106: ・就職活動支援ならびに資格取得を推奨するため、学内においてTOEIC等の資格試験を実施する。さらに授業内においても関連する資格取得について、授業担当者より推奨し受験を促す。（簿記・TOEIC・旅行業務取扱主任者等）何らかの形で資格取得状況を把握する。 | H106: ・5月30日に公務員講座説明会と合わせて資格取得講座説明会を実施し、76人の学生が出席した。 ・教育後援会からの資格合格奨励制度を今年度も実施し、34人が受給した。なお、過年度の受給状況は、2016年度11人、2017年度23人、2018年度37人となっている。 ・簿記は、日商簿記3級に13人が合格した（前年度合格者4人）。 ・日商原価計算初級は、原価計算論の授業と連携し授業担当者から受験を促した結果、19人が合格した。 | I106: 3
B107: 16 | C107: ③国際交流の推進
C108: 外国人留学生の受け入れと生活支援、学生の留学支援、海外の大学・研究機関等との連携、協定の締結等に取組む。 | D108: 【2016年度～2019年度の総括】 ・中国・西南交通大学との学術交流協定を締結したほか、海外から研究者を招聘し、講演会やシンポジウムを毎年1回から2回程度実施した。 ・学生の短期留学プログラム開設の準備をした。 ・地域で国際交流活動を行った。 ・外国人留学生については、2016年度に1人入学した。 【2020年度・2021年度の見込】 ・これまでの国際交流委員会の取組みを基礎とし、国際交流センターの設立に向けて準備を進める。 | E108: 3 | F108: 31 | G108: ・国際交流センターの発足に向け検討する。他大学との交流では2018年度に引き続き、中国西南交通大学公共政策学院との地域経営研究に関する交流を行う(9月頃）。 ５月には中国成都市からの「農村観光視察団」の訪問に合わせて地域経営に関する日中国際シンポジウムを実施する。 | H108: ・国際交流センターの発足にむけて、学術交流事業や短期留学事業、地域と外国人の交流事業、留学生募集などの検討会議（2回）を行い、2020年度の発足を目指して準備を進めた。 ・中国成都市からの農村観光視察団を受け入れ、農村振興、特に観光産業を活用した農村の経済振興の課題についてシンポジウムを実施し、日中農村振興学術交流を行った。また、西南交通大学公共管理及政法学院（中国）と本学地域経営学部との間に「学術交流及び協力に関する協定」を締結した（5月）。 ・中国・西南交通大学公共政策学院と地域経営研究に関するワークショップ形式の交流を行った（9月）。 ・中国・重慶工商大学の研究交流のため研究者を招き、交流活動を行った（11月）。 ・韓国・淑明女子大学から研究交流のため研究者を招き、講演会を開催した（2月）。 ・学生の短期語学留学プログラムの開設に向けて、オーストラリア・ディーキン大学の英語プログラムを視察した（2月）。 | I108: 4
B112: 第４ 教育研究等の質の向上に関する目標
B113: ２ 研究の質の向上に関する目標 （１）研究の質の向上に関する目標
B115: 中 期 目 標 | D115: 「地域協働型教育研究」を展開し、持続可能な社会システムの構築のための研究を理論と実践の両面から推進する。そのため、北近畿地域における開かれた学びの拠点として、「過疎・少子高齢化」、「若者の雇用確保」、「地域産業の振興」など の課題に対して 、地域や組織 、団体、業種間を超えた連携・協働体制を構築し、研究成果を教育や地域社会に還元する。
B117: 中期計画番号 | C117: 中期計画 | D117: 業務の実績（中期計画） | E117: 自己 評価 | F117: 年度計画 番号 | G117: 年度計画 | H117: 業務の実績（年度計画） | I117: 自己 評価
B119: ２ 研究の質の向上に関する目標を達成するための措置
B120: （１）研究水準及び研究の成果等に関する目標を達成するための措置
C121: ①地域に資する地域経営研究の拠点大学
B122: 17 | C122: ア 地域経営研究の拠点大学づくりへの取り組み
C123: 「地域協働型教育研究」を展開し、積極的に地域社会との関わりを持つ中で、世界的な視野を持ちながら、過疎化の進展、地域産業の衰退など地域の様々な課題の解決に資する地域経営研究の拠点大学を目指す。 | D123: 【2016年度～2019年度の総括】 ・「地域協働型教育研究」を探求することを目的とし、2017年度に「地域経営学研究会（地域経営学とは何か）」、2018年度に「地域協働型教育研究会（福知山公立大学における地域協働型教育の「これまで」と「これから」」、2019年度に「北近畿地域研究会（地域研究の成果と課題を地域経営学の視点から明らかにする）」を発足し、活動を行ってきた。それらの研究成果として、「福知山公立大学研究紀要別冊第1号、第2号、第3号」を発刊した。以上を通して、未確立の学術領域である「地域経営学」「地域協働型教育研究」に関する理論的・実証的研究により学術の方向性を示した。ディプロマ・ポリシー及びカリキュラム・ポリシーの改定や授業科目の見直し等、2020年度新カリキュラムにその成果を反映させた。 ・2018年度より教員のオンラインデータベースの活用を進めており、2018年度で6人（8件）、2019年度で9人（14件）が契約し、情報収集など地域経営研究活動に活かした。 【2020年度・2021年度の見込】 ・情報学部の教員を含めた新たな研究会を立ち上げ、文理連携した地域協働型の研究を推進する。 ・SDGｓの地域における取組について、自治体との連携事業を実施する。具体的には、「与謝野町スマートグリーンビレッジ確立協議会に参加し（教員5人）、①自然循環農業推進②防災・減災システム構築③市民教育システムなどの連携事業を構築する。 ・継続である「関係人口創出・拡大事業」における研究課題を継承、発展させる。 | E123: 3 | F123: 32 | G123: ・2017・2018年度の「地域経営学研究会」の活動と2018年度の「地域協働型教育研究」の活動を踏まえ、新たな研究会を立ち上げて地域協働型の研究の成果と課題を纏める。同活動には、2019年度の「福知山公立大学研究活性化助成金」を活用する。 また、2018年度の「地域協働型教育研究」の活動については、2018年度中に論文集を作成し、2019年度に報告会を開催する。 ・個人研究費とは別予算として教員1人当たり30千円を計上し、希望するデータベースを各教員で契約し、教員・研究活動の推進を図る。 | H123: ・地域経営学の視点から具体的な地域研究の成果と課題をまとめるため、新たに「北近畿地域研究会」を立ち上げ、地域協働型教育の実践と検証など地域経営学をテーマにしたものや地域社会の個別のテーマでの分析・提言を「福知山公立大学研究紀要別冊第3号」に7本の論文としてまとめた。また、研究成果は、学内合評会で発表し、学内で地域経営学の理解を深めた。 ・「地域協働型教育研究（地域研究プロジェクト）」では、教員による成果報告会（7月13日）を市民を対象に開催した。大河ドラマ放映による経済効果の推計など7テーマをポスターセッション方式で発表し、来場者に説明した。 ・データベース契約件数が教員9人で14件となり、前年度より6件増加した。契約実績は次のとおり。①証券アナリストジャーナル②現代ファイナンス③医学中央雑誌④メディカルオンライン⑤マーケティングジャーナル⑥地域学研究⑦日本観光学会誌⑧データでみる県勢2019⑨都市データパック2019⑩Collaboration and Co-creation⑪Social Accounting and Public Management⑫「社会調査」系電子ジャーナル⑬47行政ジャーナル⑭朝日新聞デジタル | I123: 4
F124: 33 | G124: ・北近畿地域連携会議と連携しつつ、北近畿の課題解決に資する「地域研究プロジェクト」を学内公募する。 | H124: ・地域・企業が抱える課題に対して本学が有する「知」を活用する機会を創出することを目的に、地域研究プロジェクトとして、次の4件に取り組んだ。 ①大河ドラマ「麒麟がくる」の放映が福知山および北近畿地域における地域活性化に与える影響に関する研究 ②機械学習型人工知能を用いた安価な農作物の選別システムの構築 ③高精度衛星測位を用いた自動車運転技能確認の研究 ④北近畿地域におけるデータ駆動型の観光地域経営に関する研究 ※①②は自由テーマ。③④は北近畿地域連携会議が取り組む研究テーマと関連性のある指定テーマ。 | I124: 3
F125: 34 | G125: ・包括協定団体との戦略的連携の一環として、包括協定団体との地域協働型教育研究の新規事業を展開する。具体的には、京都府北部地域連携都市圏を構成する４市２町と連携し、講師を招いたセッション 集会）を実施（年4回）する。 | H125: ・包括協定団体、とりわけ京都府北部の自治体から構成される京都府北部地域連携都市圏形成推進協議会と共催（一部受託事業）し、「北近畿創生フューチャーセッション（生涯学習講座）」を企画実施した。本企画は、圏域やセクターを超えて北近畿地域で共通する課題を北近畿地域内のスピーカーからの話題提供により、課題解決のための方策を参加者全員で検討し、コミュニティを創造するもので、実施した企画テーマ等は以下のとおり。 ①健康長寿の地域づくりの未来（6/29福知山市、40人参加） ②高齢ドライバーと地域交通の未来（10/29京丹後市、46人参加） ③多文化共生と防災の未来（2/1舞鶴市、42人参加） ④地域コミュニティと自治の未来（2/22与謝野町、54人参加） | I125: 3
B126: 18 | C126: イ 関係情報の収集
C127: 統計資料をはじめ北近畿地域の様々な情報の収集、整備を図る。 | D127: 【2016年度～2019年度の総括】 ・2017年度より、京都府北部の5市2町を中心とした北近畿地域の統計資料等を収集し、本学ホームページにおいて「北近畿地域統計資料等一覧」を掲載した。 ・統計資料等は、2019年度末時点で、401種類の資料を掲載した。 【2020年度・2021年度の見込】 ・統計資料等の収集を継続し、2021年度末時点で、430種類の掲載を目指す。 | E127: 3 | F127: 35 | G127: ・2017年度より継続して収集している5市2町を中心とした北近畿地域の統計資料等についてデータ化を進め、公開する。また、収集した統計資料等は、本学ホームページにおいて「北近畿地域統計資料等一覧」を掲載する。 | H127: ・2017年度より、京都府北部の5市2町を中心とした北近畿地域の統計資料等を収集し、本学ホームページで「北近畿地域統計資料等一覧」を掲載した。 ・統計資料等は、2019年度末時点で401種類の資料を収集し、前年度より81種類増加した。 | I127: 3
F128: 36 | G128: ・施設利用の目安として、①施設利用件数90件、②蔵書増4,000冊、③府県を超えた行政機関等の地域連携部門と協力した連携事業2件、④大学と地域住民等との共同プロジェクト等により創出された新商品・新製品等の開発1件を目指す。 | H128: ・メディアセンター施設利用の実績は、目標を大幅に上回った。 ①施設利用件数 370件（前年度139件） ②蔵書増 4,980冊（登録冊数：80,076冊） ③府県を超えた行政機関等の地域連携部門と協力した連携事業として、新商品開発事業、府立高校図書館との連携、福知山市教育委員会との連携、丘児童センターとの交流事業、綾部中学校職場体験学習、3Dモデリング講座、RESAS研修会を実施した。 ④本学教員と民間企業等との共同開発により、栗の大きさや重量、虫食い傷などの選別作業をロボットが行うための「外観検査AIソフト」を開発し、福知山産業フェア（10月）での実演、京都ビジネス交流フェア（2月）でのパネル展示を行った。 | I128: 4
B129: 19 | C129: ②開かれた学びの拠点として、外部団体との連携・協力の推進
A130: ● | C130: 地域や組織、団体、業種間を越えた連携・協力を推進する。 | D130: 【2016年度～2019年度の総括】 ・2016年度に北近畿地域連携センター及び市民学習・キャリア支援センターが発足し、2017年度には学内に地域連携の拠点Kita-re、2018年度には新町商店街内にまちかどキャンパス「吹風舎（ふくちしゃ）」を開設した。 ・2017年度には民間約50団体の賛同を得て、北近畿の課題をテーマに調査研究を推進する「北近畿地域連携会議」を発足させた（代表幹事：井口和起学長）。 ・2016年度からの4年間で京都府北部4市2町を含む計17団体との包括協定を締結し、教育面・研究面それぞれで開かれた学びの拠点づくりに協力頂いた。 ・2019年度に受託した総務省「関係人口創出・拡大事業」モデル事業は、地域や組織、団体、業種間を越えた連携・協力を推進することができた。 【2020年度・2021年度の見込】 ・これまでの成果を踏まえ、大学の大きな役割の一つである地域貢献について更に前進を図るため、地域連携・協力のための2つのセンターと1つの施設を北近畿地域連携機構に改組し、継続的事業のほかに新たな事業に取り組む。また、北近畿地域連携会議企業との連携研究を引き続き展開する。 ・府県を越えた行政機関の地域連携部門と協力した連携事業を展開する。 ・2020年度から2021年度にかけて、「知の拠点」にふさわしい推進事業に取り組む。 ・総務省「関係人口創出・拡大事業」モデル事業の後継事業として、福知山市等と連携し、地縁型関係人口（地方から都市に転出した関係人口（予備軍含む））の創出・拡大に向けて協働する。 | E130: 4 | F130: 37 | G130: ・北近畿地域連携会議において、参加企業等から会費を徴収することを総会に提案する。 また、同研究会で研究プロジェクトを公募（目標２件）する。 2017年度に設定した研究テーマの成果は2018年度中に報告書として取り纏め、2019年度北近畿地域連携会議総会で報告する。 ・包括協定先との定期協議会については、開催回数を2回とし、教育・研究・社会貢献分野それぞれにおいて連携・協力を推進する。1回は担当者レベルを想定して実務的な協議を行う（前半）、1回は代表者を集めての意見集約の会議を実施する（後半）。 | H130: ・産学連携による北近畿地域連携会議では、2019年度会員総会（5月28日）において、同会議の持続可能な財政基盤づくりのため、参加企業等から会費の徴収を検討する提案が了承され、12月から2月にかけて会員が求めるサービスやメリットなどを見える化するためのアンケート調査を実施した。今後、調査の分析結果を踏まえて方向性を検討していく。 ・北近畿地域連携会議の研究プロジェクト公募では、応募5件のうち3件を採択し、残る2件のうち1件は連携研究とした。2017年度・2018年度の研究成果報告書が遅れ、2019年度の総会で口頭報告し、報告書を2019年度内に発行した。 ・包括協定先との定期協議会については、事務担当者会議を10月4日に開催した。17の包括協定締結団体の事務担当者と連携し、本学の地域連携状況を共有したほか、情報学部開設を見据えての地域連携に関してワークショップ形式で意見交換等を行った。なお、代表者会議は、3月19日に予定していたが、新型コロナウィルス感染防止のため中止となった。 | I130: 2
...

Sheet 【作成用】学部・学科等
B5: 大学 | C5: 学部 | D5: 学科 | E5: 入学定員 | G5: 編入学定員 | H5: 収容定員 | I5: 在籍学生数
B6: 福知山公立大学 | C6: 地域経営学部 | D6: 地域経営学科 | E6: 95人 | G6: 5人 | H6: 335人 | I6: 295人
D7: 医療福祉経営学科 | E7: 25人 | G7: 2人 | H7: 89人 | I7: 71人
C8: 計 | E8: 120人 | G8: 7人 | H8: 424人 | I8: 366人
B9: ※平成30年5月1日現在
C13: 学部 | D13: 学科 | E13: 1年 | G13: 2年 | H13: 3年 | I13: 4年 | J13: 計 | K13: 編入学 | L13: 収容定員
C14: 地域経営学部 | D14: 地域経営学科 | E14: 95 | G14: 95 | H14: 40 | I14: 30 | J14: =SUM(E14:I14) -> 260 | K14: 10 | L14: =J14+K14 -> 270
D15: 医療福祉経営学科 | E15: 25 | G15: 25 | H15: 10 | I15: 20 | J15: =SUM(E15:I15) -> 80 | K15: 4 | L15: =J15+K15 -> 84
C16: 計 | E16: =SUM(E14:E15) -> 120 | G16: =SUM(G14:G15) -> 120 | H16: =SUM(H14:H15) -> 50 | I16: =SUM(I14:I15) -> 50 | J16: =SUM(J14:J15) -> 340 | K16: =SUM(K14:K15) -> 14 | L16: =SUM(L14:L15) -> 354
I19: 単位：人
B20: 大学 | C20: 学部 | D20: 学科 | E20: 入学定員 | F20: 編入学定員 | G20: 収容定員 | H20: 現員
H21: 男 | I21: 女 | J21: 計
B22: 福知山公立大学 | C22: 地域経営学部 | D22: 地域経営学科 | E22: 95 | F22: 5 | G22: 335 | H22: 249 | I22: 122 | J22: 371
D23: 医療福祉経営学科 | E23: 25 | F23: 2 | G23: 89 | H23: 39 | I23: 59 | J23: 98
C24: 合計 | E24: 120 | F24: 7 | G24: 424 | H24: 288 | I24: 181 | J24: 469
B25: ※2019年5月1日現在
B28: 大学 | C28: 学部・研究科 | D28: 学科・専攻 | E28: 入学定員 | F28: 編入学定員 | G28: 収容定員 | H28: 現員
H29: 男 | I29: 女 | J29: 計
B30: 福知山公立大学 | C30: 地域経営学部 | D30: 地域経営学科 | E30: 75 | F30: 5 | G30: 310 | H30: 174 | I30: 177 | J30: =SUM(H30:I30) -> 351
D31: 医療福祉経営学科 | E31: 25 | F31: 2 | G31: 104 | H31: 39 | I31: 65 | J31: =SUM(H31:I31) -> 104
C32: 情報学部 | D32: 情報学科 | E32: 100 | F32: 2 | G32: 404 | H32: 316 | I32: 114 | J32: =SUM(H32:I32) -> 430
C33: 地域情報学研究科 | D33: 地域情報学専攻 | E33: 20 | G33: 40 | H33: 28 | I33: 3 | J33: =SUM(H33:I33) -> 31
C34: 合計 | E34: =SUM(E30:E33) -> 220 | F34: =SUM(F30:F33) -> 9 | G34: =SUM(G30:G33) -> 858 | H34: =SUM(H30:H33) -> 557 | I34: =SUM(I30:I33) -> 359 | J34: =SUM(H34:I34) -> 916

Sheet 【作成用】組織図（平成30年）
B3: 公立大学法人福知山公立大学 組織図
L5: 事務局
E6: 理事会選考会議
H7: 経営審議会 | M7: 総務企画・財務グループ
B9: 理事長（学長） | E9: 理事会 | N9: 企画戦略
H11: 教育研究審議会 | N11: 地域連携・協働
E13: 監事 | N13: 総務・人事
E15: 内部統制推進委員会 | N15: 財務
B18: 公立大学 | E18: 地域経営学部 | H18: 地域経営学科 | M18: 学務・学生支援グループ
H20: 医療福祉経営学科 | N20: 入試広報
N22: 学務
E24: 教授会 | I24: 入試委員会 | N24: 学生・キャリアサポート
I26: 教務委員会
E28: 自己点検・評価委員会 | I28: 学生委員会
E30: 広報委員会 | I30: キャリアサポート委員会
E32: SD委員会 | I32: FD委員会
E34: 衛生委員会
E36: 危機管理・人権・倫理委員会
E38: 国際交流センター委員会
E40: 研究費不正使用防止対策委員会
E42: 研究活動不正行為防止対策委員会
D44: 付属施設
E46: メディアセンター（図書館） | I46: メディアセンター委員会
E48: 北近畿地域連携センター | I48: 北近畿地域連携センター委員会
E50: 市民学習・キャリア支援センター | I50: 市民学習・キャリア支援センター委員会

Sheet 年度計画等（全体）
D1: 公立大学法人福知山公立大学中期計画・年度計画（平成31年度年度計画・平成30年度執行見込）
B3: 中期目標 | E3: 中期計画 | J3: 平成３１年度年度計画
B4: 前文
D5: 福知山公立大学は、京都府北部、兵庫県北部にまたがる丹波、丹後、但馬により形成される「三たん地域」の中央部にある福知山市に位置する北近畿地域唯一の４年制大学である。 人口60万人に達する北近畿地域は、豊かな自然、歴史・文化資源、特色ある産業や高次都市機能を備えているものの、人口減少や高齢化の進行、産業の衰退、雇用の減少、市街地の空洞化など、様々な課題が生じている。 特に、進学・就職による若者の都市部への流出は深刻であり、地域から貴重な人材と資産、活力が失われていることを意味する。 北近畿地域が人口減少・高齢化に伴う地域活力の減退からの脱却を図り、持続可能な地域社会の形成、地域が本来持つ素晴らしい資源を活かした地方創生を実現するためには、北近畿地域の行政機関や企業、金融機関、各種団体等と広域的に連携・協力して地域全体の活性化を図るとともに、地域の発展に寄与する人材を育成し、「地域で学び、地域で働く」という人材循環システムを構築しなければならない。 そのことが、北近畿地域のみならず、同様の問題を抱える日本全国の様々な地域を舞台に活躍する人材の育成及び広域的な人材循環にもつながる。 以上を踏まえ、公立大学法人福知山公立大学（以下、「法人」という。）の設立団体である福知山市は、福知山公立大学が福知山市のみでなく北近畿地域にとっての学びの拠点となり、地域住民の誇りとなる魅力あふれる大学となるよう、“教育のまち福知山「学びの拠点」基本構想”（以下、「基本構想」という。）に掲げる次の基本理念のもと、中期目標を定め、法人に指示するものである。 ○地域を愛し、地域のために働きたいと思える、地域の将来を担う人材育成拠点を構築する。 ○地域産業の振興と雇用創出による賑わいと地域活力にあふれ、若者が定住する魅力あるまちを生み出す産業振興拠点を構築する。 ○市民一人ひとりの自己実現を支援し、生涯にわたり学びを享受できる生涯学習拠点を構築する。
B6: 第１ 基本的な目標 | E6: 第１ 基本的な目標
C7: １ 基本理念・目的 | F7: １ 基本理念・目的
D8: 福知山公立大学の基本理念を、「市民の大学、地域のための大学、世界とともに歩む大学」とする。 この基本理念のもと、福知山公立大学は、総合的な知識と専門的な学術を深く教授研究するとともに、地域協働型教育研究を積極的に展開することにより、地域に根ざし、世界を視野に活躍できる高度な知識及び技能を有する人材を育成し、北近畿地域の持続可能な地域社会の形成と地方創生に寄与することを目的とする。 そのため、基本構想に基づき、様々な地域課題の調査研究の実践を通じて、地域の将来を担う人材を育成するとともに、地域住民の自己実現を支援する「学びの拠点」を構築し、世界に貢献する開かれた大学の実現を目指すものとする。 | I8: 福知山公立大学は、平成28年4月1日に学校法人成美学園成美大学から福知山市を設置者とする公立大学法人福知山公立大学として新たなスタートをきった。 基本理念を「市民の大学、地域のための大学、世界とともに歩む大学」とする本学は、日本で唯一の地域経営学部を有し、総合的な知識と専門的な学術を深く教授研究するとともに、地域協働型教育研究を積極的に展開することにより、地域に根ざし、世界を視野に活躍できる高度な知識及び技能を有する人材を育成し、北近畿地域をはじめとする地域における持続可能な社会の形成と地方創生に寄与することを目的とする。そのため、「学びの拠点」を構築し、世界を視野にかつ地域に開かれた大学のあるべき姿を追究する。 このような基本理念と目的を踏まえ、中期目標を実現するための具体的計画として中期計画を定める。
C9: ２ 目指すべき大学像 | F9: ２ 目指すべき大学像
D10: 福知山公立大学の基本理念・目的に基づき、目指すべき大学像を次のとおりとする。 （１） 地域社会を支え、地域社会に支えられる大学 （２） 持続可能な社会の創出に貢献する知の拠点大学 （３） 地域と世界をつなぐ、グローカリズム研究実践の拠点大学 | I10: 福知山公立大学の基本理念・目的に基づき、目指すべき大学像を次のとおりとする。 （１） 地域社会を支え、地域社会に支えられる大学 （２） 持続可能な社会の創出に貢献する知の拠点大学 （３） 地域と世界をつなぐ、グローカリズム研究実践の拠点大学
C11: ３ 育成する人材像 | F11: ３ 育成する人材像
D12: 福知山公立大学が育成する人材像を、「地域に根ざし、世界を視野に活躍するグローカリスト（Glocalist）※」とする。 世界（グローバル）を見つめる幅広い視野を持ち、地域（ローカル）に根を下ろし、地域で活躍できる人材を育成するため、フィールド研究重視の実践的教育システムを採用し、学生と教職員が地域に出向く「地域協働型教育研究」を展開することにより、ゆるぎない信念、豊かな包容力、的確な課題解決力を育てるアクティブな教養教育を展開する。 ※グローカリスト（Glocalist）：GlobalとLocalをあわせた“Glocal”に、人を意味する“ist”を加えた造語。 | I12: 福知山公立大学が育成する人材像を、「地域に根ざし、世界を視野に活躍するグローカリスト（Glocalist）※」とする。 世界（グローバル）を見つめる幅広い視野を持ち、地域（ローカル）に根を下ろし、地域で活躍できる人材を育成するため、フィールド研究重視の実践的教育システムを採用し、学生と教職員が地域に出向く「地域協働型教育研究」を展開することにより、ゆるぎない信念、豊かな包容力、的確な課題解決力を育てるアクティブな教養教育を展開する。 ※グローカリスト（Glocalist）：GlobalとLocalをあわせた“Glocal”に、人を意味する“ist”を加えた造語。
B13: 第２ 中期目標の期間 | E13: 第２ 中期計画の期間 | J13: 第２ 年度計画の期間
D14: 中期目標の期間は、平成28年4月1日から平成34年3月31日までの6年間とする。 | I14: 中期計画の期間は、平成28年4月1日から平成34年3月31日までの6年間とする。 | L14: 平成30年4月1日から平成31年3月31日までとする（中期計画期間の3年目）。
B15: 第３ 教育研究上の基本組織 | E15: 第３ 教育研究上の基本組織 | J15: 第３ 教育研究上の基本組織
D16: この中期目標を達成するため、福知山公立大学に、次の学部学科を置く。 学部 学科 なお、中期目標期間中において、基本構想及び地域社会のニーズや社会情勢等を踏まえ、学部学科編成の最適化及び早期に入学定員200名の実現を目指すものとする。

Sheet 自己点検評価体系図
B3: 公立大学法人福知山公立大学 組織図
K5: 事務局
E6: 理事会選考会議
H7: 経営審議会 | M7: 総務企画・財務グループ
B8: 理事長（学長）
E9: 理事会 | N9: 企画戦略
H11: 教育研究審議会 | N11: 地域連携・協働
E13: 監事 | N13: 総務・人事
H15: 内部統制推進委員会 | N15: 財務
H17: リスクマネジメント委員会
B18: 公立大学
E19: 地域経営学部 | H19: 地域経営学科 | M19: 学務・学生支援グループ
H21: 医療福祉経営学科 | N21: 入試広報
N23: 学務
E25: 教授会 | I25: 入試委員会 | N25: 学生・キャリアサポート
I27: 教務委員会
E29: 自己点検・評価委員会 | I29: 学生委員会
E31: 広報委員会 | I31: キャリアサポート委員会
E33: 人権・倫理委員会 | I33: FD委員会
E35: SD委員会
E37: 衛生委員会
C39: 附属施設
E41: メディアセンター（図書館） | I41: メディアセンター委員会
E43: 北近畿地域連携センター | I43: 北近畿地域連携センター委員会
E45: 市民学習・キャリア支援センター | I45: 市民学習・キャリア支援センター委員会
I47: 国際交流センター委員会
